Workbook

Sheet Hitters
H1: 1.2 | I1: 2 | J1: 1 | K1: 1.2 | L1: 1.6 | M1: 1 | N1: 0.2 | O1: 0.1 | W1: 1 | X1: 1 | Y1: 1 | Z1: 1 | AB1: 0.8 | AC1: 0.2 | AD1: 1 | AE1: 0.1 | AF1: 0.1 | AG1: 0.1 | AI1: (-2*10^-6)*A1^3+0.00032*A1^2-0.0021*A1
X2: 0.2 | Y2: 0.5 | Z2: 0.3 | AA2: 1
H3: 2.5 | M3: 0.6 | W3: 2 | AB3: 1 | AD3: 0.6 | AI3: 2.5 | AJ3: 0.6 | AK3: 2 | AL3: 1 | AM3: 0.6
H5: 100 | I5: 100 | J5: 100 | K5: 100 | L5: 100 | M5: 100 | N5: 100 | O5: 100 | P5: 100 | W5: 100 | X5: 100 | Y5: 100 | Z5: 100 | AA5: 100 | AB5: 100 | AC5: 100 | AD5: 100 | AE5: 100 | AF5: 100 | AG5: 100 | AI5: =H$1*((-0.000002)*H5^3+0.00032*H5^2+(-0.0021)*H5)+I$1*((-0.000002)*I5^3+0.00032*I5^2+(-0.0021)*I5)+J$1*((-0.000002)*J5^3+0.00032*J5^2+(-0.0021)*J5)+K$1*((-0.000002)*K5^3+0.00032*K5^2+(-0.0021)*K5)+L$1*((-0.000002)*L5^3+0.00032*L5^2+(-0.0021)*L5) -> 6.93 | AJ5: =M$1*((-0.000002)*M5^3+0.00032*M5^2+(-0.0021)*M5)+N$1*((-0.000002)*N5^3+0.00032*N5^2+(-0.0021)*N5)+O$1*((-0.000002)*O5^3+0.00032*O5^2+(-0.0021)*O5) -> 1.287 | AK5: =IF(AA5>50,W$1*((-0.000002)*W5^3+0.00032*W5^2+(-0.0021)*W5)+X$1*((-0.000002)*X5^3+0.00032*X5^2+(-0.0021)*X5)+Y$1*((-0.000002)*Y5^3+0.00032*Y5^2+(-0.0021)*Y5)+Z$1*((-0.000002)*Z5^3+0.00032*Z5^2+(-0.0021)*Z5),X$2*((-0.000002)*X5^3+0.00032*X5^2+(-0.0021)*X5)+Y$2*((-0.000002)*Y5^3+0.00032*Y5^2+(-0.0021)*Y5)+Z$2*((-0.000002)*Z5^3+0.00032*Z5^2+(-0.0021)*Z5)+AA$2*((-0.000002)*AA5^3+0.00032*AA5^2+(-0.0021)*AA5)) -> 3.96 | AL5: =AB$1*((-0.000002)*AB5^3+0.00032*AB5^2+(-0.0021)*AB5)+AC$1*((-0.000002)*AC5^3+0.00032*AC5^2+(-0.0021)*AC5) -> 0.99 | AM5: =AD$1*((-0.000002)*AD5^3+0.00032*AD5^2+(-0.0021)*AD5)+AE$1*((-0.000002)*AE5^3+0.00032*AE5^2+(-0.0021)*AE5)+AF$1*((-0.000002)*AF5^3+0.00032*AF5^2+(-0.0021)*AF5)+AG$1*((-0.000002)*AG5^3+0.00032*AG5^2+(-0.0021)*AG5) -> 1.287
A6: Overall Projection | B6: Rnk | C6: Player | D6: Pos | E6: B | F6: T | G6: Age | H6: Contact | I6: Power | J6: vs L | K6: vs R | L6: Batting Eye | M6: Baserunning | N6: Bunt | O6: Push/Pull | P6: Overall | Q6: Rank | R6: Player | S6: Pos | T6: B | U6: T | V6: Age | W6: Range | X6: Glove | Y6: Arm Strength | Z6: Arm Accuracy | AA6: Pitch Calling | AB6: Durability | AC6: Health | AD6: Speed | AE6: Patience | AF6: Temper | AG6: Makeup | AH6: Overall | AI6: hitting | AJ6: baserunning | AK6: fielding | AL6: durability | AM6: intangibles
A7: =IFERROR((AI7*AI$3+AJ7*AJ$3+AK7*AK$3+AL7*AL$3+AM7*AM$3)*100/(AI$5*AI$3+AJ$5*AJ$3+AK$5*AK$3+AL$5*AL$3+AM$5*AM$3),0) -> 75.250027 | B7: 1 | C7: Lozada, Marshall | D7: 3B | E7: R | F7: R | G7: 18 | H7: 88 | I7: 52 | J7: 61 | K7: 77 | L7: 72 | M7: 88 | N7: 42 | O7: 62 | P7: 88 | Q7: 1 | R7: Lozada, Marshall | S7: 3B | T7: R | U7: R | V7: 18 | W7: 63 | X7: 66 | Y7: 100 | Z7: 87 | AA7: 0 | AB7: 92 | AC7: 100 | AD7: 89 | AE7: 42 | AF7: 46 | AG7: 64 | AH7: 88 | AI7: =H$1*((-0.000002)*H7^3+0.00032*H7^2+(-0.0021)*H7)+I$1*((-0.000002)*I7^3+0.00032*I7^2+(-0.0021)*I7)+J$1*((-0.000002)*J7^3+0.00032*J7^2+(-0.0021)*J7)+K$1*((-0.000002)*K7^3+0.00032*K7^2+(-0.0021)*K7)+L$1*((-0.000002)*L7^3+0.00032*L7^2+(-0.0021)*L7) -> 4.8797004 | AJ7: =M$1*((-0.000002)*M7^3+0.00032*M7^2+(-0.0021)*M7)+N$1*((-0.000002)*N7^3+0.00032*N7^2+(-0.0021)*N7)+O$1*((-0.000002)*O7^3+0.00032*O7^2+(-0.0021)*O7) -> 1.0582792 | AK7: =IF(AA7<50,W$1*((-0.000002)*W7^3+0.00032*W7^2+(-0.0021)*W7)+X$1*((-0.000002)*X7^3+0.00032*X7^2+(-0.0021)*X7)+Y$1*((-0.000002)*Y7^3+0.00032*Y7^2+(-0.0021)*Y7)+Z$1*((-0.000002)*Z7^3+0.00032*Z7^2+(-0.0021)*Z7),X$2*((-0.000002)*X7^3+0.00032*X7^2+(-0.0021)*X7)+Y$2*((-0.000002)*Y7^3+0.00032*Y7^2+(-0.0021)*Y7)+Z$2*((-0.000002)*Z7^3+0.00032*Z7^2+(-0.0021)*Z7)+AA$2*((-0.000002)*AA7^3+0.00032*AA7^2+(-0.0021)*AA7)) -> 3.230388 | AL7: =AB$1*((-0.000002)*AB7^3+0.00032*AB7^2+(-0.0021)*AB7)+AC$1*((-0.000002)*AC7^3+0.00032*AC7^2+(-0.0021)*AC7) -> 0.9643232 | AM7: =AD$1*((-0.000002)*AD7^3+0.00032*AD7^2+(-0.0021)*AD7)+AE$1*((-0.000002)*AE7^3+0.00032*AE7^2+(-0.0021)*AE7)+AF$1*((-0.000002)*AF7^3+0.00032*AF7^2+(-0.0021)*AF7)+AG$1*((-0.000002)*AG7^3+0.00032*AG7^2+(-0.0021)*AG7) -> 1.0744804
A8: =IFERROR((AI8*AI$3+AJ8*AJ$3+AK8*AK$3+AL8*AL$3+AM8*AM$3)*100/(AI$5*AI$3+AJ$5*AJ$3+AK$5*AK$3+AL$5*AL$3+AM$5*AM$3),0) -> 83.537811 | B8: 2 | C8: Romero, Jerome | D8: SS | E8: R | F8: R | G8: 18 | H8: 82 | I8: 86 | J8: 84 | K8: 45 | L8: 82 | M8: 62 | N8: 47 | O8: 73 | P8: 89 | Q8: 2 | R8: Romero, Jerome | S8: SS | T8: R | U8: R | V8: 18 | W8: 95 | X8: 100 | Y8: 77 | Z8: 74 | AA8: 4 | AB8: 78 | AC8: 62 | AD8: 100 | AE8: 75 | AF8: 63 | AG8: 98 | AH8: 89 | AI8: =H$1*((-0.000002)*H8^3+0.00032*H8^2+(-0.0021)*H8)+I$1*((-0.000002)*I8^3+0.00032*I8^2+(-0.0021)*I8)+J$1*((-0.000002)*J8^3+0.00032*J8^2+(-0.0021)*J8)+K$1*((-0.000002)*K8^3+0.00032*K8^2+(-0.0021)*K8)+L$1*((-0.000002)*L8^3+0.00032*L8^2+(-0.0021)*L8) -> 5.6245112 | AJ8: =M$1*((-0.000002)*M8^3+0.00032*M8^2+(-0.0021)*M8)+N$1*((-0.000002)*N8^3+0.00032*N8^2+(-0.0021)*N8)+O$1*((-0.000002)*O8^3+0.00032*O8^2+(-0.0021)*O8) -> 0.7807254 | AK8: =IF(AA8<50,W$1*((-0.000002)*W8^3+0.00032*W8^2+(-0.0021)*W8)+X$1*((-0.000002)*X8^3+0.00032*X8^2+(-0.0021)*X8)+Y$1*((-0.000002)*Y8^3+0.00032*Y8^2+(-0.0021)*Y8)+Z$1*((-0.000002)*Z8^3+0.00032*Z8^2+(-0.0021)*Z8),X$2*((-0.000002)*X8^3+0.00032*X8^2+(-0.0021)*X8)+Y$2*((-0.000002)*Y8^3+0.00032*Y8^2+(-0.0021)*Y8)+Z$2*((-0.000002)*Z8^3+0.00032*Z8^2+(-0.0021)*Z8)+AA$2*((-0.000002)*AA8^3+0.00032*AA8^2+(-0.0021)*AA8)) -> 3.572736 | AL8: =AB$1*((-0.000002)*AB8^3+0.00032*AB8^2+(-0.0021)*AB8)+AC$1*((-0.000002)*AC8^3+0.00032*AC8^2+(-0.0021)*AC8) -> 0.7918256 | AM8: =AD$1*((-0.000002)*AD8^3+0.00032*AD8^2+(-0.0021)*AD8)+AE$1*((-0.000002)*AE8^3+0.00032*AE8^2+(-0.0021)*AE8)+AF$1*((-0.000002)*AF8^3+0.00032*AF8^2+(-0.0021)*AF8)+AG$1*((-0.000002)*AG8^3+0.00032*AG8^2+(-0.0021)*AG8) -> 1.2321532
A9: =IFERROR((AI9*AI$3+AJ9*AJ$3+AK9*AK$3+AL9*AL$3+AM9*AM$3)*100/(AI$5*AI$3+AJ$5*AJ$3+AK$5*AK$3+AL$5*AL$3+AM$5*AM$3),0) -> 69.832543 | B9: 3 | C9: Cunnane, John | D9: RF | E9: R | F9: R | G9: 18 | H9: 99 | I9: 92 | J9: 55 | K9: 40 | L9: 77 | M9: 43 | N9: 52 | O9: 33 | P9: 81 | Q9: 3 | R9: Cunnane, John | S9: RF | T9: R | U9: R | V9: 18 | W9: 55 | X9: 50 | Y9: 61 | Z9: 67 | AA9: 0 | AB9: 92 | AC9: 86 | AD9: 51 | AE9: 37 | AF9: 88 | AG9: 78 | AH9: 81 | AI9: =H$1*((-0.000002)*H9^3+0.00032*H9^2+(-0.0021)*H9)+I$1*((-0.000002)*I9^3+0.00032*I9^2+(-0.0021)*I9)+J$1*((-0.000002)*J9^3+0.00032*J9^2+(-0.0021)*J9)+K$1*((-0.000002)*K9^3+0.00032*K9^2+(-0.0021)*K9)+L$1*((-0.000002)*L9^3+0.00032*L9^2+(-0.0021)*L9) -> 5.2969668 | AJ9: =M$1*((-0.000002)*M9^3+0.00032*M9^2+(-0.0021)*M9)+N$1*((-0.000002)*N9^3+0.00032*N9^2+(-0.0021)*N9)+O$1*((-0.000002)*O9^3+0.00032*O9^2+(-0.0021)*O9) -> 0.4580694 | AK9: =IF(AA9<50,W$1*((-0.000002)*W9^3+0.00032*W9^2+(-0.0021)*W9)+X$1*((-0.000002)*X9^3+0.00032*X9^2+(-0.0021)*X9)+Y$1*((-0.000002)*Y9^3+0.00032*Y9^2+(-0.0021)*Y9)+Z$1*((-0.000002)*Z9^3+0.00032*Z9^2+(-0.0021)*Z9),X$2*((-0.000002)*X9^3+0.00032*X9^2+(-0.0021)*X9)+Y$2*((-0.000002)*Y9^3+0.00032*Y9^2+(-0.0021)*Y9)+Z$2*((-0.000002)*Z9^3+0.00032*Z9^2+(-0.0021)*Z9)+AA$2*((-0.000002)*AA9^3+0.00032*AA9^2+(-0.0021)*AA9)) -> 2.267662 | AL9: =AB$1*((-0.000002)*AB9^3+0.00032*AB9^2+(-0.0021)*AB9)+AC$1*((-0.000002)*AC9^3+0.00032*AC9^2+(-0.0021)*AC9) -> 0.9491248 | AM9: =AD$1*((-0.000002)*AD9^3+0.00032*AD9^2+(-0.0021)*AD9)+AE$1*((-0.000002)*AE9^3+0.00032*AE9^2+(-0.0021)*AE9)+AF$1*((-0.000002)*AF9^3+0.00032*AF9^2+(-0.0021)*AF9)+AG$1*((-0.000002)*AG9^3+0.00032*AG9^2+(-0.0021)*AG9) -> 0.6622566
A10: =IFERROR((AI10*AI$3+AJ10*AJ$3+AK10*AK$3+AL10*AL$3+AM10*AM$3)*100/(AI$5*AI$3+AJ$5*AJ$3+AK$5*AK$3+AL$5*AL$3+AM$5*AM$3),0) -> 67.417684 | B10: 5 | C10: Bailey, Alexander | D10: 1B | E10: R | F10: R | G10: 18 | H10: 59 | I10: 76 | J10: 66 | K10: 75 | L10: 71 | M10: 51 | N10: 44 | O10: 39 | P10: 74 | Q10: 5 | R10: Bailey, Alexander | S10: 1B | T10: R | U10: R | V10: 18 | W10: 69 | X10: 79 | Y10: 32 | Z10: 42 | AA10: 14 | AB10: 80 | AC10: 67 | AD10: 61 | AE10: 60 | AF10: 90 | AG10: 78 | AH10: 74 | AI10: =H$1*((-0.000002)*H10^3+0.00032*H10^2+(-0.0021)*H10)+I$1*((-0.000002)*I10^3+0.00032*I10^2+(-0.0021)*I10)+J$1*((-0.000002)*J10^3+0.00032*J10^2+(-0.0021)*J10)+K$1*((-0.000002)*K10^3+0.00032*K10^2+(-0.0021)*K10)+L$1*((-0.000002)*L10^3+0.00032*L10^2+(-0.0021)*L10) -> 5.1525952 | AJ10: =M$1*((-0.000002)*M10^3+0.00032*M10^2+(-0.0021)*M10)+N$1*((-0.000002)*N10^3+0.00032*N10^2+(-0.0021)*N10)+O$1*((-0.000002)*O10^3+0.00032*O10^2+(-0.0021)*O10) -> 0.5598866 | AK10: =IF(AA10<50,W$1*((-0.000002)*W10^3+0.00032*W10^2+(-0.0021)*W10)+X$1*((-0.000002)*X10^3+0.00032*X10^2+(-0.0021)*X10)+Y$1*((-0.000002)*Y10^3+0.00032*Y10^2+(-0.0021)*Y10)+Z$1*((-0.000002)*Z10^3+0.00032*Z10^2+(-0.0021)*Z10),X$2*((-0.000002)*X10^3+0.00032*X10^2+(-0.0021)*X10)+Y$2*((-0.000002)*Y10^3+0.00032*Y10^2+(-0.0021)*Y10)+Z$2*((-0.000002)*Z10^3+0.00032*Z10^2+(-0.0021)*Z10)+AA$2*((-0.000002)*AA10^3+0.00032*AA10^2+(-0.0021)*AA10)) -> 2.089792 | AL10: =AB$1*((-0.000002)*AB10^3+0.00032*AB10^2+(-0.0021)*AB10)+AC$1*((-0.000002)*AC10^3+0.00032*AC10^2+(-0.0021)*AC10) -> 0.8236508 | AM10: =AD$1*((-0.000002)*AD10^3+0.00032*AD10^2+(-0.0021)*AD10)+AE$1*((-0.000002)*AE10^3+0.00032*AE10^2+(-0.0021)*AE10)+AF$1*((-0.000002)*AF10^3+0.00032*AF10^2+(-0.0021)*AF10)+AG$1*((-0.000002)*AG10^3+0.00032*AG10^2+(-0.0021)*AG10) -> 0.8459556
A11: =IFERROR((AI11*AI$3+AJ11*AJ$3+AK11*AK$3+AL11*AL$3+AM11*AM$3)*100/(AI$5*AI$3+AJ$5*AJ$3+AK$5*AK$3+AL$5*AL$3+AM$5*AM$3),0) -> 74.307689 | B11: 7 | C11: Patrick, Alex | D11: 3B | E11: R | F11: R | G11: 18 | H11: 37 | I11: 95 | J11: 80 | K11: 68 | L11: 78 | M11: 40 | N11: 45 | O11: 36 | P11: 80 | Q11: 7 | R11: Patrick, Alex | S11: 3B | T11: R | U11: R | V11: 18 | W11: 60 | X11: 58 | Y11: 94 | Z11: 74 | AA11: 34 | AB11: 78 | AC11: 100 | AD11: 60 | AE11: 67 | AF11: 32 | AG11: 85 | AH11: 80 | AI11: =H$1*((-0.000002)*H11^3+0.00032*H11^2+(-0.0021)*H11)+I$1*((-0.000002)*I11^3+0.00032*I11^2+(-0.0021)*I11)+J$1*((-0.000002)*J11^3+0.00032*J11^2+(-0.0021)*J11)+K$1*((-0.000002)*K11^3+0.00032*K11^2+(-0.0021)*K11)+L$1*((-0.000002)*L11^3+0.00032*L11^2+(-0.0021)*L11) -> 5.2983696 | AJ11: =M$1*((-0.000002)*M11^3+0.00032*M11^2+(-0.0021)*M11)+N$1*((-0.000002)*N11^3+0.00032*N11^2+(-0.0021)*N11)+O$1*((-0.000002)*O11^3+0.00032*O11^2+(-0.0021)*O11) -> 0.3988308 | AK11: =IF(AA11<50,W$1*((-0.000002)*W11^3+0.00032*W11^2+(-0.0021)*W11)+X$1*((-0.000002)*X11^3+0.00032*X11^2+(-0.0021)*X11)+Y$1*((-0.000002)*Y11^3+0.00032*Y11^2+(-0.0021)*Y11)+Z$1*((-0.000002)*Z11^3+0.00032*Z11^2+(-0.0021)*Z11),X$2*((-0.000002)*X11^3+0.00032*X11^2+(-0.0021)*X11)+Y$2*((-0.000002)*Y11^3+0.00032*Y11^2+(-0.0021)*Y11)+Z$2*((-0.000002)*Z11^3+0.00032*Z11^2+(-0.0021)*Z11)+AA$2*((-0.000002)*AA11^3+0.00032*AA11^2+(-0.0021)*AA11)) -> 2.91388 | AL11: =AB$1*((-0.000002)*AB11^3+0.00032*AB11^2+(-0.0021)*AB11)+AC$1*((-0.000002)*AC11^3+0.00032*AC11^2+(-0.0021)*AC11) -> 0.8651808 | AM11: =AD$1*((-0.000002)*AD11^3+0.00032*AD11^2+(-0.0021)*AD11)+AE$1*((-0.000002)*AE11^3+0.00032*AE11^2+(-0.0021)*AE11)+AF$1*((-0.000002)*AF11^3+0.00032*AF11^2+(-0.0021)*AF11)+AG$1*((-0.000002)*AG11^3+0.00032*AG11^2+(-0.0021)*AG11) -> 0.7734448
A12: =IFERROR((AI12*AI$3+AJ12*AJ$3+AK12*AK$3+AL12*AL$3+AM12*AM$3)*100/(AI$5*AI$3+AJ$5*AJ$3+AK$5*AK$3+AL$5*AL$3+AM$5*AM$3),0) -> 63.931151 | B12: 11 | C12: Sanchez, Angel | D12: LF | E12: S | F12: L | G12: 18 | H12: 77 | I12: 77 | J12: 61 | K12: 71 | L12: 62 | M12: 21 | N12: 0 | O12: 26 | P12: 73 | Q12: 11 | R12: Sanchez, Angel | S12: LF | T12: S | U12: L | V12: 18 | W12: 53 | X12: 47 | Y12: 46 | Z12: 56 | AA12: 14 | AB12: 91 | AC12: 100 | AD12: 43 | AE12: 81 | AF12: 23 | AG12: 44 | AH12: 73 | AI12: =H$1*((-0.000002)*H12^3+0.00032*H12^2+(-0.0021)*H12)+I$1*((-0.000002)*I12^3+0.00032*I12^2+(-0.0021)*I12)+J$1*((-0.000002)*J12^3+0.00032*J12^2+(-0.0021)*J12)+K$1*((-0.000002)*K12^3+0.00032*K12^2+(-0.0021)*K12)+L$1*((-0.000002)*L12^3+0.00032*L12^2+(-0.0021)*L12) -> 5.1356988 | AJ12: =M$1*((-0.000002)*M12^3+0.00032*M12^2+(-0.0021)*M12)+N$1*((-0.000002)*N12^3+0.00032*N12^2+(-0.0021)*N12)+O$1*((-0.000002)*O12^3+0.00032*O12^2+(-0.0021)*O12) -> 0.0911548 | AK12: =IF(AA12<50,W$1*((-0.000002)*W12^3+0.00032*W12^2+(-0.0021)*W12)+X$1*((-0.000002)*X12^3+0.00032*X12^2+(-0.0021)*X12)+Y$1*((-0.000002)*Y12^3+0.00032*Y12^2+(-0.0021)*Y12)+Z$1*((-0.000002)*Z12^3+0.00032*Z12^2+(-0.0021)*Z12),X$2*((-0.000002)*X12^3+0.00032*X12^2+(-0.0021)*X12)+Y$2*((-0.000002)*Y12^3+0.00032*Y12^2+(-0.0021)*Y12)+Z$2*((-0.000002)*Z12^3+0.00032*Z12^2+(-0.0021)*Z12)+AA$2*((-0.000002)*AA12^3+0.00032*AA12^2+(-0.0021)*AA12)) -> 1.810896 | AL12: =AB$1*((-0.000002)*AB12^3+0.00032*AB12^2+(-0.0021)*AB12)+AC$1*((-0.000002)*AC12^3+0.00032*AC12^2+(-0.0021)*AC12) -> 0.9593424 | AM12: =AD$1*((-0.000002)*AD12^3+0.00032*AD12^2+(-0.0021)*AD12)+AE$1*((-0.000002)*AE12^3+0.00032*AE12^2+(-0.0021)*AE12)+AF$1*((-0.000002)*AF12^3+0.00032*AF12^2+(-0.0021)*AF12)+AG$1*((-0.000002)*AG12^3+0.00032*AG12^2+(-0.0021)*AG12) -> 0.4743596
A13: =IFERROR((AI13*AI$3+AJ13*AJ$3+AK13*AK$3+AL13*AL$3+AM13*AM$3)*100/(AI$5*AI$3+AJ$5*AJ$3+AK$5*AK$3+AL$5*AL$3+AM$5*AM$3),0) -> 62.680297 | B13: 12 | C13: Arguelles, Arquimedes | D13: 2B | E13: R | F13: R | G13: 18 | H13: 93 | I13: 28 | J13: 44 | K13: 59 | L13: 59 | M13: 74 | N13: 77 | O13: 45 | P13: 80 | Q13: 12 | R13: Arguelles, Arquimedes | S13: 2B | T13: R | U13: R | V13: 18 | W13: 100 | X13: 83 | Y13: 60 | Z13: 80 | AA13: 21 | AB13: 85 | AC13: 100 | AD13: 95 | AE13: 82 | AF13: 0 | AG13: 52 | AH13: 80 | AI13: =H$1*((-0.000002)*H13^3+0.00032*H13^2+(-0.0021)*H13)+I$1*((-0.000002)*I13^3+0.00032*I13^2+(-0.0021)*I13)+J$1*((-0.000002)*J13^3+0.00032*J13^2+(-0.0021)*J13)+K$1*((-0.000002)*K13^3+0.00032*K13^2+(-0.0021)*K13)+L$1*((-0.000002)*L13^3+0.00032*L13^2+(-0.0021)*L13) -> 3.4314368 | AJ13: =M$1*((-0.000002)*M13^3+0.00032*M13^2+(-0.0021)*M13)+N$1*((-0.000002)*N13^3+0.00032*N13^2+(-0.0021)*N13)+O$1*((-0.000002)*O13^3+0.00032*O13^2+(-0.0021)*O13) -> 0.9880998 | AK13: =IF(AA13<50,W$1*((-0.000002)*W13^3+0.00032*W13^2+(-0.0021)*W13)+X$1*((-0.000002)*X13^3+0.00032*X13^2+(-0.0021)*X13)+Y$1*((-0.000002)*Y13^3+0.00032*Y13^2+(-0.0021)*Y13)+Z$1*((-0.000002)*Z13^3+0.00032*Z13^2+(-0.0021)*Z13),X$2*((-0.000002)*X13^3+0.00032*X13^2+(-0.0021)*X13)+Y$2*((-0.000002)*Y13^3+0.00032*Y13^2+(-0.0021)*Y13)+Z$2*((-0.000002)*Z13^3+0.00032*Z13^2+(-0.0021)*Z13)+AA$2*((-0.000002)*AA13^3+0.00032*AA13^2+(-0.0021)*AA13)) -> 3.326606 | AL13: =AB$1*((-0.000002)*AB13^3+0.00032*AB13^2+(-0.0021)*AB13)+AC$1*((-0.000002)*AC13^3+0.00032*AC13^2+(-0.0021)*AC13) -> 0.9222 | AM13: =AD$1*((-0.000002)*AD13^3+0.00032*AD13^2+(-0.0021)*AD13)+AE$1*((-0.000002)*AE13^3+0.00032*AE13^2+(-0.0021)*AE13)+AF$1*((-0.000002)*AF13^3+0.00032*AF13^2+(-0.0021)*AF13)+AG$1*((-0.000002)*AG13^3+0.00032*AG13^2+(-0.0021)*AG13) -> 1.1089108
A14: =IFERROR((AI14*AI$3+AJ14*AJ$3+AK14*AK$3+AL14*AL$3+AM14*AM$3)*100/(AI$5*AI$3+AJ$5*AJ$3+AK$5*AK$3+AL$5*AL$3+AM$5*AM$3),0) -> 68.597196 | B14: 14 | C14: Finnegan, Johermyn | D14: SS | E14: L | F14: R | G14: 18 | H14: 73 | I14: 51 | J14: 33 | K14: 67 | L14: 60 | M14: 72 | N14: 42 | O14: 47 | P14: 73 | Q14: 14 | R14: Finnegan, Johermyn | S14: SS | T14: L | U14: R | V14: 18 | W14: 89 | X14: 100 | Y14: 100 | Z14: 86 | AA14: 2 | AB14: 74 | AC14: 85 | AD14: 57 | AE14: 66 | AF14: 87 | AG14: 62 | AH14: 73 | AI14: =H$1*((-0.000002)*H14^3+0.00032*H14^2+(-0.0021)*H14)+I$1*((-0.000002)*I14^3+0.00032*I14^2+(-0.0021)*I14)+J$1*((-0.000002)*J14^3+0.00032*J14^2+(-0.0021)*J14)+K$1*((-0.000002)*K14^3+0.00032*K14^2+(-0.0021)*K14)+L$1*((-0.000002)*L14^3+0.00032*L14^2+(-0.0021)*L14) -> 3.839382 | AJ14: =M$1*((-0.000002)*M14^3+0.00032*M14^2+(-0.0021)*M14)+N$1*((-0.000002)*N14^3+0.00032*N14^2+(-0.0021)*N14)+O$1*((-0.000002)*O14^3+0.00032*O14^2+(-0.0021)*O14) -> 0.8668582 | AK14: =IF(AA14<50,W$1*((-0.000002)*W14^3+0.00032*W14^2+(-0.0021)*W14)+X$1*((-0.000002)*X14^3+0.00032*X14^2+(-0.0021)*X14)+Y$1*((-0.000002)*Y14^3+0.00032*Y14^2+(-0.0021)*Y14)+Z$1*((-0.000002)*Z14^3+0.00032*Z14^2+(-0.0021)*Z14),X$2*((-0.000002)*X14^3+0.00032*X14^2+(-0.0021)*X14)+Y$2*((-0.000002)*Y14^3+0.00032*Y14^2+(-0.0021)*Y14)+Z$2*((-0.000002)*Z14^3+0.00032*Z14^2+(-0.0021)*Z14)+AA$2*((-0.000002)*AA14^3+0.00032*AA14^2+(-0.0021)*AA14)) -> 3.83189 | AL14: =AB$1*((-0.000002)*AB14^3+0.00032*AB14^2+(-0.0021)*AB14)+AC$1*((-0.000002)*AC14^3+0.00032*AC14^2+(-0.0021)*AC14) -> 0.8102276 | AM14: =AD$1*((-0.000002)*AD14^3+0.00032*AD14^2+(-0.0021)*AD14)+AE$1*((-0.000002)*AE14^3+0.00032*AE14^2+(-0.0021)*AE14)+AF$1*((-0.000002)*AF14^3+0.00032*AF14^2+(-0.0021)*AF14)+AG$1*((-0.000002)*AG14^3+0.00032*AG14^2+(-0.0021)*AG14) -> 0.7721866
A15: =IFERROR((AI15*AI$3+AJ15*AJ$3+AK15*AK$3+AL15*AL$3+AM15*AM$3)*100/(AI$5*AI$3+AJ$5*AJ$3+AK$5*AK$3+AL$5*AL$3+AM$5*AM$3),0) -> 60.439092 | B15: 17 | C15: Nieves, Julio | D15: LF | E15: L | F15: L | G15: 18 | H15: 89 | I15: 56 | J15: 56 | K15: 58 | L15: 57 | M15: 95 | N15: 32 | O15: 31 | P15: 74 | Q15: 17 | R15: Nieves, Julio | S15: LF | T15: L | U15: L | V15: 18 | W15: 61 | X15: 50 | Y15: 48 | Z15: 58 | AA15: 11 | AB15: 84 | AC15: 89 | AD15: 63 | AE15: 56 | AF15: 62 | AG15: 56 | AH15: 74 | AI15: =H$1*((-0.000002)*H15^3+0.00032*H15^2+(-0.0021)*H15)+I$1*((-0.000002)*I15^3+0.00032*I15^2+(-0.0021)*I15)+J$1*((-0.000002)*J15^3+0.00032*J15^2+(-0.0021)*J15)+K$1*((-0.000002)*K15^3+0.00032*K15^2+(-0.0021)*K15)+L$1*((-0.000002)*L15^3+0.00032*L15^2+(-0.0021)*L15) -> 4.28622 | AJ15: =M$1*((-0.000002)*M15^3+0.00032*M15^2+(-0.0021)*M15)+N$1*((-0.000002)*N15^3+0.00032*N15^2+(-0.0021)*N15)+O$1*((-0.000002)*O15^3+0.00032*O15^2+(-0.0021)*O15) -> 1.0310226 | AK15: =IF(AA15<50,W$1*((-0.000002)*W15^3+0.00032*W15^2+(-0.0021)*W15)+X$1*((-0.000002)*X15^3+0.00032*X15^2+(-0.0021)*X15)+Y$1*((-0.000002)*Y15^3+0.00032*Y15^2+(-0.0021)*Y15)+Z$1*((-0.000002)*Z15^3+0.00032*Z15^2+(-0.0021)*Z15),X$2*((-0.000002)*X15^3+0.00032*X15^2+(-0.0021)*X15)+Y$2*((-0.000002)*Y15^3+0.00032*Y15^2+(-0.0021)*Y15)+Z$2*((-0.000002)*Z15^3+0.00032*Z15^2+(-0.0021)*Z15)+AA$2*((-0.000002)*AA15^3+0.00032*AA15^2+(-0.0021)*AA15)) -> 2.03341 | AL15: =AB$1*((-0.000002)*AB15^3+0.00032*AB15^2+(-0.0021)*AB15)+AC$1*((-0.000002)*AC15^3+0.00032*AC15^2+(-0.0021)*AC15) -> 0.904466 | AM15: =AD$1*((-0.000002)*AD15^3+0.00032*AD15^2+(-0.0021)*AD15)+AE$1*((-0.000002)*AE15^3+0.00032*AE15^2+(-0.0021)*AE15)+AF$1*((-0.000002)*AF15^3+0.00032*AF15^2+(-0.0021)*AF15)+AG$1*((-0.000002)*AG15^3+0.00032*AG15^2+(-0.0021)*AG15) -> 0.806946
A16: =IFERROR((AI16*AI$3+AJ16*AJ$3+AK16*AK$3+AL16*AL$3+AM16*AM$3)*100/(AI$5*AI$3+AJ$5*AJ$3+AK$5*AK$3+AL$5*AL$3+AM$5*AM$3),0) -> 66.857347 | B16: 18 | C16: Cruz, Yamid | D16: 2B | E16: R | F16: R | G16: 18 | H16: 26 | I16: 100 | J16: 60 | K16: 66 | L16: 76 | M16: 42 | N16: 31 | O16: 44 | P16: 61 | Q16: 18 | R16: Cruz, Yamid | S16: 2B | T16: R | U16: R | V16: 18 | W16: 64 | X16: 64 | Y16: 66 | Z16: 70 | AA16: 18 | AB16: 56 | AC16: 97 | AD16: 26 | AE16: 65 | AF16: 66 | AG16: 35 | AH16: 61 | AI16: =H$1*((-0.000002)*H16^3+0.00032*H16^2+(-0.0021)*H16)+I$1*((-0.000002)*I16^3+0.00032*I16^2+(-0.0021)*I16)+J$1*((-0.000002)*J16^3+0.00032*J16^2+(-0.0021)*J16)+K$1*((-0.000002)*K16^3+0.00032*K16^2+(-0.0021)*K16)+L$1*((-0.000002)*L16^3+0.00032*L16^2+(-0.0021)*L16) -> 4.839504 | AJ16: =M$1*((-0.000002)*M16^3+0.00032*M16^2+(-0.0021)*M16)+N$1*((-0.000002)*N16^3+0.00032*N16^2+(-0.0021)*N16)+O$1*((-0.000002)*O16^3+0.00032*O16^2+(-0.0021)*O16) -> 0.4003468 | AK16: =IF(AA16<50,W$1*((-0.000002)*W16^3+0.00032*W16^2+(-0.0021)*W16)+X$1*((-0.000002)*X16^3+0.00032*X16^2+(-0.0021)*X16)+Y$1*((-0.000002)*Y16^3+0.00032*Y16^2+(-0.0021)*Y16)+Z$1*((-0.000002)*Z16^3+0.00032*Z16^2+(-0.0021)*Z16),X$2*((-0.000002)*X16^3+0.00032*X16^2+(-0.0021)*X16)+Y$2*((-0.000002)*Y16^3+0.00032*Y16^2+(-0.0021)*Y16)+Z$2*((-0.000002)*Z16^3+0.00032*Z16^2+(-0.0021)*Z16)+AA$2*((-0.000002)*AA16^3+0.00032*AA16^2+(-0.0021)*AA16)) -> 2.719392 | AL16: =AB$1*((-0.000002)*AB16^3+0.00032*AB16^2+(-0.0021)*AB16)+AC$1*((-0.000002)*AC16^3+0.00032*AC16^2+(-0.0021)*AC16) -> 0.6241172 | AM16: =AD$1*((-0.000002)*AD16^3+0.00032*AD16^2+(-0.0021)*AD16)+AE$1*((-0.000002)*AE16^3+0.00032*AE16^2+(-0.0021)*AE16)+AF$1*((-0.000002)*AF16^3+0.00032*AF16^2+(-0.0021)*AF16)+AG$1*((-0.000002)*AG16^3+0.00032*AG16^2+(-0.0021)*AG16) -> 0.2845008
A17: =IFERROR((AI17*AI$3+AJ17*AJ$3+AK17*AK$3+AL17*AL$3+AM17*AM$3)*100/(AI$5*AI$3+AJ$5*AJ$3+AK$5*AK$3+AL$5*AL$3+AM$5*AM$3),0) -> 73.006889 | B17: 19 | C17: Duchscherer, Bobby Joe | D17: 2B | E17: R | F17: R | G17: 18 | H17: 85 | I17: 73 | J17: 75 | K17: 62 | L17: 64 | M17: 79 | N17: 76 | O17: 48 | P17: 85 | Q17: 19 | R17: Duchscherer, Bobby Joe | S17: 2B | T17: R | U17: R | V17: 18 | W17: 83 | X17: 60 | Y17: 51 | Z17: 59 | AA17: 30 | AB17: 84 | AC17: 82 | AD17: 87 | AE17: 62 | AF17: 32 | AG17: 91 | AH17: 85 | AI17: =H$1*((-0.000002)*H17^3+0.00032*H17^2+(-0.0021)*H17)+I$1*((-0.000002)*I17^3+0.00032*I17^2+(-0.0021)*I17)+J$1*((-0.000002)*J17^3+0.00032*J17^2+(-0.0021)*J17)+K$1*((-0.000002)*K17^3+0.00032*K17^2+(-0.0021)*K17)+L$1*((-0.000002)*L17^3+0.00032*L17^2+(-0.0021)*L17) -> 5.224062 | AJ17: =M$1*((-0.000002)*M17^3+0.00032*M17^2+(-0.0021)*M17)+N$1*((-0.000002)*N17^3+0.00032*N17^2+(-0.0021)*N17)+O$1*((-0.000002)*O17^3+0.00032*O17^2+(-0.0021)*O17) -> 1.0488252 | AK17: =IF(AA17<50,W$1*((-0.000002)*W17^3+0.00032*W17^2+(-0.0021)*W17)+X$1*((-0.000002)*X17^3+0.00032*X17^2+(-0.0021)*X17)+Y$1*((-0.000002)*Y17^3+0.00032*Y17^2+(-0.0021)*Y17)+Z$1*((-0.000002)*Z17^3+0.00032*Z17^2+(-0.0021)*Z17),X$2*((-0.000002)*X17^3+0.00032*X17^2+(-0.0021)*X17)+Y$2*((-0.000002)*Y17^3+0.00032*Y17^2+(-0.0021)*Y17)+Z$2*((-0.000002)*Z17^3+0.00032*Z17^2+(-0.0021)*Z17)+AA$2*((-0.000002)*AA17^3+0.00032*AA17^2+(-0.0021)*AA17)) -> 2.519786 | AL17: =AB$1*((-0.000002)*AB17^3+0.00032*AB17^2+(-0.0021)*AB17)+AC$1*((-0.000002)*AC17^3+0.00032*AC17^2+(-0.0021)*AC17) -> 0.8922384 | AM17: =AD$1*((-0.000002)*AD17^3+0.00032*AD17^2+(-0.0021)*AD17)+AE$1*((-0.000002)*AE17^3+0.00032*AE17^2+(-0.0021)*AE17)+AF$1*((-0.000002)*AF17^3+0.00032*AF17^2+(-0.0021)*AF17)+AG$1*((-0.000002)*AG17^3+0.00032*AG17^2+(-0.0021)*AG17) -> 1.0993586
A18: =IFERROR((AI18*AI$3+AJ18*AJ$3+AK18*AK$3+AL18*AL$3+AM18*AM$3)*100/(AI$5*AI$3+AJ$5*AJ$3+AK$5*AK$3+AL$5*AL$3+AM$5*AM$3),0) -> 55.804694 | B18: 22 | C18: Morris, Dillon | D18: SS | E18: S | F18: R | G18: 18 | H18: 55 | I18: 58 | J18: 22 | K18: 41 | L18: 38 | M18: 70 | N18: 23 | O18: 31 | P18: 67 | Q18: 22 | R18: Morris, Dillon | S18: SS | T18: S | U18: R | V18: 18 | W18: 83 | X18: 76 | Y18: 80 | Z18: 86 | AA18: 5 | AB18: 87 | AC18: 78 | AD18: 67 | AE18: 84 | AF18: 85 | AG18: 68 | AH18: 67 | AI18: =H$1*((-0.000002)*H18^3+0.00032*H18^2+(-0.0021)*H18)+I$1*((-0.000002)*I18^3+0.00032*I18^2+(-0.0021)*I18)+J$1*((-0.000002)*J18^3+0.00032*J18^2+(-0.0021)*J18)+K$1*((-0.000002)*K18^3+0.00032*K18^2+(-0.0021)*K18)+L$1*((-0.000002)*L18^3+0.00032*L18^2+(-0.0021)*L18) -> 2.6528272 | AJ18: =M$1*((-0.000002)*M18^3+0.00032*M18^2+(-0.0021)*M18)+N$1*((-0.000002)*N18^3+0.00032*N18^2+(-0.0021)*N18)+O$1*((-0.000002)*O18^3+0.00032*O18^2+(-0.0021)*O18) -> 0.772613 | AK18: =IF(AA18<50,W$1*((-0.000002)*W18^3+0.00032*W18^2+(-0.0021)*W18)+X$1*((-0.000002)*X18^3+0.00032*X18^2+(-0.0021)*X18)+Y$1*((-0.000002)*Y18^3+0.00032*Y18^2+(-0.0021)*Y18)+Z$1*((-0.000002)*Z18^3+0.00032*Z18^2+(-0.0021)*Z18),X$2*((-0.000002)*X18^3+0.00032*X18^2+(-0.0021)*X18)+Y$2*((-0.000002)*Y18^3+0.00032*Y18^2+(-0.0021)*Y18)+Z$2*((-0.000002)*Z18^3+0.00032*Z18^2+(-0.0021)*Z18)+AA$2*((-0.000002)*AA18^3+0.00032*AA18^2+(-0.0021)*AA18)) -> 3.467382 | AL18: =AB$1*((-0.000002)*AB18^3+0.00032*AB18^2+(-0.0021)*AB18)+AC$1*((-0.000002)*AC18^3+0.00032*AC18^2+(-0.0021)*AC18) -> 0.9046944 | AM18: =AD$1*((-0.000002)*AD18^3+0.00032*AD18^2+(-0.0021)*AD18)+AE$1*((-0.000002)*AE18^3+0.00032*AE18^2+(-0.0021)*AE18)+AF$1*((-0.000002)*AF18^3+0.00032*AF18^2+(-0.0021)*AF18)+AG$1*((-0.000002)*AG18^3+0.00032*AG18^2+(-0.0021)*AG18) -> 0.9451918
... A85: =IFERROR((AI85*AI$3+AJ85*AJ$3+AK85*AK$3+AL85*AL$3+AM85*AM$3)*100/(AI$5*AI$3+AJ$5*AJ$3+AK$5*AK$3+AL$5*AL$3+AM$5*AM$3),0) -> 29.107011 | B85: 141 | C85: Harper, Moe | D85: DH | E85: R | F85: R | G85: 21 | H85: 34 | I85: 12 | J85: 46 | K85: 28 | L85: 61 | M85: 21 | N85: 0 | O85: 20 | P85: 42 | Q85: 141 | R85: Harper, Moe | S85: DH | T85: R | U85: R | V85: 21 | W85: 0 | X85: 45 | Y85: 45 | Z85: 51 | AA85: 0 | AB85: 94 | AC85: 62 | AD85: 19 | AE85: 86 | AF85: 33 | AG85: 59 | AH85: 42 | AI85: =H$1*((-0.000002)*H85^3+0.00032*H85^2+(-0.0021)*H85)+I$1*((-0.000002)*I85^3+0.00032*I85^2+(-0.0021)*I85)+J$1*((-0.000002)*J85^3+0.00032*J85^2+(-0.0021)*J85)+K$1*((-0.000002)*K85^3+0.00032*K85^2+(-0.0021)*K85)+L$1*((-0.000002)*L85^3+0.00032*L85^2+(-0.0021)*L85) -> 1.8362544 | AJ85: =M$1*((-0.000002)*M85^3+0.00032*M85^2+(-0.0021)*M85)+N$1*((-0.000002)*N85^3+0.00032*N85^2+(-0.0021)*N85)+O$1*((-0.000002)*O85^3+0.00032*O85^2+(-0.0021)*O85) -> 0.085498 | AK85: =IF(AA85<50,W$1*((-0.000002)*W85^3+0.00032*W85^2+(-0.0021)*W85)+X$1*((-0.000002)*X85^3+0.00032*X85^2+(-0.0021)*X85)+Y$1*((-0.000002)*Y85^3+0.00032*Y85^2+(-0.0021)*Y85)+Z$1*((-0.000002)*Z85^3+0.00032*Z85^2+(-0.0021)*Z85),X$2*((-0.000002)*X85^3+0.00032*X85^2+(-0.0021)*X85)+Y$2*((-0.000002)*Y85^3+0.00032*Y85^2+(-0.0021)*Y85)+Z$2*((-0.000002)*Z85^3+0.00032*Z85^2+(-0.0021)*Z85)+AA$2*((-0.000002)*AA85^3+0.00032*AA85^2+(-0.0021)*AA85)) -> 1.202418 | AL85: =AB$1*((-0.000002)*AB85^3+0.00032*AB85^2+(-0.0021)*AB85)+AC$1*((-0.000002)*AC85^3+0.00032*AC85^2+(-0.0021)*AC85) -> 0.8998064 | AM85: =AD$1*((-0.000002)*AD85^3+0.00032*AD85^2+(-0.0021)*AD85)+AE$1*((-0.000002)*AE85^3+0.00032*AE85^2+(-0.0021)*AE85)+AF$1*((-0.000002)*AF85^3+0.00032*AF85^2+(-0.0021)*AF85)+AG$1*((-0.000002)*AG85^3+0.00032*AG85^2+(-0.0021)*AG85) -> 0.2319596
A86: =IFERROR((AI86*AI$3+AJ86*AJ$3+AK86*AK$3+AL86*AL$3+AM86*AM$3)*100/(AI$5*AI$3+AJ$5*AJ$3+AK$5*AK$3+AL$5*AL$3+AM$5*AM$3),0) -> 0 | B86: 227 | C86: Hodges, John | D86: C | E86: L | F86: R | G86: 21 | H86: ? | I86: ? | J86: ? | K86: ? | L86: ? | M86: ? | N86: ? | O86: ? | P86: ? | Q86: 227 | R86: Hodges, John | S86: C | T86: L | U86: R | V86: 21 | W86: ? | X86: ? | Y86: ? | Z86: ? | AA86: ? | AB86: ? | AC86: ? | AD86: ? | AE86: ? | AF86: ? | AG86: ? | AH86: ? | AI86: =H$1*((-0.000002)*H86^3+0.00032*H86^2+(-0.0021)*H86)+I$1*((-0.000002)*I86^3+0.00032*I86^2+(-0.0021)*I86)+J$1*((-0.000002)*J86^3+0.00032*J86^2+(-0.0021)*J86)+K$1*((-0.000002)*K86^3+0.00032*K86^2+(-0.0021)*K86)+L$1*((-0.000002)*L86^3+0.00032*L86^2+(-0.0021)*L86) -> #VALUE! | AJ86: =M$1*((-0.000002)*M86^3+0.00032*M86^2+(-0.0021)*M86)+N$1*((-0.000002)*N86^3+0.00032*N86^2+(-0.0021)*N86)+O$1*((-0.000002)*O86^3+0.00032*O86^2+(-0.0021)*O86) -> #VALUE! | AK86: =IF(AA86<50,W$1*((-0.000002)*W86^3+0.00032*W86^2+(-0.0021)*W86)+X$1*((-0.000002)*X86^3+0.00032*X86^2+(-0.0021)*X86)+Y$1*((-0.000002)*Y86^3+0.00032*Y86^2+(-0.0021)*Y86)+Z$1*((-0.000002)*Z86^3+0.00032*Z86^2+(-0.0021)*Z86),X$2*((-0.000002)*X86^3+0.00032*X86^2+(-0.0021)*X86)+Y$2*((-0.000002)*Y86^3+0.00032*Y86^2+(-0.0021)*Y86)+Z$2*((-0.000002)*Z86^3+0.00032*Z86^2+(-0.0021)*Z86)+AA$2*((-0.000002)*AA86^3+0.00032*AA86^2+(-0.0021)*AA86)) -> #VALUE! | AL86: =AB$1*((-0.000002)*AB86^3+0.00032*AB86^2+(-0.0021)*AB86)+AC$1*((-0.000002)*AC86^3+0.00032*AC86^2+(-0.0021)*AC86) -> #VALUE! | AM86: =AD$1*((-0.000002)*AD86^3+0.00032*AD86^2+(-0.0021)*AD86)+AE$1*((-0.000002)*AE86^3+0.00032*AE86^2+(-0.0021)*AE86)+AF$1*((-0.000002)*AF86^3+0.00032*AF86^2+(-0.0021)*AF86)+AG$1*((-0.000002)*AG86^3+0.00032*AG86^2+(-0.0021)*AG86) -> #VALUE!
A87: =IFERROR((AI87*AI$3+AJ87*AJ$3+AK87*AK$3+AL87*AL$3+AM87*AM$3)*100/(AI$5*AI$3+AJ$5*AJ$3+AK$5*AK$3+AL$5*AL$3+AM$5*AM$3),0) -> 0 | B87: 228 | C87: Ramirez, Gerardo | D87: C | E87: R | F87: R | G87: 21 | H87: ? | I87: ? | J87: ? | K87: ? | L87: ? | M87: ? | N87: ? | O87: ? | P87: ? | Q87: 228 | R87: Ramirez, Gerardo | S87: C | T87: R | U87: R | V87: 21 | W87: ? | X87: ? | Y87: ? | Z87: ? | AA87: ? | AB87: ? | AC87: ? | AD87: ? | AE87: ? | AF87: ? | AG87: ? | AH87: ? | AI87: =H$1*((-0.000002)*H87^3+0.00032*H87^2+(-0.0021)*H87)+I$1*((-0.000002)*I87^3+0.00032*I87^2+(-0.0021)*I87)+J$1*((-0.000002)*J87^3+0.00032*J87^2+(-0.0021)*J87)+K$1*((-0.000002)*K87^3+0.00032*K87^2+(-0.0021)*K87)+L$1*((-0.000002)*L87^3+0.00032*L87^2+(-0.0021)*L87) -> #VALUE! | AJ87: =M$1*((-0.000002)*M87^3+0.00032*M87^2+(-0.0021)*M87)+N$1*((-0.000002)*N87^3+0.00032*N87^2+(-0.0021)*N87)+O$1*((-0.000002)*O87^3+0.00032*O87^2+(-0.0021)*O87) -> #VALUE! | AK87: =IF(AA87<50,W$1*((-0.000002)*W87^3+0.00032*W87^2+(-0.0021)*W87)+X$1*((-0.000002)*X87^3+0.00032*X87^2+(-0.0021)*X87)+Y$1*((-0.000002)*Y87^3+0.00032*Y87^2+(-0.0021)*Y87)+Z$1*((-0.000002)*Z87^3+0.00032*Z87^2+(-0.0021)*Z87),X$2*((-0.000002)*X87^3+0.00032*X87^2+(-0.0021)*X87)+Y$2*((-0.000002)*Y87^3+0.00032*Y87^2+(-0.0021)*Y87)+Z$2*((-0.000002)*Z87^3+0.00032*Z87^2+(-0.0021)*Z87)+AA$2*((-0.000002)*AA87^3+0.00032*AA87^2+(-0.0021)*AA87)) -> #VALUE! | AL87: =AB$1*((-0.000002)*AB87^3+0.00032*AB87^2+(-0.0021)*AB87)+AC$1*((-0.000002)*AC87^3+0.00032*AC87^2+(-0.0021)*AC87) -> #VALUE! | AM87: =AD$1*((-0.000002)*AD87^3+0.00032*AD87^2+(-0.0021)*AD87)+AE$1*((-0.000002)*AE87^3+0.00032*AE87^2+(-0.0021)*AE87)+AF$1*((-0.000002)*AF87^3+0.00032*AF87^2+(-0.0021)*AF87)+AG$1*((-0.000002)*AG87^3+0.00032*AG87^2+(-0.0021)*AG87) -> #VALUE!
A88: =IFERROR((AI88*AI$3+AJ88*AJ$3+AK88*AK$3+AL88*AL$3+AM88*AM$3)*100/(AI$5*AI$3+AJ$5*AJ$3+AK$5*AK$3+AL$5*AL$3+AM$5*AM$3),0) -> 0 | B88: 229 | C88: Davis, Alan | D88: C | E88: R | F88: R | G88: 21 | H88: ? | I88: ? | J88: ? | K88: ? | L88: ? | M88: ? | N88: ? | O88: ? | P88: ? | Q88: 229 | R88: Davis, Alan | S88: C | T88: R | U88: R | V88: 21 | W88: ? | X88: ? | Y88: ? | Z88: ? | AA88: ? | AB88: ? | AC88: ? | AD88: ? | AE88: ? | AF88: ? | AG88: ? | AH88: ? | AI88: =H$1*((-0.000002)*H88^3+0.00032*H88^2+(-0.0021)*H88)+I$1*((-0.000002)*I88^3+0.00032*I88^2+(-0.0021)*I88)+J$1*((-0.000002)*J88^3+0.00032*J88^2+(-0.0021)*J88)+K$1*((-0.000002)*K88^3+0.00032*K88^2+(-0.0021)*K88)+L$1*((-0.000002)*L88^3+0.00032*L88^2+(-0.0021)*L88) -> #VALUE! | AJ88: =M$1*((-0.000002)*M88^3+0.00032*M88^2+(-0.0021)*M88)+N$1*((-0.000002)*N88^3+0.00032*N88^2+(-0.0021)*N88)+O$1*((-0.000002)*O88^3+0.00032*O88^2+(-0.0021)*O88) -> #VALUE! | AK88: =IF(AA88<50,W$1*((-0.000002)*W88^3+0.00032*W88^2+(-0.0021)*W88)+X$1*((-0.000002)*X88^3+0.00032*X88^2+(-0.0021)*X88)+Y$1*((-0.000002)*Y88^3+0.00032*Y88^2+(-0.0021)*Y88)+Z$1*((-0.000002)*Z88^3+0.00032*Z88^2+(-0.0021)*Z88),X$2*((-0.000002)*X88^3+0.00032*X88^2+(-0.0021)*X88)+Y$2*((-0.000002)*Y88^3+0.00032*Y88^2+(-0.0021)*Y88)+Z$2*((-0.000002)*Z88^3+0.00032*Z88^2+(-0.0021)*Z88)+AA$2*((-0.000002)*AA88^3+0.00032*AA88^2+(-0.0021)*AA88)) -> #VALUE! | AL88: =AB$1*((-0.000002)*AB88^3+0.00032*AB88^2+(-0.0021)*AB88)+AC$1*((-0.000002)*AC88^3+0.00032*AC88^2+(-0.0021)*AC88) -> #VALUE! | AM88: =AD$1*((-0.000002)*AD88^3+0.00032*AD88^2+(-0.0021)*AD88)+AE$1*((-0.000002)*AE88^3+0.00032*AE88^2+(-0.0021)*AE88)+AF$1*((-0.000002)*AF88^3+0.00032*AF88^2+(-0.0021)*AF88)+AG$1*((-0.000002)*AG88^3+0.00032*AG88^2+(-0.0021)*AG88) -> #VALUE!
A89: =IFERROR((AI89*AI$3+AJ89*AJ$3+AK89*AK$3+AL89*AL$3+AM89*AM$3)*100/(AI$5*AI$3+AJ$5*AJ$3+AK$5*AK$3+AL$5*AL$3+AM$5*AM$3),0) -> 0 | B89: 230 | C89: Miley, Johan | D89: C | E89: R | F89: R | G89: 22 | H89: ? | I89: ? | J89: ? | K89: ? | L89: ? | M89: ? | N89: ? | O89: ? | P89: ? | Q89: 230 | R89: Miley, Johan | S89: C | T89: R | U89: R | V89: 22 | W89: ? | X89: ? | Y89: ? | Z89: ? | AA89: ? | AB89: ? | AC89: ? | AD89: ? | AE89: ? | AF89: ? | AG89: ? | AH89: ? | AI89: =H$1*((-0.000002)*H89^3+0.00032*H89^2+(-0.0021)*H89)+I$1*((-0.000002)*I89^3+0.00032*I89^2+(-0.0021)*I89)+J$1*((-0.000002)*J89^3+0.00032*J89^2+(-0.0021)*J89)+K$1*((-0.000002)*K89^3+0.00032*K89^2+(-0.0021)*K89)+L$1*((-0.000002)*L89^3+0.00032*L89^2+(-0.0021)*L89) -> #VALUE! | AJ89: =M$1*((-0.000002)*M89^3+0.00032*M89^2+(-0.0021)*M89)+N$1*((-0.000002)*N89^3+0.00032*N89^2+(-0.0021)*N89)+O$1*((-0.000002)*O89^3+0.00032*O89^2+(-0.0021)*O89) -> #VALUE! | AK89: =IF(AA89<50,W$1*((-0.000002)*W89^3+0.00032*W89^2+(-0.0021)*W89)+X$1*((-0.000002)*X89^3+0.00032*X89^2+(-0.0021)*X89)+Y$1*((-0.000002)*Y89^3+0.00032*Y89^2+(-0.0021)*Y89)+Z$1*((-0.000002)*Z89^3+0.00032*Z89^2+(-0.0021)*Z89),X$2*((-0.000002)*X89^3+0.00032*X89^2+(-0.0021)*X89)+Y$2*((-0.000002)*Y89^3+0.00032*Y89^2+(-0.0021)*Y89)+Z$2*((-0.000002)*Z89^3+0.00032*Z89^2+(-0.0021)*Z89)+AA$2*((-0.000002)*AA89^3+0.00032*AA89^2+(-0.0021)*AA89)) -> #VALUE! | AL89: =AB$1*((-0.000002)*AB89^3+0.00032*AB89^2+(-0.0021)*AB89)+AC$1*((-0.000002)*AC89^3+0.00032*AC89^2+(-0.0021)*AC89) -> #VALUE! | AM89: =AD$1*((-0.000002)*AD89^3+0.00032*AD89^2+(-0.0021)*AD89)+AE$1*((-0.000002)*AE89^3+0.00032*AE89^2+(-0.0021)*AE89)+AF$1*((-0.000002)*AF89^3+0.00032*AF89^2+(-0.0021)*AF89)+AG$1*((-0.000002)*AG89^3+0.00032*AG89^2+(-0.0021)*AG89) -> #VALUE!
A90: =IFERROR((AI90*AI$3+AJ90*AJ$3+AK90*AK$3+AL90*AL$3+AM90*AM$3)*100/(AI$5*AI$3+AJ$5*AJ$3+AK$5*AK$3+AL$5*AL$3+AM$5*AM$3),0) -> 0 | B90: 231 | C90: Jodie, Tony | D90: C | E90: R | F90: R | G90: 21 | H90: ? | I90: ? | J90: ? | K90: ? | L90: ? | M90: ? | N90: ? | O90: ? | P90: ? | Q90: 231 | R90: Jodie, Tony | S90: C | T90: R | U90: R | V90: 21 | W90: ? | X90: ? | Y90: ? | Z90: ? | AA90: ? | AB90: ? | AC90: ? | AD90: ? | AE90: ? | AF90: ? | AG90: ? | AH90: ? | AI90: =H$1*((-0.000002)*H90^3+0.00032*H90^2+(-0.0021)*H90)+I$1*((-0.000002)*I90^3+0.00032*I90^2+(-0.0021)*I90)+J$1*((-0.000002)*J90^3+0.00032*J90^2+(-0.0021)*J90)+K$1*((-0.000002)*K90^3+0.00032*K90^2+(-0.0021)*K90)+L$1*((-0.000002)*L90^3+0.00032*L90^2+(-0.0021)*L90) -> #VALUE! | AJ90: =M$1*((-0.000002)*M90^3+0.00032*M90^2+(-0.0021)*M90)+N$1*((-0.000002)*N90^3+0.00032*N90^2+(-0.0021)*N90)+O$1*((-0.000002)*O90^3+0.00032*O90^2+(-0.0021)*O90) -> #VALUE! | AK90: =IF(AA90<50,W$1*((-0.000002)*W90^3+0.00032*W90^2+(-0.0021)*W90)+X$1*((-0.000002)*X90^3+0.00032*X90^2+(-0.0021)*X90)+Y$1*((-0.000002)*Y90^3+0.00032*Y90^2+(-0.0021)*Y90)+Z$1*((-0.000002)*Z90^3+0.00032*Z90^2+(-0.0021)*Z90),X$2*((-0.000002)*X90^3+0.00032*X90^2+(-0.0021)*X90)+Y$2*((-0.000002)*Y90^3+0.00032*Y90^2+(-0.0021)*Y90)+Z$2*((-0.000002)*Z90^3+0.00032*Z90^2+(-0.0021)*Z90)+AA$2*((-0.000002)*AA90^3+0.00032*AA90^2+(-0.0021)*AA90)) -> #VALUE! | AL90: =AB$1*((-0.000002)*AB90^3+0.00032*AB90^2+(-0.0021)*AB90)+AC$1*((-0.000002)*AC90^3+0.00032*AC90^2+(-0.0021)*AC90) -> #VALUE! | AM90: =AD$1*((-0.000002)*AD90^3+0.00032*AD90^2+(-0.0021)*AD90)+AE$1*((-0.000002)*AE90^3+0.00032*AE90^2+(-0.0021)*AE90)+AF$1*((-0.000002)*AF90^3+0.00032*AF90^2+(-0.0021)*AF90)+AG$1*((-0.000002)*AG90^3+0.00032*AG90^2+(-0.0021)*AG90) -> #VALUE!
A91: =IFERROR((AI91*AI$3+AJ91*AJ$3+AK91*AK$3+AL91*AL$3+AM91*AM$3)*100/(AI$5*AI$3+AJ$5*AJ$3+AK$5*AK$3+AL$5*AL$3+AM$5*AM$3),0) -> 0 | B91: 232 | C91: Hernandez, Ezdra | D91: C | E91: R | F91: R | G91: 19 | H91: ? | I91: ? | J91: ? | K91: ? | L91: ? | M91: ? | N91: ? | O91: ? | P91: ? | Q91: 232 | R91: Hernandez, Ezdra | S91: C | T91: R | U91: R | V91: 19 | W91: ? | X91: ? | Y91: ? | Z91: ? | AA91: ? | AB91: ? | AC91: ? | AD91: ? | AE91: ? | AF91: ? | AG91: ? | AH91: ? | AI91: =H$1*((-0.000002)*H91^3+0.00032*H91^2+(-0.0021)*H91)+I$1*((-0.000002)*I91^3+0.00032*I91^2+(-0.0021)*I91)+J$1*((-0.000002)*J91^3+0.00032*J91^2+(-0.0021)*J91)+K$1*((-0.000002)*K91^3+0.00032*K91^2+(-0.0021)*K91)+L$1*((-0.000002)*L91^3+0.00032*L91^2+(-0.0021)*L91) -> #VALUE! | AJ91: =M$1*((-0.000002)*M91^3+0.00032*M91^2+(-0.0021)*M91)+N$1*((-0.000002)*N91^3+0.00032*N91^2+(-0.0021)*N91)+O$1*((-0.000002)*O91^3+0.00032*O91^2+(-0.0021)*O91) -> #VALUE! | AK91: =IF(AA91<50,W$1*((-0.000002)*W91^3+0.00032*W91^2+(-0.0021)*W91)+X$1*((-0.000002)*X91^3+0.00032*X91^2+(-0.0021)*X91)+Y$1*((-0.000002)*Y91^3+0.00032*Y91^2+(-0.0021)*Y91)+Z$1*((-0.000002)*Z91^3+0.00032*Z91^2+(-0.0021)*Z91),X$2*((-0.000002)*X91^3+0.00032*X91^2+(-0.0021)*X91)+Y$2*((-0.000002)*Y91^3+0.00032*Y91^2+(-0.0021)*Y91)+Z$2*((-0.000002)*Z91^3+0.00032*Z91^2+(-0.0021)*Z91)+AA$2*((-0.000002)*AA91^3+0.00032*AA91^2+(-0.0021)*AA91)) -> #VALUE! | AL91: =AB$1*((-0.000002)*AB91^3+0.00032*AB91^2+(-0.0021)*AB91)+AC$1*((-0.000002)*AC91^3+0.00032*AC91^2+(-0.0021)*AC91) -> #VALUE! | AM91: =AD$1*((-0.000002)*AD91^3+0.00032*AD91^2+(-0.0021)*AD91)+AE$1*((-0.000002)*AE91^3+0.00032*AE91^2+(-0.0021)*AE91)+AF$1*((-0.000002)*AF91^3+0.00032*AF91^2+(-0.0021)*AF91)+AG$1*((-0.000002)*AG91^3+0.00032*AG91^2+(-0.0021)*AG91) -> #VALUE!
A92: =IFERROR((AI92*AI$3+AJ92*AJ$3+AK92*AK$3+AL92*AL$3+AM92*AM$3)*100/(AI$5*AI$3+AJ$5*AJ$3+AK$5*AK$3+AL$5*AL$3+AM$5*AM$3),0) -> 0 | B92: 233 | C92: Burks, Gill | D92: C | E92: R | F92: R | G92: 19 | H92: ? | I92: ? | J92: ? | K92: ? | L92: ? | M92: ? | N92: ? | O92: ? | P92: ? | Q92: 233 | R92: Burks, Gill | S92: C | T92: R | U92: R | V92: 19 | W92: ? | X92: ? | Y92: ? | Z92: ? | AA92: ? | AB92: ? | AC92: ? | AD92: ? | AE92: ? | AF92: ? | AG92: ? | AH92: ? | AI92: =H$1*((-0.000002)*H92^3+0.00032*H92^2+(-0.0021)*H92)+I$1*((-0.000002)*I92^3+0.00032*I92^2+(-0.0021)*I92)+J$1*((-0.000002)*J92^3+0.00032*J92^2+(-0.0021)*J92)+K$1*((-0.000002)*K92^3+0.00032*K92^2+(-0.0021)*K92)+L$1*((-0.000002)*L92^3+0.00032*L92^2+(-0.0021)*L92) -> #VALUE! | AJ92: =M$1*((-0.000002)*M92^3+0.00032*M92^2+(-0.0021)*M92)+N$1*((-0.000002)*N92^3+0.00032*N92^2+(-0.0021)*N92)+O$1*((-0.000002)*O92^3+0.00032*O92^2+(-0.0021)*O92) -> #VALUE! | AK92: =IF(AA92<50,W$1*((-0.000002)*W92^3+0.00032*W92^2+(-0.0021)*W92)+X$1*((-0.000002)*X92^3+0.00032*X92^2+(-0.0021)*X92)+Y$1*((-0.000002)*Y92^3+0.00032*Y92^2+(-0.0021)*Y92)+Z$1*((-0.000002)*Z92^3+0.00032*Z92^2+(-0.0021)*Z92),X$2*((-0.000002)*X92^3+0.00032*X92^2+(-0.0021)*X92)+Y$2*((-0.000002)*Y92^3+0.00032*Y92^2+(-0.0021)*Y92)+Z$2*((-0.000002)*Z92^3+0.00032*Z92^2+(-0.0021)*Z92)+AA$2*((-0.000002)*AA92^3+0.00032*AA92^2+(-0.0021)*AA92)) -> #VALUE! | AL92: =AB$1*((-0.000002)*AB92^3+0.00032*AB92^2+(-0.0021)*AB92)+AC$1*((-0.000002)*AC92^3+0.00032*AC92^2+(-0.0021)*AC92) -> #VALUE! | AM92: =AD$1*((-0.000002)*AD92^3+0.00032*AD92^2+(-0.0021)*AD92)+AE$1*((-0.000002)*AE92^3+0.00032*AE92^2+(-0.0021)*AE92)+AF$1*((-0.000002)*AF92^3+0.00032*AF92^2+(-0.0021)*AF92)+AG$1*((-0.000002)*AG92^3+0.00032*AG92^2+(-0.0021)*AG92) -> #VALUE!
A93: =IFERROR((AI93*AI$3+AJ93*AJ$3+AK93*AK$3+AL93*AL$3+AM93*AM$3)*100/(AI$5*AI$3+AJ$5*AJ$3+AK$5*AK$3+AL$5*AL$3+AM$5*AM$3),0) -> 0 | B93: 234 | C93: King, Roger | D93: C | E93: R | F93: R | G93: 20 | H93: ? | I93: ? | J93: ? | K93: ? | L93: ? | M93: ? | N93: ? | O93: ? | P93: ? | Q93: 234 | R93: King, Roger | S93: C | T93: R | U93: R | V93: 20 | W93: ? | X93: ? | Y93: ? | Z93: ? | AA93: ? | AB93: ? | AC93: ? | AD93: ? | AE93: ? | AF93: ? | AG93: ? | AH93: ? | AI93: =H$1*((-0.000002)*H93^3+0.00032*H93^2+(-0.0021)*H93)+I$1*((-0.000002)*I93^3+0.00032*I93^2+(-0.0021)*I93)+J$1*((-0.000002)*J93^3+0.00032*J93^2+(-0.0021)*J93)+K$1*((-0.000002)*K93^3+0.00032*K93^2+(-0.0021)*K93)+L$1*((-0.000002)*L93^3+0.00032*L93^2+(-0.0021)*L93) -> #VALUE! | AJ93: =M$1*((-0.000002)*M93^3+0.00032*M93^2+(-0.0021)*M93)+N$1*((-0.000002)*N93^3+0.00032*N93^2+(-0.0021)*N93)+O$1*((-0.000002)*O93^3+0.00032*O93^2+(-0.0021)*O93) -> #VALUE! | AK93: =IF(AA93<50,W$1*((-0.000002)*W93^3+0.00032*W93^2+(-0.0021)*W93)+X$1*((-0.000002)*X93^3+0.00032*X93^2+(-0.0021)*X93)+Y$1*((-0.000002)*Y93^3+0.00032*Y93^2+(-0.0021)*Y93)+Z$1*((-0.000002)*Z93^3+0.00032*Z93^2+(-0.0021)*Z93),X$2*((-0.000002)*X93^3+0.00032*X93^2+(-0.0021)*X93)+Y$2*((-0.000002)*Y93^3+0.00032*Y93^2+(-0.0021)*Y93)+Z$2*((-0.000002)*Z93^3+0.00032*Z93^2+(-0.0021)*Z93)+AA$2*((-0.000002)*AA93^3+0.00032*AA93^2+(-0.0021)*AA93)) -> #VALUE! | AL93: =AB$1*((-0.000002)*AB93^3+0.00032*AB93^2+(-0.0021)*AB93)+AC$1*((-0.000002)*AC93^3+0.00032*AC93^2+(-0.0021)*AC93) -> #VALUE! | AM93: =AD$1*((-0.000002)*AD93^3+0.00032*AD93^2+(-0.0021)*AD93)+AE$1*((-0.000002)*AE93^3+0.00032*AE93^2+(-0.0021)*AE93)+AF$1*((-0.000002)*AF93^3+0.00032*AF93^2+(-0.0021)*AF93)+AG$1*((-0.000002)*AG93^3+0.00032*AG93^2+(-0.0021)*AG93) -> #VALUE!
A94: =IFERROR((AI94*AI$3+AJ94*AJ$3+AK94*AK$3+AL94*AL$3+AM94*AM$3)*100/(AI$5*AI$3+AJ$5*AJ$3+AK$5*AK$3+AL$5*AL$3+AM$5*AM$3),0) -> 0 | B94: 235 | C94: Riley, Clay | D94: C | E94: R | F94: R | G94: 21 | H94: ? | I94: ? | J94: ? | K94: ? | L94: ? | M94: ? | N94: ? | O94: ? | P94: ? | Q94: 235 | R94: Riley, Clay | S94: C | T94: R | U94: R | V94: 21 | W94: ? | X94: ? | Y94: ? | Z94: ? | AA94: ? | AB94: ? | AC94: ? | AD94: ? | AE94: ? | AF94: ? | AG94: ? | AH94: ? | AI94: =H$1*((-0.000002)*H94^3+0.00032*H94^2+(-0.0021)*H94)+I$1*((-0.000002)*I94^3+0.00032*I94^2+(-0.0021)*I94)+J$1*((-0.000002)*J94^3+0.00032*J94^2+(-0.0021)*J94)+K$1*((-0.000002)*K94^3+0.00032*K94^2+(-0.0021)*K94)+L$1*((-0.000002)*L94^3+0.00032*L94^2+(-0.0021)*L94) -> #VALUE! | AJ94: =M$1*((-0.000002)*M94^3+0.00032*M94^2+(-0.0021)*M94)+N$1*((-0.000002)*N94^3+0.00032*N94^2+(-0.0021)*N94)+O$1*((-0.000002)*O94^3+0.00032*O94^2+(-0.0021)*O94) -> #VALUE! | AK94: =IF(AA94<50,W$1*((-0.000002)*W94^3+0.00032*W94^2+(-0.0021)*W94)+X$1*((-0.000002)*X94^3+0.00032*X94^2+(-0.0021)*X94)+Y$1*((-0.000002)*Y94^3+0.00032*Y94^2+(-0.0021)*Y94)+Z$1*((-0.000002)*Z94^3+0.00032*Z94^2+(-0.0021)*Z94),X$2*((-0.000002)*X94^3+0.00032*X94^2+(-0.0021)*X94)+Y$2*((-0.000002)*Y94^3+0.00032*Y94^2+(-0.0021)*Y94)+Z$2*((-0.000002)*Z94^3+0.00032*Z94^2+(-0.0021)*Z94)+AA$2*((-0.000002)*AA94^3+0.00032*AA94^2+(-0.0021)*AA94)) -> #VALUE! | AL94: =AB$1*((-0.000002)*AB94^3+0.00032*AB94^2+(-0.0021)*AB94)+AC$1*((-0.000002)*AC94^3+0.00032*AC94^2+(-0.0021)*AC94) -> #VALUE! | AM94: =AD$1*((-0.000002)*AD94^3+0.00032*AD94^2+(-0.0021)*AD94)+AE$1*((-0.000002)*AE94^3+0.00032*AE94^2+(-0.0021)*AE94)+AF$1*((-0.000002)*AF94^3+0.00032*AF94^2+(-0.0021)*AF94)+AG$1*((-0.000002)*AG94^3+0.00032*AG94^2+(-0.0021)*AG94) -> #VALUE!
A95: =IFERROR((AI95*AI$3+AJ95*AJ$3+AK95*AK$3+AL95*AL$3+AM95*AM$3)*100/(AI$5*AI$3+AJ$5*AJ$3+AK$5*AK$3+AL$5*AL$3+AM$5*AM$3),0) -> 0 | B95: 236 | C95: Mendoza, Stefen | D95: C | E95: R | F95: R | G95: 19 | H95: ? | I95: ? | J95: ? | K95: ? | L95: ? | M95: ? | N95: ? | O95: ? | P95: ? | Q95: 236 | R95: Mendoza, Stefen | S95: C | T95: R | U95: R | V95: 19 | W95: ? | X95: ? | Y95: ? | Z95: ? | AA95: ? | AB95: ? | AC95: ? | AD95: ? | AE95: ? | AF95: ? | AG95: ? | AH95: ? | AI95: =H$1*((-0.000002)*H95^3+0.00032*H95^2+(-0.0021)*H95)+I$1*((-0.000002)*I95^3+0.00032*I95^2+(-0.0021)*I95)+J$1*((-0.000002)*J95^3+0.00032*J95^2+(-0.0021)*J95)+K$1*((-0.000002)*K95^3+0.00032*K95^2+(-0.0021)*K95)+L$1*((-0.000002)*L95^3+0.00032*L95^2+(-0.0021)*L95) -> #VALUE! | AJ95: =M$1*((-0.000002)*M95^3+0.00032*M95^2+(-0.0021)*M95)+N$1*((-0.000002)*N95^3+0.00032*N95^2+(-0.0021)*N95)+O$1*((-0.000002)*O95^3+0.00032*O95^2+(-0.0021)*O95) -> #VALUE! | AK95: =IF(AA95<50,W$1*((-0.000002)*W95^3+0.00032*W95^2+(-0.0021)*W95)+X$1*((-0.000002)*X95^3+0.00032*X95^2+(-0.0021)*X95)+Y$1*((-0.000002)*Y95^3+0.00032*Y95^2+(-0.0021)*Y95)+Z$1*((-0.000002)*Z95^3+0.00032*Z95^2+(-0.0021)*Z95),X$2*((-0.000002)*X95^3+0.00032*X95^2+(-0.0021)*X95)+Y$2*((-0.000002)*Y95^3+0.00032*Y95^2+(-0.0021)*Y95)+Z$2*((-0.000002)*Z95^3+0.00032*Z95^2+(-0.0021)*Z95)+AA$2*((-0.000002)*AA95^3+0.00032*AA95^2+(-0.0021)*AA95)) -> #VALUE! | AL95: =AB$1*((-0.000002)*AB95^3+0.00032*AB95^2+(-0.0021)*AB95)+AC$1*((-0.000002)*AC95^3+0.00032*AC95^2+(-0.0021)*AC95) -> #VALUE! | AM95: =AD$1*((-0.000002)*AD95^3+0.00032*AD95^2+(-0.0021)*AD95)+AE$1*((-0.000002)*AE95^3+0.00032*AE95^2+(-0.0021)*AE95)+AF$1*((-0.000002)*AF95^3+0.00032*AF95^2+(-0.0021)*AF95)+AG$1*((-0.000002)*AG95^3+0.00032*AG95^2+(-0.0021)*AG95) -> #VALUE!
A96: =IFERROR((AI96*AI$3+AJ96*AJ$3+AK96*AK$3+AL96*AL$3+AM96*AM$3)*100/(AI$5*AI$3+AJ$5*AJ$3+AK$5*AK$3+AL$5*AL$3+AM$5*AM$3),0) -> 0 | B96: 237 | C96: Johnson, Wilkin | D96: C | E96: L | F96: R | G96: 18 | H96: ? | I96: ? | J96: ? | K96: ? | L96: ? | M96: ? | N96: ? | O96: ? | P96: ? | Q96: 237 | R96: Johnson, Wilkin | S96: C | T96: L | U96: R | V96: 18 | W96: ? | X96: ? | Y96: ? | Z96: ? | AA96: ? | AB96: ? | AC96: ? | AD96: ? | AE96: ? | AF96: ? | AG96: ? | AH96: ? | AI96: =H$1*((-0.000002)*H96^3+0.00032*H96^2+(-0.0021)*H96)+I$1*((-0.000002)*I96^3+0.00032*I96^2+(-0.0021)*I96)+J$1*((-0.000002)*J96^3+0.00032*J96^2+(-0.0021)*J96)+K$1*((-0.000002)*K96^3+0.00032*K96^2+(-0.0021)*K96)+L$1*((-0.000002)*L96^3+0.00032*L96^2+(-0.0021)*L96) -> #VALUE! | AJ96: =M$1*((-0.000002)*M96^3+0.00032*M96^2+(-0.0021)*M96)+N$1*((-0.000002)*N96^3+0.00032*N96^2+(-0.0021)*N96)+O$1*((-0.000002)*O96^3+0.00032*O96^2+(-0.0021)*O96) -> #VALUE! | AK96: =IF(AA96<50,W$1*((-0.000002)*W96^3+0.00032*W96^2+(-0.0021)*W96)+X$1*((-0.000002)*X96^3+0.00032*X96^2+(-0.0021)*X96)+Y$1*((-0.000002)*Y96^3+0.00032*Y96^2+(-0.0021)*Y96)+Z$1*((-0.000002)*Z96^3+0.00032*Z96^2+(-0.0021)*Z96),X$2*((-0.000002)*X96^3+0.00032*X96^2+(-0.0021)*X96)+Y$2*((-0.000002)*Y96^3+0.00032*Y96^2+(-0.0021)*Y96)+Z$2*((-0.000002)*Z96^3+0.00032*Z96^2+(-0.0021)*Z96)+AA$2*((-0.000002)*AA96^3+0.00032*AA96^2+(-0.0021)*AA96)) -> #VALUE! | AL96: =AB$1*((-0.000002)*AB96^3+0.00032*AB96^2+(-0.0021)*AB96)+AC$1*((-0.000002)*AC96^3+0.00032*AC96^2+(-0.0021)*AC96) -> #VALUE! | AM96: =AD$1*((-0.000002)*AD96^3+0.00032*AD96^2+(-0.0021)*AD96)+AE$1*((-0.000002)*AE96^3+0.00032*AE96^2+(-0.0021)*AE96)+AF$1*((-0.000002)*AF96^3+0.00032*AF96^2+(-0.0021)*AF96)+AG$1*((-0.000002)*AG96^3+0.00032*AG96^2+(-0.0021)*AG96) -> #VALUE!
A97: =IFERROR((AI97*AI$3+AJ97*AJ$3+AK97*AK$3+AL97*AL$3+AM97*AM$3)*100/(AI$5*AI$3+AJ$5*AJ$3+AK$5*AK$3+AL$5*AL$3+AM$5*AM$3),0) -> 0 | B97: 238 | C97: Crespo, Jose | D97: C | E97: R | F97: R | G97: 18 | H97: ? | I97: ? | J97: ? | K97: ? | L97: ? | M97: ? | N97: ? | O97: ? | P97: ? | Q97: 238 | R97: Crespo, Jose | S97: C | T97: R | U97: R | V97: 18 | W97: ? | X97: ? | Y97: ? | Z97: ? | AA97: ? | AB97: ? | AC97: ? | AD97: ? | AE97: ? | AF97: ? | AG97: ? | AH97: ? | AI97: =H$1*((-0.000002)*H97^3+0.00032*H97^2+(-0.0021)*H97)+I$1*((-0.000002)*I97^3+0.00032*I97^2+(-0.0021)*I97)+J$1*((-0.000002)*J97^3+0.00032*J97^2+(-0.0021)*J97)+K$1*((-0.000002)*K97^3+0.00032*K97^2+(-0.0021)*K97)+L$1*((-0.000002)*L97^3+0.00032*L97^2+(-0.0021)*L97) -> #VALUE! | AJ97: =M$1*((-0.000002)*M97^3+0.00032*M97^2+(-0.0021)*M97)+N$1*((-0.000002)*N97^3+0.00032*N97^2+(-0.0021)*N97)+O$1*((-0.000002)*O97^3+0.00032*O97^2+(-0.0021)*O97) -> #VALUE! | AK97: =IF(AA97<50,W$1*((-0.000002)*W97^3+0.00032*W97^2+(-0.0021)*W97)+X$1*((-0.000002)*X97^3+0.00032*X97^2+(-0.0021)*X97)+Y$1*((-0.000002)*Y97^3+0.00032*Y97^2+(-0.0021)*Y97)+Z$1*((-0.000002)*Z97^3+0.00032*Z97^2+(-0.0021)*Z97),X$2*((-0.000002)*X97^3+0.00032*X97^2+(-0.0021)*X97)+Y$2*((-0.000002)*Y97^3+0.00032*Y97^2+(-0.0021)*Y97)+Z$2*((-0.000002)*Z97^3+0.00032*Z97^2+(-0.0021)*Z97)+AA$2*((-0.000002)*AA97^3+0.00032*AA97^2+(-0.0021)*AA97)) -> #VALUE! | AL97: =AB$1*((-0.000002)*AB97^3+0.00032*AB97^2+(-0.0021)*AB97)+AC$1*((-0.000002)*AC97^3+0.00032*AC97^2+(-0.0021)*AC97) -> #VALUE! | AM97: =AD$1*((-0.000002)*AD97^3+0.00032*AD97^2+(-0.0021)*AD97)+AE$1*((-0.000002)*AE97^3+0.00032*AE97^2+(-0.0021)*AE97)+AF$1*((-0.000002)*AF97^3+0.00032*AF97^2+(-0.0021)*AF97)+AG$1*((-0.000002)*AG97^3+0.00032*AG97^2+(-0.0021)*AG97) -> #VALUE!
... A168: =IFERROR((AI168*AI$3+AJ168*AJ$3+AK168*AK$3+AL168*AL$3+AM168*AM$3)*100/(AI$5*AI$3+AJ$5*AJ$3+AK$5*AK$3+AL$5*AL$3+AM$5*AM$3),0) -> 0 | B168: 309 | C168: Accardo, Einar | D168: RF | E168: R | F168: R | G168: 18 | H168: ? | I168: ? | J168: ? | K168: ? | L168: ? | M168: ? | N168: ? | O168: ? | P168: ? | Q168: 309 | R168: Accardo, Einar | S168: RF | T168: R | U168: R | V168: 18 | W168: ? | X168: ? | Y168: ? | Z168: ? | AA168: ? | AB168: ? | AC168: ? | AD168: ? | AE168: ? | AF168: ? | AG168: ? | AH168: ? | AI168: =H$1*((-0.000002)*H168^3+0.00032*H168^2+(-0.0021)*H168)+I$1*((-0.000002)*I168^3+0.00032*I168^2+(-0.0021)*I168)+J$1*((-0.000002)*J168^3+0.00032*J168^2+(-0.0021)*J168)+K$1*((-0.000002)*K168^3+0.00032*K168^2+(-0.0021)*K168)+L$1*((-0.000002)*L168^3+0.00032*L168^2+(-0.0021)*L168) -> #VALUE! | AJ168: =M$1*((-0.000002)*M168^3+0.00032*M168^2+(-0.0021)*M168)+N$1*((-0.000002)*N168^3+0.00032*N168^2+(-0.0021)*N168)+O$1*((-0.000002)*O168^3+0.00032*O168^2+(-0.0021)*O168) -> #VALUE! | AK168: =IF(AA168<50,W$1*((-0.000002)*W168^3+0.00032*W168^2+(-0.0021)*W168)+X$1*((-0.000002)*X168^3+0.00032*X168^2+(-0.0021)*X168)+Y$1*((-0.000002)*Y168^3+0.00032*Y168^2+(-0.0021)*Y168)+Z$1*((-0.000002)*Z168^3+0.00032*Z168^2+(-0.0021)*Z168),X$2*((-0.000002)*X168^3+0.00032*X168^2+(-0.0021)*X168)+Y$2*((-0.000002)*Y168^3+0.00032*Y168^2+(-0.0021)*Y168)+Z$2*((-0.000002)*Z168^3+0.00032*Z168^2+(-0.0021)*Z168)+AA$2*((-0.000002)*AA168^3+0.00032*AA168^2+(-0.0021)*AA168)) -> #VALUE! | AL168: =AB$1*((-0.000002)*AB168^3+0.00032*AB168^2+(-0.0021)*AB168)+AC$1*((-0.000002)*AC168^3+0.00032*AC168^2+(-0.0021)*AC168) -> #VALUE! | AM168: =AD$1*((-0.000002)*AD168^3+0.00032*AD168^2+(-0.0021)*AD168)+AE$1*((-0.000002)*AE168^3+0.00032*AE168^2+(-0.0021)*AE168)+AF$1*((-0.000002)*AF168^3+0.00032*AF168^2+(-0.0021)*AF168)+AG$1*((-0.000002)*AG168^3+0.00032*AG168^2+(-0.0021)*AG168) -> #VALUE!
A169: =IFERROR((AI169*AI$3+AJ169*AJ$3+AK169*AK$3+AL169*AL$3+AM169*AM$3)*100/(AI$5*AI$3+AJ$5*AJ$3+AK$5*AK$3+AL$5*AL$3+AM$5*AM$3),0) -> 0 | B169: 310 | C169: Ryal, Dennys | D169: ? | E169: ? | F169: ? | G169: ? | H169: ? | I169: ? | J169: ? | K169: ? | L169: ? | M169: ? | N169: ? | O169: ? | P169: ? | Q169: 310 | R169: Ryal, Dennys | S169: ? | T169: ? | U169: ? | V169: ? | W169: ? | X169: ? | Y169: ? | Z169: ? | AA169: ? | AB169: ? | AC169: ? | AD169: ? | AE169: ? | AF169: ? | AG169: ? | AH169: ? | AI169: =H$1*((-0.000002)*H169^3+0.00032*H169^2+(-0.0021)*H169)+I$1*((-0.000002)*I169^3+0.00032*I169^2+(-0.0021)*I169)+J$1*((-0.000002)*J169^3+0.00032*J169^2+(-0.0021)*J169)+K$1*((-0.000002)*K169^3+0.00032*K169^2+(-0.0021)*K169)+L$1*((-0.000002)*L169^3+0.00032*L169^2+(-0.0021)*L169) -> #VALUE! | AJ169: =M$1*((-0.000002)*M169^3+0.00032*M169^2+(-0.0021)*M169)+N$1*((-0.000002)*N169^3+0.00032*N169^2+(-0.0021)*N169)+O$1*((-0.000002)*O169^3+0.00032*O169^2+(-0.0021)*O169) -> #VALUE! | AK169: =IF(AA169<50,W$1*((-0.000002)*W169^3+0.00032*W169^2+(-0.0021)*W169)+X$1*((-0.000002)*X169^3+0.00032*X169^2+(-0.0021)*X169)+Y$1*((-0.000002)*Y169^3+0.00032*Y169^2+(-0.0021)*Y169)+Z$1*((-0.000002)*Z169^3+0.00032*Z169^2+(-0.0021)*Z169),X$2*((-0.000002)*X169^3+0.00032*X169^2+(-0.0021)*X169)+Y$2*((-0.000002)*Y169^3+0.00032*Y169^2+(-0.0021)*Y169)+Z$2*((-0.000002)*Z169^3+0.00032*Z169^2+(-0.0021)*Z169)+AA$2*((-0.000002)*AA169^3+0.00032*AA169^2+(-0.0021)*AA169)) -> #VALUE! | AL169: =AB$1*((-0.000002)*AB169^3+0.00032*AB169^2+(-0.0021)*AB169)+AC$1*((-0.000002)*AC169^3+0.00032*AC169^2+(-0.0021)*AC169) -> #VALUE! | AM169: =AD$1*((-0.000002)*AD169^3+0.00032*AD169^2+(-0.0021)*AD169)+AE$1*((-0.000002)*AE169^3+0.00032*AE169^2+(-0.0021)*AE169)+AF$1*((-0.000002)*AF169^3+0.00032*AF169^2+(-0.0021)*AF169)+AG$1*((-0.000002)*AG169^3+0.00032*AG169^2+(-0.0021)*AG169) -> #VALUE!
A170: =IFERROR((AI170*AI$3+AJ170*AJ$3+AK170*AK$3+AL170*AL$3+AM170*AM$3)*100/(AI$5*AI$3+AJ$5*AJ$3+AK$5*AK$3+AL$5*AL$3+AM$5*AM$3),0) -> 0 | B170: 311 | C170: Lange, Ronald | D170: ? | E170: ? | F170: ? | G170: ? | H170: ? | I170: ? | J170: ? | K170: ? | L170: ? | M170: ? | N170: ? | O170: ? | P170: ? | Q170: 311 | R170: Lange, Ronald | S170: ? | T170: ? | U170: ? | V170: ? | W170: ? | X170: ? | Y170: ? | Z170: ? | AA170: ? | AB170: ? | AC170: ? | AD170: ? | AE170: ? | AF170: ? | AG170: ? | AH170: ? | AI170: =H$1*((-0.000002)*H170^3+0.00032*H170^2+(-0.0021)*H170)+I$1*((-0.000002)*I170^3+0.00032*I170^2+(-0.0021)*I170)+J$1*((-0.000002)*J170^3+0.00032*J170^2+(-0.0021)*J170)+K$1*((-0.000002)*K170^3+0.00032*K170^2+(-0.0021)*K170)+L$1*((-0.000002)*L170^3+0.00032*L170^2+(-0.0021)*L170) -> #VALUE! | AJ170: =M$1*((-0.000002)*M170^3+0.00032*M170^2+(-0.0021)*M170)+N$1*((-0.000002)*N170^3+0.00032*N170^2+(-0.0021)*N170)+O$1*((-0.000002)*O170^3+0.00032*O170^2+(-0.0021)*O170) -> #VALUE! | AK170: =IF(AA170<50,W$1*((-0.000002)*W170^3+0.00032*W170^2+(-0.0021)*W170)+X$1*((-0.000002)*X170^3+0.00032*X170^2+(-0.0021)*X170)+Y$1*((-0.000002)*Y170^3+0.00032*Y170^2+(-0.0021)*Y170)+Z$1*((-0.000002)*Z170^3+0.00032*Z170^2+(-0.0021)*Z170),X$2*((-0.000002)*X170^3+0.00032*X170^2+(-0.0021)*X170)+Y$2*((-0.000002)*Y170^3+0.00032*Y170^2+(-0.0021)*Y170)+Z$2*((-0.000002)*Z170^3+0.00032*Z170^2+(-0.0021)*Z170)+AA$2*((-0.000002)*AA170^3+0.00032*AA170^2+(-0.0021)*AA170)) -> #VALUE! | AL170: =AB$1*((-0.000002)*AB170^3+0.00032*AB170^2+(-0.0021)*AB170)+AC$1*((-0.000002)*AC170^3+0.00032*AC170^2+(-0.0021)*AC170) -> #VALUE! | AM170: =AD$1*((-0.000002)*AD170^3+0.00032*AD170^2+(-0.0021)*AD170)+AE$1*((-0.000002)*AE170^3+0.00032*AE170^2+(-0.0021)*AE170)+AF$1*((-0.000002)*AF170^3+0.00032*AF170^2+(-0.0021)*AF170)+AG$1*((-0.000002)*AG170^3+0.00032*AG170^2+(-0.0021)*AG170) -> #VALUE!
A171: =IFERROR((AI171*AI$3+AJ171*AJ$3+AK171*AK$3+AL171*AL$3+AM171*AM$3)*100/(AI$5*AI$3+AJ$5*AJ$3+AK$5*AK$3+AL$5*AL$3+AM$5*AM$3),0) -> 0 | B171: 312 | C171: Sullivan, John | D171: ? | E171: ? | F171: ? | G171: ? | H171: ? | I171: ? | J171: ? | K171: ? | L171: ? | M171: ? | N171: ? | O171: ? | P171: ? | Q171: 312 | R171: Sullivan, John | S171: ? | T171: ? | U171: ? | V171: ? | W171: ? | X171: ? | Y171: ? | Z171: ? | AA171: ? | AB171: ? | AC171: ? | AD171: ? | AE171: ? | AF171: ? | AG171: ? | AH171: ? | AI171: =H$1*((-0.000002)*H171^3+0.00032*H171^2+(-0.0021)*H171)+I$1*((-0.000002)*I171^3+0.00032*I171^2+(-0.0021)*I171)+J$1*((-0.000002)*J171^3+0.00032*J171^2+(-0.0021)*J171)+K$1*((-0.000002)*K171^3+0.00032*K171^2+(-0.0021)*K171)+L$1*((-0.000002)*L171^3+0.00032*L171^2+(-0.0021)*L171) -> #VALUE! | AJ171: =M$1*((-0.000002)*M171^3+0.00032*M171^2+(-0.0021)*M171)+N$1*((-0.000002)*N171^3+0.00032*N171^2+(-0.0021)*N171)+O$1*((-0.000002)*O171^3+0.00032*O171^2+(-0.0021)*O171) -> #VALUE! | AK171: =IF(AA171<50,W$1*((-0.000002)*W171^3+0.00032*W171^2+(-0.0021)*W171)+X$1*((-0.000002)*X171^3+0.00032*X171^2+(-0.0021)*X171)+Y$1*((-0.000002)*Y171^3+0.00032*Y171^2+(-0.0021)*Y171)+Z$1*((-0.000002)*Z171^3+0.00032*Z171^2+(-0.0021)*Z171),X$2*((-0.000002)*X171^3+0.00032*X171^2+(-0.0021)*X171)+Y$2*((-0.000002)*Y171^3+0.00032*Y171^2+(-0.0021)*Y171)+Z$2*((-0.000002)*Z171^3+0.00032*Z171^2+(-0.0021)*Z171)+AA$2*((-0.000002)*AA171^3+0.00032*AA171^2+(-0.0021)*AA171)) -> #VALUE! | AL171: =AB$1*((-0.000002)*AB171^3+0.00032*AB171^2+(-0.0021)*AB171)+AC$1*((-0.000002)*AC171^3+0.00032*AC171^2+(-0.0021)*AC171) -> #VALUE! | AM171: =AD$1*((-0.000002)*AD171^3+0.00032*AD171^2+(-0.0021)*AD171)+AE$1*((-0.000002)*AE171^3+0.00032*AE171^2+(-0.0021)*AE171)+AF$1*((-0.000002)*AF171^3+0.00032*AF171^2+(-0.0021)*AF171)+AG$1*((-0.000002)*AG171^3+0.00032*AG171^2+(-0.0021)*AG171) -> #VALUE!
A172: =IFERROR((AI172*AI$3+AJ172*AJ$3+AK172*AK$3+AL172*AL$3+AM172*AM$3)*100/(AI$5*AI$3+AJ$5*AJ$3+AK$5*AK$3+AL$5*AL$3+AM$5*AM$3),0) -> 0 | B172: 313 | C172: Wengert, Japhet | D172: ? | E172: ? | F172: ? | G172: ? | H172: ? | I172: ? | J172: ? | K172: ? | L172: ? | M172: ? | N172: ? | O172: ? | P172: ? | Q172: 313 | R172: Wengert, Japhet | S172: ? | T172: ? | U172: ? | V172: ? | W172: ? | X172: ? | Y172: ? | Z172: ? | AA172: ? | AB172: ? | AC172: ? | AD172: ? | AE172: ? | AF172: ? | AG172: ? | AH172: ? | AI172: =H$1*((-0.000002)*H172^3+0.00032*H172^2+(-0.0021)*H172)+I$1*((-0.000002)*I172^3+0.00032*I172^2+(-0.0021)*I172)+J$1*((-0.000002)*J172^3+0.00032*J172^2+(-0.0021)*J172)+K$1*((-0.000002)*K172^3+0.00032*K172^2+(-0.0021)*K172)+L$1*((-0.000002)*L172^3+0.00032*L172^2+(-0.0021)*L172) -> #VALUE! | AJ172: =M$1*((-0.000002)*M172^3+0.00032*M172^2+(-0.0021)*M172)+N$1*((-0.000002)*N172^3+0.00032*N172^2+(-0.0021)*N172)+O$1*((-0.000002)*O172^3+0.00032*O172^2+(-0.0021)*O172) -> #VALUE! | AK172: =IF(AA172<50,W$1*((-0.000002)*W172^3+0.00032*W172^2+(-0.0021)*W172)+X$1*((-0.000002)*X172^3+0.00032*X172^2+(-0.0021)*X172)+Y$1*((-0.000002)*Y172^3+0.00032*Y172^2+(-0.0021)*Y172)+Z$1*((-0.000002)*Z172^3+0.00032*Z172^2+(-0.0021)*Z172),X$2*((-0.000002)*X172^3+0.00032*X172^2+(-0.0021)*X172)+Y$2*((-0.000002)*Y172^3+0.00032*Y172^2+(-0.0021)*Y172)+Z$2*((-0.000002)*Z172^3+0.00032*Z172^2+(-0.0021)*Z172)+AA$2*((-0.000002)*AA172^3+0.00032*AA172^2+(-0.0021)*AA172)) -> #VALUE! | AL172: =AB$1*((-0.000002)*AB172^3+0.00032*AB172^2+(-0.0021)*AB172)+AC$1*((-0.000002)*AC172^3+0.00032*AC172^2+(-0.0021)*AC172) -> #VALUE! | AM172: =AD$1*((-0.000002)*AD172^3+0.00032*AD172^2+(-0.0021)*AD172)+AE$1*((-0.000002)*AE172^3+0.00032*AE172^2+(-0.0021)*AE172)+AF$1*((-0.000002)*AF172^3+0.00032*AF172^2+(-0.0021)*AF172)+AG$1*((-0.000002)*AG172^3+0.00032*AG172^2+(-0.0021)*AG172) -> #VALUE!
A173: =IFERROR((AI173*AI$3+AJ173*AJ$3+AK173*AK$3+AL173*AL$3+AM173*AM$3)*100/(AI$5*AI$3+AJ$5*AJ$3+AK$5*AK$3+AL$5*AL$3+AM$5*AM$3),0) -> 0 | B173: 314 | C173: Cash, Shaggy | D173: ? | E173: ? | F173: ? | G173: ? | H173: ? | I173: ? | J173: ? | K173: ? | L173: ? | M173: ? | N173: ? | O173: ? | P173: ? | Q173: 314 | R173: Cash, Shaggy | S173: ? | T173: ? | U173: ? | V173: ? | W173: ? | X173: ? | Y173: ? | Z173: ? | AA173: ? | AB173: ? | AC173: ? | AD173: ? | AE173: ? | AF173: ? | AG173: ? | AH173: ? | AI173: =H$1*((-0.000002)*H173^3+0.00032*H173^2+(-0.0021)*H173)+I$1*((-0.000002)*I173^3+0.00032*I173^2+(-0.0021)*I173)+J$1*((-0.000002)*J173^3+0.00032*J173^2+(-0.0021)*J173)+K$1*((-0.000002)*K173^3+0.00032*K173^2+(-0.0021)*K173)+L$1*((-0.000002)*L173^3+0.00032*L173^2+(-0.0021)*L173) -> #VALUE! | AJ173: =M$1*((-0.000002)*M173^3+0.00032*M173^2+(-0.0021)*M173)+N$1*((-0.000002)*N173^3+0.00032*N173^2+(-0.0021)*N173)+O$1*((-0.000002)*O173^3+0.00032*O173^2+(-0.0021)*O173) -> #VALUE! | AK173: =IF(AA173<50,W$1*((-0.000002)*W173^3+0.00032*W173^2+(-0.0021)*W173)+X$1*((-0.000002)*X173^3+0.00032*X173^2+(-0.0021)*X173)+Y$1*((-0.000002)*Y173^3+0.00032*Y173^2+(-0.0021)*Y173)+Z$1*((-0.000002)*Z173^3+0.00032*Z173^2+(-0.0021)*Z173),X$2*((-0.000002)*X173^3+0.00032*X173^2+(-0.0021)*X173)+Y$2*((-0.000002)*Y173^3+0.00032*Y173^2+(-0.0021)*Y173)+Z$2*((-0.000002)*Z173^3+0.00032*Z173^2+(-0.0021)*Z173)+AA$2*((-0.000002)*AA173^3+0.00032*AA173^2+(-0.0021)*AA173)) -> #VALUE! | AL173: =AB$1*((-0.000002)*AB173^3+0.00032*AB173^2+(-0.0021)*AB173)+AC$1*((-0.000002)*AC173^3+0.00032*AC173^2+(-0.0021)*AC173) -> #VALUE! | AM173: =AD$1*((-0.000002)*AD173^3+0.00032*AD173^2+(-0.0021)*AD173)+AE$1*((-0.000002)*AE173^3+0.00032*AE173^2+(-0.0021)*AE173)+AF$1*((-0.000002)*AF173^3+0.00032*AF173^2+(-0.0021)*AF173)+AG$1*((-0.000002)*AG173^3+0.00032*AG173^2+(-0.0021)*AG173) -> #VALUE!
A174: =IFERROR((AI174*AI$3+AJ174*AJ$3+AK174*AK$3+AL174*AL$3+AM174*AM$3)*100/(AI$5*AI$3+AJ$5*AJ$3+AK$5*AK$3+AL$5*AL$3+AM$5*AM$3),0) -> 0 | B174: 315 | C174: Cannon, Philip | D174: ? | E174: ? | F174: ? | G174: ? | H174: ? | I174: ? | J174: ? | K174: ? | L174: ? | M174: ? | N174: ? | O174: ? | P174: ? | Q174: 315 | R174: Cannon, Philip | S174: ? | T174: ? | U174: ? | V174: ? | W174: ? | X174: ? | Y174: ? | Z174: ? | AA174: ? | AB174: ? | AC174: ? | AD174: ? | AE174: ? | AF174: ? | AG174: ? | AH174: ? | AI174: =H$1*((-0.000002)*H174^3+0.00032*H174^2+(-0.0021)*H174)+I$1*((-0.000002)*I174^3+0.00032*I174^2+(-0.0021)*I174)+J$1*((-0.000002)*J174^3+0.00032*J174^2+(-0.0021)*J174)+K$1*((-0.000002)*K174^3+0.00032*K174^2+(-0.0021)*K174)+L$1*((-0.000002)*L174^3+0.00032*L174^2+(-0.0021)*L174) -> #VALUE! | AJ174: =M$1*((-0.000002)*M174^3+0.00032*M174^2+(-0.0021)*M174)+N$1*((-0.000002)*N174^3+0.00032*N174^2+(-0.0021)*N174)+O$1*((-0.000002)*O174^3+0.00032*O174^2+(-0.0021)*O174) -> #VALUE! | AK174: =IF(AA174<50,W$1*((-0.000002)*W174^3+0.00032*W174^2+(-0.0021)*W174)+X$1*((-0.000002)*X174^3+0.00032*X174^2+(-0.0021)*X174)+Y$1*((-0.000002)*Y174^3+0.00032*Y174^2+(-0.0021)*Y174)+Z$1*((-0.000002)*Z174^3+0.00032*Z174^2+(-0.0021)*Z174),X$2*((-0.000002)*X174^3+0.00032*X174^2+(-0.0021)*X174)+Y$2*((-0.000002)*Y174^3+0.00032*Y174^2+(-0.0021)*Y174)+Z$2*((-0.000002)*Z174^3+0.00032*Z174^2+(-0.0021)*Z174)+AA$2*((-0.000002)*AA174^3+0.00032*AA174^2+(-0.0021)*AA174)) -> #VALUE! | AL174: =AB$1*((-0.000002)*AB174^3+0.00032*AB174^2+(-0.0021)*AB174)+AC$1*((-0.000002)*AC174^3+0.00032*AC174^2+(-0.0021)*AC174) -> #VALUE! | AM174: =AD$1*((-0.000002)*AD174^3+0.00032*AD174^2+(-0.0021)*AD174)+AE$1*((-0.000002)*AE174^3+0.00032*AE174^2+(-0.0021)*AE174)+AF$1*((-0.000002)*AF174^3+0.00032*AF174^2+(-0.0021)*AF174)+AG$1*((-0.000002)*AG174^3+0.00032*AG174^2+(-0.0021)*AG174) -> #VALUE!
A175: =IFERROR((AI175*AI$3+AJ175*AJ$3+AK175*AK$3+AL175*AL$3+AM175*AM$3)*100/(AI$5*AI$3+AJ$5*AJ$3+AK$5*AK$3+AL$5*AL$3+AM$5*AM$3),0) -> 0 | B175: 316 | C175: Fisher, Brad | D175: ? | E175: ? | F175: ? | G175: ? | H175: ? | I175: ? | J175: ? | K175: ? | L175: ? | M175: ? | N175: ? | O175: ? | P175: ? | Q175: 316 | R175: Fisher, Brad | S175: ? | T175: ? | U175: ? | V175: ? | W175: ? | X175: ? | Y175: ? | Z175: ? | AA175: ? | AB175: ? | AC175: ? | AD175: ? | AE175: ? | AF175: ? | AG175: ? | AH175: ? | AI175: =H$1*((-0.000002)*H175^3+0.00032*H175^2+(-0.0021)*H175)+I$1*((-0.000002)*I175^3+0.00032*I175^2+(-0.0021)*I175)+J$1*((-0.000002)*J175^3+0.00032*J175^2+(-0.0021)*J175)+K$1*((-0.000002)*K175^3+0.00032*K175^2+(-0.0021)*K175)+L$1*((-0.000002)*L175^3+0.00032*L175^2+(-0.0021)*L175) -> #VALUE! | AJ175: =M$1*((-0.000002)*M175^3+0.00032*M175^2+(-0.0021)*M175)+N$1*((-0.000002)*N175^3+0.00032*N175^2+(-0.0021)*N175)+O$1*((-0.000002)*O175^3+0.00032*O175^2+(-0.0021)*O175) -> #VALUE! | AK175: =IF(AA175<50,W$1*((-0.000002)*W175^3+0.00032*W175^2+(-0.0021)*W175)+X$1*((-0.000002)*X175^3+0.00032*X175^2+(-0.0021)*X175)+Y$1*((-0.000002)*Y175^3+0.00032*Y175^2+(-0.0021)*Y175)+Z$1*((-0.000002)*Z175^3+0.00032*Z175^2+(-0.0021)*Z175),X$2*((-0.000002)*X175^3+0.00032*X175^2+(-0.0021)*X175)+Y$2*((-0.000002)*Y175^3+0.00032*Y175^2+(-0.0021)*Y175)+Z$2*((-0.000002)*Z175^3+0.00032*Z175^2+(-0.0021)*Z175)+AA$2*((-0.000002)*AA175^3+0.00032*AA175^2+(-0.0021)*AA175)) -> #VALUE! | AL175: =AB$1*((-0.000002)*AB175^3+0.00032*AB175^2+(-0.0021)*AB175)+AC$1*((-0.000002)*AC175^3+0.00032*AC175^2+(-0.0021)*AC175) -> #VALUE! | AM175: =AD$1*((-0.000002)*AD175^3+0.00032*AD175^2+(-0.0021)*AD175)+AE$1*((-0.000002)*AE175^3+0.00032*AE175^2+(-0.0021)*AE175)+AF$1*((-0.000002)*AF175^3+0.00032*AF175^2+(-0.0021)*AF175)+AG$1*((-0.000002)*AG175^3+0.00032*AG175^2+(-0.0021)*AG175) -> #VALUE!
A176: =IFERROR((AI176*AI$3+AJ176*AJ$3+AK176*AK$3+AL176*AL$3+AM176*AM$3)*100/(AI$5*AI$3+AJ$5*AJ$3+AK$5*AK$3+AL$5*AL$3+AM$5*AM$3),0) -> 0 | B176: 317 | C176: Owen, Norberto | D176: ? | E176: ? | F176: ? | G176: ? | H176: ? | I176: ? | J176: ? | K176: ? | L176: ? | M176: ? | N176: ? | O176: ? | P176: ? | Q176: 317 | R176: Owen, Norberto | S176: ? | T176: ? | U176: ? | V176: ? | W176: ? | X176: ? | Y176: ? | Z176: ? | AA176: ? | AB176: ? | AC176: ? | AD176: ? | AE176: ? | AF176: ? | AG176: ? | AH176: ? | AI176: =H$1*((-0.000002)*H176^3+0.00032*H176^2+(-0.0021)*H176)+I$1*((-0.000002)*I176^3+0.00032*I176^2+(-0.0021)*I176)+J$1*((-0.000002)*J176^3+0.00032*J176^2+(-0.0021)*J176)+K$1*((-0.000002)*K176^3+0.00032*K176^2+(-0.0021)*K176)+L$1*((-0.000002)*L176^3+0.00032*L176^2+(-0.0021)*L176) -> #VALUE! | AJ176: =M$1*((-0.000002)*M176^3+0.00032*M176^2+(-0.0021)*M176)+N$1*((-0.000002)*N176^3+0.00032*N176^2+(-0.0021)*N176)+O$1*((-0.000002)*O176^3+0.00032*O176^2+(-0.0021)*O176) -> #VALUE! | AK176: =IF(AA176<50,W$1*((-0.000002)*W176^3+0.00032*W176^2+(-0.0021)*W176)+X$1*((-0.000002)*X176^3+0.00032*X176^2+(-0.0021)*X176)+Y$1*((-0.000002)*Y176^3+0.00032*Y176^2+(-0.0021)*Y176)+Z$1*((-0.000002)*Z176^3+0.00032*Z176^2+(-0.0021)*Z176),X$2*((-0.000002)*X176^3+0.00032*X176^2+(-0.0021)*X176)+Y$2*((-0.000002)*Y176^3+0.00032*Y176^2+(-0.0021)*Y176)+Z$2*((-0.000002)*Z176^3+0.00032*Z176^2+(-0.0021)*Z176)+AA$2*((-0.000002)*AA176^3+0.00032*AA176^2+(-0.0021)*AA176)) -> #VALUE! | AL176: =AB$1*((-0.000002)*AB176^3+0.00032*AB176^2+(-0.0021)*AB176)+AC$1*((-0.000002)*AC176^3+0.00032*AC176^2+(-0.0021)*AC176) -> #VALUE! | AM176: =AD$1*((-0.000002)*AD176^3+0.00032*AD176^2+(-0.0021)*AD176)+AE$1*((-0.000002)*AE176^3+0.00032*AE176^2+(-0.0021)*AE176)+AF$1*((-0.000002)*AF176^3+0.00032*AF176^2+(-0.0021)*AF176)+AG$1*((-0.000002)*AG176^3+0.00032*AG176^2+(-0.0021)*AG176) -> #VALUE!
A177: =IFERROR((AI177*AI$3+AJ177*AJ$3+AK177*AK$3+AL177*AL$3+AM177*AM$3)*100/(AI$5*AI$3+AJ$5*AJ$3+AK$5*AK$3+AL$5*AL$3+AM$5*AM$3),0) -> 0 | B177: 318 | C177: Fonville, Scot | D177: ? | E177: ? | F177: ? | G177: ? | H177: ? | I177: ? | J177: ? | K177: ? | L177: ? | M177: ? | N177: ? | O177: ? | P177: ? | Q177: 318 | R177: Fonville, Scot | S177: ? | T177: ? | U177: ? | V177: ? | W177: ? | X177: ? | Y177: ? | Z177: ? | AA177: ? | AB177: ? | AC177: ? | AD177: ? | AE177: ? | AF177: ? | AG177: ? | AH177: ? | AI177: =H$1*((-0.000002)*H177^3+0.00032*H177^2+(-0.0021)*H177)+I$1*((-0.000002)*I177^3+0.00032*I177^2+(-0.0021)*I177)+J$1*((-0.000002)*J177^3+0.00032*J177^2+(-0.0021)*J177)+K$1*((-0.000002)*K177^3+0.00032*K177^2+(-0.0021)*K177)+L$1*((-0.000002)*L177^3+0.00032*L177^2+(-0.0021)*L177) -> #VALUE! | AJ177: =M$1*((-0.000002)*M177^3+0.00032*M177^2+(-0.0021)*M177)+N$1*((-0.000002)*N177^3+0.00032*N177^2+(-0.0021)*N177)+O$1*((-0.000002)*O177^3+0.00032*O177^2+(-0.0021)*O177) -> #VALUE! | AK177: =IF(AA177<50,W$1*((-0.000002)*W177^3+0.00032*W177^2+(-0.0021)*W177)+X$1*((-0.000002)*X177^3+0.00032*X177^2+(-0.0021)*X177)+Y$1*((-0.000002)*Y177^3+0.00032*Y177^2+(-0.0021)*Y177)+Z$1*((-0.000002)*Z177^3+0.00032*Z177^2+(-0.0021)*Z177),X$2*((-0.000002)*X177^3+0.00032*X177^2+(-0.0021)*X177)+Y$2*((-0.000002)*Y177^3+0.00032*Y177^2+(-0.0021)*Y177)+Z$2*((-0.000002)*Z177^3+0.00032*Z177^2+(-0.0021)*Z177)+AA$2*((-0.000002)*AA177^3+0.00032*AA177^2+(-0.0021)*AA177)) -> #VALUE! | AL177: =AB$1*((-0.000002)*AB177^3+0.00032*AB177^2+(-0.0021)*AB177)+AC$1*((-0.000002)*AC177^3+0.00032*AC177^2+(-0.0021)*AC177) -> #VALUE! | AM177: =AD$1*((-0.000002)*AD177^3+0.00032*AD177^2+(-0.0021)*AD177)+AE$1*((-0.000002)*AE177^3+0.00032*AE177^2+(-0.0021)*AE177)+AF$1*((-0.000002)*AF177^3+0.00032*AF177^2+(-0.0021)*AF177)+AG$1*((-0.000002)*AG177^3+0.00032*AG177^2+(-0.0021)*AG177) -> #VALUE!
A178: =IFERROR((AI178*AI$3+AJ178*AJ$3+AK178*AK$3+AL178*AL$3+AM178*AM$3)*100/(AI$5*AI$3+AJ$5*AJ$3+AK$5*AK$3+AL$5*AL$3+AM$5*AM$3),0) -> 0 | B178: 319 | C178: Springer, Brad | D178: ? | E178: ? | F178: ? | G178: ? | H178: ? | I178: ? | J178: ? | K178: ? | L178: ? | M178: ? | N178: ? | O178: ? | P178: ? | Q178: 319 | R178: Springer, Brad | S178: ? | T178: ? | U178: ? | V178: ? | W178: ? | X178: ? | Y178: ? | Z178: ? | AA178: ? | AB178: ? | AC178: ? | AD178: ? | AE178: ? | AF178: ? | AG178: ? | AH178: ? | AI178: =H$1*((-0.000002)*H178^3+0.00032*H178^2+(-0.0021)*H178)+I$1*((-0.000002)*I178^3+0.00032*I178^2+(-0.0021)*I178)+J$1*((-0.000002)*J178^3+0.00032*J178^2+(-0.0021)*J178)+K$1*((-0.000002)*K178^3+0.00032*K178^2+(-0.0021)*K178)+L$1*((-0.000002)*L178^3+0.00032*L178^2+(-0.0021)*L178) -> #VALUE! | AJ178: =M$1*((-0.000002)*M178^3+0.00032*M178^2+(-0.0021)*M178)+N$1*((-0.000002)*N178^3+0.00032*N178^2+(-0.0021)*N178)+O$1*((-0.000002)*O178^3+0.00032*O178^2+(-0.0021)*O178) -> #VALUE! | AK178: =IF(AA178<50,W$1*((-0.000002)*W178^3+0.00032*W178^2+(-0.0021)*W178)+X$1*((-0.000002)*X178^3+0.00032*X178^2+(-0.0021)*X178)+Y$1*((-0.000002)*Y178^3+0.00032*Y178^2+(-0.0021)*Y178)+Z$1*((-0.000002)*Z178^3+0.00032*Z178^2+(-0.0021)*Z178),X$2*((-0.000002)*X178^3+0.00032*X178^2+(-0.0021)*X178)+Y$2*((-0.000002)*Y178^3+0.00032*Y178^2+(-0.0021)*Y178)+Z$2*((-0.000002)*Z178^3+0.00032*Z178^2+(-0.0021)*Z178)+AA$2*((-0.000002)*AA178^3+0.00032*AA178^2+(-0.0021)*AA178)) -> #VALUE! | AL178: =AB$1*((-0.000002)*AB178^3+0.00032*AB178^2+(-0.0021)*AB178)+AC$1*((-0.000002)*AC178^3+0.00032*AC178^2+(-0.0021)*AC178) -> #VALUE! | AM178: =AD$1*((-0.000002)*AD178^3+0.00032*AD178^2+(-0.0021)*AD178)+AE$1*((-0.000002)*AE178^3+0.00032*AE178^2+(-0.0021)*AE178)+AF$1*((-0.000002)*AF178^3+0.00032*AF178^2+(-0.0021)*AF178)+AG$1*((-0.000002)*AG178^3+0.00032*AG178^2+(-0.0021)*AG178) -> #VALUE!
A179: =IFERROR((AI179*AI$3+AJ179*AJ$3+AK179*AK$3+AL179*AL$3+AM179*AM$3)*100/(AI$5*AI$3+AJ$5*AJ$3+AK$5*AK$3+AL$5*AL$3+AM$5*AM$3),0) -> 0 | B179: 320 | C179: Lieber, Damian | D179: ? | E179: ? | F179: ? | G179: ? | H179: ? | I179: ? | J179: ? | K179: ? | L179: ? | M179: ? | N179: ? | O179: ? | P179: ? | Q179: 320 | R179: Lieber, Damian | S179: ? | T179: ? | U179: ? | V179: ? | W179: ? | X179: ? | Y179: ? | Z179: ? | AA179: ? | AB179: ? | AC179: ? | AD179: ? | AE179: ? | AF179: ? | AG179: ? | AH179: ? | AI179: =H$1*((-0.000002)*H179^3+0.00032*H179^2+(-0.0021)*H179)+I$1*((-0.000002)*I179^3+0.00032*I179^2+(-0.0021)*I179)+J$1*((-0.000002)*J179^3+0.00032*J179^2+(-0.0021)*J179)+K$1*((-0.000002)*K179^3+0.00032*K179^2+(-0.0021)*K179)+L$1*((-0.000002)*L179^3+0.00032*L179^2+(-0.0021)*L179) -> #VALUE! | AJ179: =M$1*((-0.000002)*M179^3+0.00032*M179^2+(-0.0021)*M179)+N$1*((-0.000002)*N179^3+0.00032*N179^2+(-0.0021)*N179)+O$1*((-0.000002)*O179^3+0.00032*O179^2+(-0.0021)*O179) -> #VALUE! | AK179: =IF(AA179<50,W$1*((-0.000002)*W179^3+0.00032*W179^2+(-0.0021)*W179)+X$1*((-0.000002)*X179^3+0.00032*X179^2+(-0.0021)*X179)+Y$1*((-0.000002)*Y179^3+0.00032*Y179^2+(-0.0021)*Y179)+Z$1*((-0.000002)*Z179^3+0.00032*Z179^2+(-0.0021)*Z179),X$2*((-0.000002)*X179^3+0.00032*X179^2+(-0.0021)*X179)+Y$2*((-0.000002)*Y179^3+0.00032*Y179^2+(-0.0021)*Y179)+Z$2*((-0.000002)*Z179^3+0.00032*Z179^2+(-0.0021)*Z179)+AA$2*((-0.000002)*AA179^3+0.00032*AA179^2+(-0.0021)*AA179)) -> #VALUE! | AL179: =AB$1*((-0.000002)*AB179^3+0.00032*AB179^2+(-0.0021)*AB179)+AC$1*((-0.000002)*AC179^3+0.00032*AC179^2+(-0.0021)*AC179) -> #VALUE! | AM179: =AD$1*((-0.000002)*AD179^3+0.00032*AD179^2+(-0.0021)*AD179)+AE$1*((-0.000002)*AE179^3+0.00032*AE179^2+(-0.0021)*AE179)+AF$1*((-0.000002)*AF179^3+0.00032*AF179^2+(-0.0021)*AF179)+AG$1*((-0.000002)*AG179^3+0.00032*AG179^2+(-0.0021)*AG179) -> #VALUE!
A180: =IFERROR((AI180*AI$3+AJ180*AJ$3+AK180*AK$3+AL180*AL$3+AM180*AM$3)*100/(AI$5*AI$3+AJ$5*AJ$3+AK$5*AK$3+AL$5*AL$3+AM$5*AM$3),0) -> 0 | B180: 321 | C180: Brown, Todd | D180: ? | E180: ? | F180: ? | G180: ? | H180: ? | I180: ? | J180: ? | K180: ? | L180: ? | M180: ? | N180: ? | O180: ? | P180: ? | Q180: 321 | R180: Brown, Todd | S180: ? | T180: ? | U180: ? | V180: ? | W180: ? | X180: ? | Y180: ? | Z180: ? | AA180: ? | AB180: ? | AC180: ? | AD180: ? | AE180: ? | AF180: ? | AG180: ? | AH180: ? | AI180: =H$1*((-0.000002)*H180^3+0.00032*H180^2+(-0.0021)*H180)+I$1*((-0.000002)*I180^3+0.00032*I180^2+(-0.0021)*I180)+J$1*((-0.000002)*J180^3+0.00032*J180^2+(-0.0021)*J180)+K$1*((-0.000002)*K180^3+0.00032*K180^2+(-0.0021)*K180)+L$1*((-0.000002)*L180^3+0.00032*L180^2+(-0.0021)*L180) -> #VALUE! | AJ180: =M$1*((-0.000002)*M180^3+0.00032*M180^2+(-0.0021)*M180)+N$1*((-0.000002)*N180^3+0.00032*N180^2+(-0.0021)*N180)+O$1*((-0.000002)*O180^3+0.00032*O180^2+(-0.0021)*O180) -> #VALUE! | AK180: =IF(AA180<50,W$1*((-0.000002)*W180^3+0.00032*W180^2+(-0.0021)*W180)+X$1*((-0.000002)*X180^3+0.00032*X180^2+(-0.0021)*X180)+Y$1*((-0.000002)*Y180^3+0.00032*Y180^2+(-0.0021)*Y180)+Z$1*((-0.000002)*Z180^3+0.00032*Z180^2+(-0.0021)*Z180),X$2*((-0.000002)*X180^3+0.00032*X180^2+(-0.0021)*X180)+Y$2*((-0.000002)*Y180^3+0.00032*Y180^2+(-0.0021)*Y180)+Z$2*((-0.000002)*Z180^3+0.00032*Z180^2+(-0.0021)*Z180)+AA$2*((-0.000002)*AA180^3+0.00032*AA180^2+(-0.0021)*AA180)) -> #VALUE! | AL180: =AB$1*((-0.000002)*AB180^3+0.00032*AB180^2+(-0.0021)*AB180)+AC$1*((-0.000002)*AC180^3+0.00032*AC180^2+(-0.0021)*AC180) -> #VALUE! | AM180: =AD$1*((-0.000002)*AD180^3+0.00032*AD180^2+(-0.0021)*AD180)+AE$1*((-0.000002)*AE180^3+0.00032*AE180^2+(-0.0021)*AE180)+AF$1*((-0.000002)*AF180^3+0.00032*AF180^2+(-0.0021)*AF180)+AG$1*((-0.000002)*AG180^3+0.00032*AG180^2+(-0.0021)*AG180) -> #VALUE!
... A359: =IFERROR((AI359*AI$3+AJ359*AJ$3+AK359*AK$3+AL359*AL$3+AM359*AM$3)*100/(AI$5*AI$3+AJ$5*AJ$3+AK$5*AK$3+AL$5*AL$3+AM$5*AM$3),0) -> 0 | B359: 500 | C359: James, Yunel | D359: ? | E359: ? | F359: ? | G359: ? | H359: ? | I359: ? | J359: ? | K359: ? | L359: ? | M359: ? | N359: ? | O359: ? | P359: ? | Q359: 500 | R359: James, Yunel | S359: ? | T359: ? | U359: ? | V359: ? | W359: ? | X359: ? | Y359: ? | Z359: ? | AA359: ? | AB359: ? | AC359: ? | AD359: ? | AE359: ? | AF359: ? | AG359: ? | AH359: ? | AI359: =H$1*((-0.000002)*H359^3+0.00032*H359^2+(-0.0021)*H359)+I$1*((-0.000002)*I359^3+0.00032*I359^2+(-0.0021)*I359)+J$1*((-0.000002)*J359^3+0.00032*J359^2+(-0.0021)*J359)+K$1*((-0.000002)*K359^3+0.00032*K359^2+(-0.0021)*K359)+L$1*((-0.000002)*L359^3+0.00032*L359^2+(-0.0021)*L359) -> #VALUE! | AJ359: =M$1*((-0.000002)*M359^3+0.00032*M359^2+(-0.0021)*M359)+N$1*((-0.000002)*N359^3+0.00032*N359^2+(-0.0021)*N359)+O$1*((-0.000002)*O359^3+0.00032*O359^2+(-0.0021)*O359) -> #VALUE! | AK359: =IF(AA359<50,W$1*((-0.000002)*W359^3+0.00032*W359^2+(-0.0021)*W359)+X$1*((-0.000002)*X359^3+0.00032*X359^2+(-0.0021)*X359)+Y$1*((-0.000002)*Y359^3+0.00032*Y359^2+(-0.0021)*Y359)+Z$1*((-0.000002)*Z359^3+0.00032*Z359^2+(-0.0021)*Z359),X$2*((-0.000002)*X359^3+0.00032*X359^2+(-0.0021)*X359)+Y$2*((-0.000002)*Y359^3+0.00032*Y359^2+(-0.0021)*Y359)+Z$2*((-0.000002)*Z359^3+0.00032*Z359^2+(-0.0021)*Z359)+AA$2*((-0.000002)*AA359^3+0.00032*AA359^2+(-0.0021)*AA359)) -> #VALUE! | AL359: =AB$1*((-0.000002)*AB359^3+0.00032*AB359^2+(-0.0021)*AB359)+AC$1*((-0.000002)*AC359^3+0.00032*AC359^2+(-0.0021)*AC359) -> #VALUE! | AM359: =AD$1*((-0.000002)*AD359^3+0.00032*AD359^2+(-0.0021)*AD359)+AE$1*((-0.000002)*AE359^3+0.00032*AE359^2+(-0.0021)*AE359)+AF$1*((-0.000002)*AF359^3+0.00032*AF359^2+(-0.0021)*AF359)+AG$1*((-0.000002)*AG359^3+0.00032*AG359^2+(-0.0021)*AG359) -> #VALUE!
A360: =(AI360*AI$3+AJ360*AJ$3+AK360*AK$3+AL360*AL$3+AM360*AM$3)*100/(AI$5*AI$3+AJ$5*AJ$3+AK$5*AK$3+AL$5*AL$3+AM$5*AM$3) -> 0 | AI360: =H$1*((-0.000002)*H360^3+0.00032*H360^2+(-0.0021)*H360)+I$1*((-0.000002)*I360^3+0.00032*I360^2+(-0.0021)*I360)+J$1*((-0.000002)*J360^3+0.00032*J360^2+(-0.0021)*J360)+K$1*((-0.000002)*K360^3+0.00032*K360^2+(-0.0021)*K360)+L$1*((-0.000002)*L360^3+0.00032*L360^2+(-0.0021)*L360) -> 0 | AJ360: =M$1*((-0.000002)*M360^3+0.00032*M360^2+(-0.0021)*M360)+N$1*((-0.000002)*N360^3+0.00032*N360^2+(-0.0021)*N360)+O$1*((-0.000002)*O360^3+0.00032*O360^2+(-0.0021)*O360) -> 0 | AK360: =IF(AA360<50,W$1*((-0.000002)*W360^3+0.00032*W360^2+(-0.0021)*W360)+X$1*((-0.000002)*X360^3+0.00032*X360^2+(-0.0021)*X360)+Y$1*((-0.000002)*Y360^3+0.00032*Y360^2+(-0.0021)*Y360)+Z$1*((-0.000002)*Z360^3+0.00032*Z360^2+(-0.0021)*Z360),X$2*((-0.000002)*X360^3+0.00032*X360^2+(-0.0021)*X360)+Y$2*((-0.000002)*Y360^3+0.00032*Y360^2+(-0.0021)*Y360)+Z$2*((-0.000002)*Z360^3+0.00032*Z360^2+(-0.0021)*Z360)+AA$2*((-0.000002)*AA360^3+0.00032*AA360^2+(-0.0021)*AA360)) -> 0 | AL360: =AB$1*((-0.000002)*AB360^3+0.00032*AB360^2+(-0.0021)*AB360)+AC$1*((-0.000002)*AC360^3+0.00032*AC360^2+(-0.0021)*AC360) -> 0 | AM360: =AD$1*((-0.000002)*AD360^3+0.00032*AD360^2+(-0.0021)*AD360)+AE$1*((-0.000002)*AE360^3+0.00032*AE360^2+(-0.0021)*AE360)+AF$1*((-0.000002)*AF360^3+0.00032*AF360^2+(-0.0021)*AF360)+AG$1*((-0.000002)*AG360^3+0.00032*AG360^2+(-0.0021)*AG360) -> 0
A361: =(AI361*AI$3+AJ361*AJ$3+AK361*AK$3+AL361*AL$3+AM361*AM$3)*100/(AI$5*AI$3+AJ$5*AJ$3+AK$5*AK$3+AL$5*AL$3+AM$5*AM$3) -> 0 | AI361: =H$1*((-0.000002)*H361^3+0.00032*H361^2+(-0.0021)*H361)+I$1*((-0.000002)*I361^3+0.00032*I361^2+(-0.0021)*I361)+J$1*((-0.000002)*J361^3+0.00032*J361^2+(-0.0021)*J361)+K$1*((-0.000002)*K361^3+0.00032*K361^2+(-0.0021)*K361)+L$1*((-0.000002)*L361^3+0.00032*L361^2+(-0.0021)*L361) -> 0 | AJ361: =M$1*((-0.000002)*M361^3+0.00032*M361^2+(-0.0021)*M361)+N$1*((-0.000002)*N361^3+0.00032*N361^2+(-0.0021)*N361)+O$1*((-0.000002)*O361^3+0.00032*O361^2+(-0.0021)*O361) -> 0 | AK361: =IF(AA361<50,W$1*((-0.000002)*W361^3+0.00032*W361^2+(-0.0021)*W361)+X$1*((-0.000002)*X361^3+0.00032*X361^2+(-0.0021)*X361)+Y$1*((-0.000002)*Y361^3+0.00032*Y361^2+(-0.0021)*Y361)+Z$1*((-0.000002)*Z361^3+0.00032*Z361^2+(-0.0021)*Z361),X$2*((-0.000002)*X361^3+0.00032*X361^2+(-0.0021)*X361)+Y$2*((-0.000002)*Y361^3+0.00032*Y361^2+(-0.0021)*Y361)+Z$2*((-0.000002)*Z361^3+0.00032*Z361^2+(-0.0021)*Z361)+AA$2*((-0.000002)*AA361^3+0.00032*AA361^2+(-0.0021)*AA361)) -> 0 | AL361: =AB$1*((-0.000002)*AB361^3+0.00032*AB361^2+(-0.0021)*AB361)+AC$1*((-0.000002)*AC361^3+0.00032*AC361^2+(-0.0021)*AC361) -> 0 | AM361: =AD$1*((-0.000002)*AD361^3+0.00032*AD361^2+(-0.0021)*AD361)+AE$1*((-0.000002)*AE361^3+0.00032*AE361^2+(-0.0021)*AE361)+AF$1*((-0.000002)*AF361^3+0.00032*AF361^2+(-0.0021)*AF361)+AG$1*((-0.000002)*AG361^3+0.00032*AG361^2+(-0.0021)*AG361) -> 0
A362: =(AI362*AI$3+AJ362*AJ$3+AK362*AK$3+AL362*AL$3+AM362*AM$3)*100/(AI$5*AI$3+AJ$5*AJ$3+AK$5*AK$3+AL$5*AL$3+AM$5*AM$3) -> 0 | AI362: =H$1*((-0.000002)*H362^3+0.00032*H362^2+(-0.0021)*H362)+I$1*((-0.000002)*I362^3+0.00032*I362^2+(-0.0021)*I362)+J$1*((-0.000002)*J362^3+0.00032*J362^2+(-0.0021)*J362)+K$1*((-0.000002)*K362^3+0.00032*K362^2+(-0.0021)*K362)+L$1*((-0.000002)*L362^3+0.00032*L362^2+(-0.0021)*L362) -> 0 | AJ362: =M$1*((-0.000002)*M362^3+0.00032*M362^2+(-0.0021)*M362)+N$1*((-0.000002)*N362^3+0.00032*N362^2+(-0.0021)*N362)+O$1*((-0.000002)*O362^3+0.00032*O362^2+(-0.0021)*O362) -> 0 | AK362: =IF(AA362<50,W$1*((-0.000002)*W362^3+0.00032*W362^2+(-0.0021)*W362)+X$1*((-0.000002)*X362^3+0.00032*X362^2+(-0.0021)*X362)+Y$1*((-0.000002)*Y362^3+0.00032*Y362^2+(-0.0021)*Y362)+Z$1*((-0.000002)*Z362^3+0.00032*Z362^2+(-0.0021)*Z362),X$2*((-0.000002)*X362^3+0.00032*X362^2+(-0.0021)*X362)+Y$2*((-0.000002)*Y362^3+0.00032*Y362^2+(-0.0021)*Y362)+Z$2*((-0.000002)*Z362^3+0.00032*Z362^2+(-0.0021)*Z362)+AA$2*((-0.000002)*AA362^3+0.00032*AA362^2+(-0.0021)*AA362)) -> 0 | AL362: =AB$1*((-0.000002)*AB362^3+0.00032*AB362^2+(-0.0021)*AB362)+AC$1*((-0.000002)*AC362^3+0.00032*AC362^2+(-0.0021)*AC362) -> 0 | AM362: =AD$1*((-0.000002)*AD362^3+0.00032*AD362^2+(-0.0021)*AD362)+AE$1*((-0.000002)*AE362^3+0.00032*AE362^2+(-0.0021)*AE362)+AF$1*((-0.000002)*AF362^3+0.00032*AF362^2+(-0.0021)*AF362)+AG$1*((-0.000002)*AG362^3+0.00032*AG362^2+(-0.0021)*AG362) -> 0
A363: =(AI363*AI$3+AJ363*AJ$3+AK363*AK$3+AL363*AL$3+AM363*AM$3)*100/(AI$5*AI$3+AJ$5*AJ$3+AK$5*AK$3+AL$5*AL$3+AM$5*AM$3) -> 0 | AI363: =H$1*((-0.000002)*H363^3+0.00032*H363^2+(-0.0021)*H363)+I$1*((-0.000002)*I363^3+0.00032*I363^2+(-0.0021)*I363)+J$1*((-0.000002)*J363^3+0.00032*J363^2+(-0.0021)*J363)+K$1*((-0.000002)*K363^3+0.00032*K363^2+(-0.0021)*K363)+L$1*((-0.000002)*L363^3+0.00032*L363^2+(-0.0021)*L363) -> 0 | AJ363: =M$1*((-0.000002)*M363^3+0.00032*M363^2+(-0.0021)*M363)+N$1*((-0.000002)*N363^3+0.00032*N363^2+(-0.0021)*N363)+O$1*((-0.000002)*O363^3+0.00032*O363^2+(-0.0021)*O363) -> 0 | AK363: =IF(AA363<50,W$1*((-0.000002)*W363^3+0.00032*W363^2+(-0.0021)*W363)+X$1*((-0.000002)*X363^3+0.00032*X363^2+(-0.0021)*X363)+Y$1*((-0.000002)*Y363^3+0.00032*Y363^2+(-0.0021)*Y363)+Z$1*((-0.000002)*Z363^3+0.00032*Z363^2+(-0.0021)*Z363),X$2*((-0.000002)*X363^3+0.00032*X363^2+(-0.0021)*X363)+Y$2*((-0.000002)*Y363^3+0.00032*Y363^2+(-0.0021)*Y363)+Z$2*((-0.000002)*Z363^3+0.00032*Z363^2+(-0.0021)*Z363)+AA$2*((-0.000002)*AA363^3+0.00032*AA363^2+(-0.0021)*AA363)) -> 0 | AL363: =AB$1*((-0.000002)*AB363^3+0.00032*AB363^2+(-0.0021)*AB363)+AC$1*((-0.000002)*AC363^3+0.00032*AC363^2+(-0.0021)*AC363) -> 0 | AM363: =AD$1*((-0.000002)*AD363^3+0.00032*AD363^2+(-0.0021)*AD363)+AE$1*((-0.000002)*AE363^3+0.00032*AE363^2+(-0.0021)*AE363)+AF$1*((-0.000002)*AF363^3+0.00032*AF363^2+(-0.0021)*AF363)+AG$1*((-0.000002)*AG363^3+0.00032*AG363^2+(-0.0021)*AG363) -> 0
A364: =(AI364*AI$3+AJ364*AJ$3+AK364*AK$3+AL364*AL$3+AM364*AM$3)*100/(AI$5*AI$3+AJ$5*AJ$3+AK$5*AK$3+AL$5*AL$3+AM$5*AM$3) -> 0 | AI364: =H$1*((-0.000002)*H364^3+0.00032*H364^2+(-0.0021)*H364)+I$1*((-0.000002)*I364^3+0.00032*I364^2+(-0.0021)*I364)+J$1*((-0.000002)*J364^3+0.00032*J364^2+(-0.0021)*J364)+K$1*((-0.000002)*K364^3+0.00032*K364^2+(-0.0021)*K364)+L$1*((-0.000002)*L364^3+0.00032*L364^2+(-0.0021)*L364) -> 0 | AJ364: =M$1*((-0.000002)*M364^3+0.00032*M364^2+(-0.0021)*M364)+N$1*((-0.000002)*N364^3+0.00032*N364^2+(-0.0021)*N364)+O$1*((-0.000002)*O364^3+0.00032*O364^2+(-0.0021)*O364) -> 0 | AK364: =IF(AA364<50,W$1*((-0.000002)*W364^3+0.00032*W364^2+(-0.0021)*W364)+X$1*((-0.000002)*X364^3+0.00032*X364^2+(-0.0021)*X364)+Y$1*((-0.000002)*Y364^3+0.00032*Y364^2+(-0.0021)*Y364)+Z$1*((-0.000002)*Z364^3+0.00032*Z364^2+(-0.0021)*Z364),X$2*((-0.000002)*X364^3+0.00032*X364^2+(-0.0021)*X364)+Y$2*((-0.000002)*Y364^3+0.00032*Y364^2+(-0.0021)*Y364)+Z$2*((-0.000002)*Z364^3+0.00032*Z364^2+(-0.0021)*Z364)+AA$2*((-0.000002)*AA364^3+0.00032*AA364^2+(-0.0021)*AA364)) -> 0 | AL364: =AB$1*((-0.000002)*AB364^3+0.00032*AB364^2+(-0.0021)*AB364)+AC$1*((-0.000002)*AC364^3+0.00032*AC364^2+(-0.0021)*AC364) -> 0 | AM364: =AD$1*((-0.000002)*AD364^3+0.00032*AD364^2+(-0.0021)*AD364)+AE$1*((-0.000002)*AE364^3+0.00032*AE364^2+(-0.0021)*AE364)+AF$1*((-0.000002)*AF364^3+0.00032*AF364^2+(-0.0021)*AF364)+AG$1*((-0.000002)*AG364^3+0.00032*AG364^2+(-0.0021)*AG364) -> 0
A365: =(AI365*AI$3+AJ365*AJ$3+AK365*AK$3+AL365*AL$3+AM365*AM$3)*100/(AI$5*AI$3+AJ$5*AJ$3+AK$5*AK$3+AL$5*AL$3+AM$5*AM$3) -> 0 | AI365: =H$1*((-0.000002)*H365^3+0.00032*H365^2+(-0.0021)*H365)+I$1*((-0.000002)*I365^3+0.00032*I365^2+(-0.0021)*I365)+J$1*((-0.000002)*J365^3+0.00032*J365^2+(-0.0021)*J365)+K$1*((-0.000002)*K365^3+0.00032*K365^2+(-0.0021)*K365)+L$1*((-0.000002)*L365^3+0.00032*L365^2+(-0.0021)*L365) -> 0 | AJ365: =M$1*((-0.000002)*M365^3+0.00032*M365^2+(-0.0021)*M365)+N$1*((-0.000002)*N365^3+0.00032*N365^2+(-0.0021)*N365)+O$1*((-0.000002)*O365^3+0.00032*O365^2+(-0.0021)*O365) -> 0 | AK365: =IF(AA365<50,W$1*((-0.000002)*W365^3+0.00032*W365^2+(-0.0021)*W365)+X$1*((-0.000002)*X365^3+0.00032*X365^2+(-0.0021)*X365)+Y$1*((-0.000002)*Y365^3+0.00032*Y365^2+(-0.0021)*Y365)+Z$1*((-0.000002)*Z365^3+0.00032*Z365^2+(-0.0021)*Z365),X$2*((-0.000002)*X365^3+0.00032*X365^2+(-0.0021)*X365)+Y$2*((-0.000002)*Y365^3+0.00032*Y365^2+(-0.0021)*Y365)+Z$2*((-0.000002)*Z365^3+0.00032*Z365^2+(-0.0021)*Z365)+AA$2*((-0.000002)*AA365^3+0.00032*AA365^2+(-0.0021)*AA365)) -> 0 | AL365: =AB$1*((-0.000002)*AB365^3+0.00032*AB365^2+(-0.0021)*AB365)+AC$1*((-0.000002)*AC365^3+0.00032*AC365^2+(-0.0021)*AC365) -> 0 | AM365: =AD$1*((-0.000002)*AD365^3+0.00032*AD365^2+(-0.0021)*AD365)+AE$1*((-0.000002)*AE365^3+0.00032*AE365^2+(-0.0021)*AE365)+AF$1*((-0.000002)*AF365^3+0.00032*AF365^2+(-0.0021)*AF365)+AG$1*((-0.000002)*AG365^3+0.00032*AG365^2+(-0.0021)*AG365) -> 0
A366: =(AI366*AI$3+AJ366*AJ$3+AK366*AK$3+AL366*AL$3+AM366*AM$3)*100/(AI$5*AI$3+AJ$5*AJ$3+AK$5*AK$3+AL$5*AL$3+AM$5*AM$3) -> 0 | AI366: =H$1*((-0.000002)*H366^3+0.00032*H366^2+(-0.0021)*H366)+I$1*((-0.000002)*I366^3+0.00032*I366^2+(-0.0021)*I366)+J$1*((-0.000002)*J366^3+0.00032*J366^2+(-0.0021)*J366)+K$1*((-0.000002)*K366^3+0.00032*K366^2+(-0.0021)*K366)+L$1*((-0.000002)*L366^3+0.00032*L366^2+(-0.0021)*L366) -> 0 | AJ366: =M$1*((-0.000002)*M366^3+0.00032*M366^2+(-0.0021)*M366)+N$1*((-0.000002)*N366^3+0.00032*N366^2+(-0.0021)*N366)+O$1*((-0.000002)*O366^3+0.00032*O366^2+(-0.0021)*O366) -> 0 | AK366: =IF(AA366<50,W$1*((-0.000002)*W366^3+0.00032*W366^2+(-0.0021)*W366)+X$1*((-0.000002)*X366^3+0.00032*X366^2+(-0.0021)*X366)+Y$1*((-0.000002)*Y366^3+0.00032*Y366^2+(-0.0021)*Y366)+Z$1*((-0.000002)*Z366^3+0.00032*Z366^2+(-0.0021)*Z366),X$2*((-0.000002)*X366^3+0.00032*X366^2+(-0.0021)*X366)+Y$2*((-0.000002)*Y366^3+0.00032*Y366^2+(-0.0021)*Y366)+Z$2*((-0.000002)*Z366^3+0.00032*Z366^2+(-0.0021)*Z366)+AA$2*((-0.000002)*AA366^3+0.00032*AA366^2+(-0.0021)*AA366)) -> 0 | AL366: =AB$1*((-0.000002)*AB366^3+0.00032*AB366^2+(-0.0021)*AB366)+AC$1*((-0.000002)*AC366^3+0.00032*AC366^2+(-0.0021)*AC366) -> 0 | AM366: =AD$1*((-0.000002)*AD366^3+0.00032*AD366^2+(-0.0021)*AD366)+AE$1*((-0.000002)*AE366^3+0.00032*AE366^2+(-0.0021)*AE366)+AF$1*((-0.000002)*AF366^3+0.00032*AF366^2+(-0.0021)*AF366)+AG$1*((-0.000002)*AG366^3+0.00032*AG366^2+(-0.0021)*AG366) -> 0
A367: =(AI367*AI$3+AJ367*AJ$3+AK367*AK$3+AL367*AL$3+AM367*AM$3)*100/(AI$5*AI$3+AJ$5*AJ$3+AK$5*AK$3+AL$5*AL$3+AM$5*AM$3) -> 0 | AI367: =H$1*((-0.000002)*H367^3+0.00032*H367^2+(-0.0021)*H367)+I$1*((-0.000002)*I367^3+0.00032*I367^2+(-0.0021)*I367)+J$1*((-0.000002)*J367^3+0.00032*J367^2+(-0.0021)*J367)+K$1*((-0.000002)*K367^3+0.00032*K367^2+(-0.0021)*K367)+L$1*((-0.000002)*L367^3+0.00032*L367^2+(-0.0021)*L367) -> 0 | AJ367: =M$1*((-0.000002)*M367^3+0.00032*M367^2+(-0.0021)*M367)+N$1*((-0.000002)*N367^3+0.00032*N367^2+(-0.0021)*N367)+O$1*((-0.000002)*O367^3+0.00032*O367^2+(-0.0021)*O367) -> 0 | AK367: =IF(AA367<50,W$1*((-0.000002)*W367^3+0.00032*W367^2+(-0.0021)*W367)+X$1*((-0.000002)*X367^3+0.00032*X367^2+(-0.0021)*X367)+Y$1*((-0.000002)*Y367^3+0.00032*Y367^2+(-0.0021)*Y367)+Z$1*((-0.000002)*Z367^3+0.00032*Z367^2+(-0.0021)*Z367),X$2*((-0.000002)*X367^3+0.00032*X367^2+(-0.0021)*X367)+Y$2*((-0.000002)*Y367^3+0.00032*Y367^2+(-0.0021)*Y367)+Z$2*((-0.000002)*Z367^3+0.00032*Z367^2+(-0.0021)*Z367)+AA$2*((-0.000002)*AA367^3+0.00032*AA367^2+(-0.0021)*AA367)) -> 0 | AL367: =AB$1*((-0.000002)*AB367^3+0.00032*AB367^2+(-0.0021)*AB367)+AC$1*((-0.000002)*AC367^3+0.00032*AC367^2+(-0.0021)*AC367) -> 0 | AM367: =AD$1*((-0.000002)*AD367^3+0.00032*AD367^2+(-0.0021)*AD367)+AE$1*((-0.000002)*AE367^3+0.00032*AE367^2+(-0.0021)*AE367)+AF$1*((-0.000002)*AF367^3+0.00032*AF367^2+(-0.0021)*AF367)+AG$1*((-0.000002)*AG367^3+0.00032*AG367^2+(-0.0021)*AG367) -> 0
A368: =(AI368*AI$3+AJ368*AJ$3+AK368*AK$3+AL368*AL$3+AM368*AM$3)*100/(AI$5*AI$3+AJ$5*AJ$3+AK$5*AK$3+AL$5*AL$3+AM$5*AM$3) -> 0 | AI368: =H$1*((-0.000002)*H368^3+0.00032*H368^2+(-0.0021)*H368)+I$1*((-0.000002)*I368^3+0.00032*I368^2+(-0.0021)*I368)+J$1*((-0.000002)*J368^3+0.00032*J368^2+(-0.0021)*J368)+K$1*((-0.000002)*K368^3+0.00032*K368^2+(-0.0021)*K368)+L$1*((-0.000002)*L368^3+0.00032*L368^2+(-0.0021)*L368) -> 0 | AJ368: =M$1*((-0.000002)*M368^3+0.00032*M368^2+(-0.0021)*M368)+N$1*((-0.000002)*N368^3+0.00032*N368^2+(-0.0021)*N368)+O$1*((-0.000002)*O368^3+0.00032*O368^2+(-0.0021)*O368) -> 0 | AK368: =IF(AA368<50,W$1*((-0.000002)*W368^3+0.00032*W368^2+(-0.0021)*W368)+X$1*((-0.000002)*X368^3+0.00032*X368^2+(-0.0021)*X368)+Y$1*((-0.000002)*Y368^3+0.00032*Y368^2+(-0.0021)*Y368)+Z$1*((-0.000002)*Z368^3+0.00032*Z368^2+(-0.0021)*Z368),X$2*((-0.000002)*X368^3+0.00032*X368^2+(-0.0021)*X368)+Y$2*((-0.000002)*Y368^3+0.00032*Y368^2+(-0.0021)*Y368)+Z$2*((-0.000002)*Z368^3+0.00032*Z368^2+(-0.0021)*Z368)+AA$2*((-0.000002)*AA368^3+0.00032*AA368^2+(-0.0021)*AA368)) -> 0 | AL368: =AB$1*((-0.000002)*AB368^3+0.00032*AB368^2+(-0.0021)*AB368)+AC$1*((-0.000002)*AC368^3+0.00032*AC368^2+(-0.0021)*AC368) -> 0 | AM368: =AD$1*((-0.000002)*AD368^3+0.00032*AD368^2+(-0.0021)*AD368)+AE$1*((-0.000002)*AE368^3+0.00032*AE368^2+(-0.0021)*AE368)+AF$1*((-0.000002)*AF368^3+0.00032*AF368^2+(-0.0021)*AF368)+AG$1*((-0.000002)*AG368^3+0.00032*AG368^2+(-0.0021)*AG368) -> 0
A369: =(AI369*AI$3+AJ369*AJ$3+AK369*AK$3+AL369*AL$3+AM369*AM$3)*100/(AI$5*AI$3+AJ$5*AJ$3+AK$5*AK$3+AL$5*AL$3+AM$5*AM$3) -> 0 | AI369: =H$1*((-0.000002)*H369^3+0.00032*H369^2+(-0.0021)*H369)+I$1*((-0.000002)*I369^3+0.00032*I369^2+(-0.0021)*I369)+J$1*((-0.000002)*J369^3+0.00032*J369^2+(-0.0021)*J369)+K$1*((-0.000002)*K369^3+0.00032*K369^2+(-0.0021)*K369)+L$1*((-0.000002)*L369^3+0.00032*L369^2+(-0.0021)*L369) -> 0 | AJ369: =M$1*((-0.000002)*M369^3+0.00032*M369^2+(-0.0021)*M369)+N$1*((-0.000002)*N369^3+0.00032*N369^2+(-0.0021)*N369)+O$1*((-0.000002)*O369^3+0.00032*O369^2+(-0.0021)*O369) -> 0 | AK369: =IF(AA369<50,W$1*((-0.000002)*W369^3+0.00032*W369^2+(-0.0021)*W369)+X$1*((-0.000002)*X369^3+0.00032*X369^2+(-0.0021)*X369)+Y$1*((-0.000002)*Y369^3+0.00032*Y369^2+(-0.0021)*Y369)+Z$1*((-0.000002)*Z369^3+0.00032*Z369^2+(-0.0021)*Z369),X$2*((-0.000002)*X369^3+0.00032*X369^2+(-0.0021)*X369)+Y$2*((-0.000002)*Y369^3+0.00032*Y369^2+(-0.0021)*Y369)+Z$2*((-0.000002)*Z369^3+0.00032*Z369^2+(-0.0021)*Z369)+AA$2*((-0.000002)*AA369^3+0.00032*AA369^2+(-0.0021)*AA369)) -> 0 | AL369: =AB$1*((-0.000002)*AB369^3+0.00032*AB369^2+(-0.0021)*AB369)+AC$1*((-0.000002)*AC369^3+0.00032*AC369^2+(-0.0021)*AC369) -> 0 | AM369: =AD$1*((-0.000002)*AD369^3+0.00032*AD369^2+(-0.0021)*AD369)+AE$1*((-0.000002)*AE369^3+0.00032*AE369^2+(-0.0021)*AE369)+AF$1*((-0.000002)*AF369^3+0.00032*AF369^2+(-0.0021)*AF369)+AG$1*((-0.000002)*AG369^3+0.00032*AG369^2+(-0.0021)*AG369) -> 0
A370: =(AI370*AI$3+AJ370*AJ$3+AK370*AK$3+AL370*AL$3+AM370*AM$3)*100/(AI$5*AI$3+AJ$5*AJ$3+AK$5*AK$3+AL$5*AL$3+AM$5*AM$3) -> 0 | AI370: =H$1*((-0.000002)*H370^3+0.00032*H370^2+(-0.0021)*H370)+I$1*((-0.000002)*I370^3+0.00032*I370^2+(-0.0021)*I370)+J$1*((-0.000002)*J370^3+0.00032*J370^2+(-0.0021)*J370)+K$1*((-0.000002)*K370^3+0.00032*K370^2+(-0.0021)*K370)+L$1*((-0.000002)*L370^3+0.00032*L370^2+(-0.0021)*L370) -> 0 | AJ370: =M$1*((-0.000002)*M370^3+0.00032*M370^2+(-0.0021)*M370)+N$1*((-0.000002)*N370^3+0.00032*N370^2+(-0.0021)*N370)+O$1*((-0.000002)*O370^3+0.00032*O370^2+(-0.0021)*O370) -> 0 | AK370: =IF(AA370<50,W$1*((-0.000002)*W370^3+0.00032*W370^2+(-0.0021)*W370)+X$1*((-0.000002)*X370^3+0.00032*X370^2+(-0.0021)*X370)+Y$1*((-0.000002)*Y370^3+0.00032*Y370^2+(-0.0021)*Y370)+Z$1*((-0.000002)*Z370^3+0.00032*Z370^2+(-0.0021)*Z370),X$2*((-0.000002)*X370^3+0.00032*X370^2+(-0.0021)*X370)+Y$2*((-0.000002)*Y370^3+0.00032*Y370^2+(-0.0021)*Y370)+Z$2*((-0.000002)*Z370^3+0.00032*Z370^2+(-0.0021)*Z370)+AA$2*((-0.000002)*AA370^3+0.00032*AA370^2+(-0.0021)*AA370)) -> 0 | AL370: =AB$1*((-0.000002)*AB370^3+0.00032*AB370^2+(-0.0021)*AB370)+AC$1*((-0.000002)*AC370^3+0.00032*AC370^2+(-0.0021)*AC370) -> 0 | AM370: =AD$1*((-0.000002)*AD370^3+0.00032*AD370^2+(-0.0021)*AD370)+AE$1*((-0.000002)*AE370^3+0.00032*AE370^2+(-0.0021)*AE370)+AF$1*((-0.000002)*AF370^3+0.00032*AF370^2+(-0.0021)*AF370)+AG$1*((-0.000002)*AG370^3+0.00032*AG370^2+(-0.0021)*AG370) -> 0
A371: =(AI371*AI$3+AJ371*AJ$3+AK371*AK$3+AL371*AL$3+AM371*AM$3)*100/(AI$5*AI$3+AJ$5*AJ$3+AK$5*AK$3+AL$5*AL$3+AM$5*AM$3) -> 0 | AI371: =H$1*((-0.000002)*H371^3+0.00032*H371^2+(-0.0021)*H371)+I$1*((-0.000002)*I371^3+0.00032*I371^2+(-0.0021)*I371)+J$1*((-0.000002)*J371^3+0.00032*J371^2+(-0.0021)*J371)+K$1*((-0.000002)*K371^3+0.00032*K371^2+(-0.0021)*K371)+L$1*((-0.000002)*L371^3+0.00032*L371^2+(-0.0021)*L371) -> 0 | AJ371: =M$1*((-0.000002)*M371^3+0.00032*M371^2+(-0.0021)*M371)+N$1*((-0.000002)*N371^3+0.00032*N371^2+(-0.0021)*N371)+O$1*((-0.000002)*O371^3+0.00032*O371^2+(-0.0021)*O371) -> 0 | AK371: =IF(AA371<50,W$1*((-0.000002)*W371^3+0.00032*W371^2+(-0.0021)*W371)+X$1*((-0.000002)*X371^3+0.00032*X371^2+(-0.0021)*X371)+Y$1*((-0.000002)*Y371^3+0.00032*Y371^2+(-0.0021)*Y371)+Z$1*((-0.000002)*Z371^3+0.00032*Z371^2+(-0.0021)*Z371),X$2*((-0.000002)*X371^3+0.00032*X371^2+(-0.0021)*X371)+Y$2*((-0.000002)*Y371^3+0.00032*Y371^2+(-0.0021)*Y371)+Z$2*((-0.000002)*Z371^3+0.00032*Z371^2+(-0.0021)*Z371)+AA$2*((-0.000002)*AA371^3+0.00032*AA371^2+(-0.0021)*AA371)) -> 0 | AL371: =AB$1*((-0.000002)*AB371^3+0.00032*AB371^2+(-0.0021)*AB371)+AC$1*((-0.000002)*AC371^3+0.00032*AC371^2+(-0.0021)*AC371) -> 0 | AM371: =AD$1*((-0.000002)*AD371^3+0.00032*AD371^2+(-0.0021)*AD371)+AE$1*((-0.000002)*AE371^3+0.00032*AE371^2+(-0.0021)*AE371)+AF$1*((-0.000002)*AF371^3+0.00032*AF371^2+(-0.0021)*AF371)+AG$1*((-0.000002)*AG371^3+0.00032*AG371^2+(-0.0021)*AG371) -> 0
... A506: =(AI506*AI$3+AJ506*AJ$3+AK506*AK$3+AL506*AL$3+AM506*AM$3)*100/(AI$5*AI$3+AJ$5*AJ$3+AK$5*AK$3+AL$5*AL$3+AM$5*AM$3) -> 0 | AI506: =H$1*((-0.000002)*H506^3+0.00032*H506^2+(-0.0021)*H506)+I$1*((-0.000002)*I506^3+0.00032*I506^2+(-0.0021)*I506)+J$1*((-0.000002)*J506^3+0.00032*J506^2+(-0.0021)*J506)+K$1*((-0.000002)*K506^3+0.00032*K506^2+(-0.0021)*K506)+L$1*((-0.000002)*L506^3+0.00032*L506^2+(-0.0021)*L506) -> 0 | AJ506: =M$1*((-0.000002)*M506^3+0.00032*M506^2+(-0.0021)*M506)+N$1*((-0.000002)*N506^3+0.00032*N506^2+(-0.0021)*N506)+O$1*((-0.000002)*O506^3+0.00032*O506^2+(-0.0021)*O506) -> 0 | AK506: =IF(AA506<50,W$1*((-0.000002)*W506^3+0.00032*W506^2+(-0.0021)*W506)+X$1*((-0.000002)*X506^3+0.00032*X506^2+(-0.0021)*X506)+Y$1*((-0.000002)*Y506^3+0.00032*Y506^2+(-0.0021)*Y506)+Z$1*((-0.000002)*Z506^3+0.00032*Z506^2+(-0.0021)*Z506),X$2*((-0.000002)*X506^3+0.00032*X506^2+(-0.0021)*X506)+Y$2*((-0.000002)*Y506^3+0.00032*Y506^2+(-0.0021)*Y506)+Z$2*((-0.000002)*Z506^3+0.00032*Z506^2+(-0.0021)*Z506)+AA$2*((-0.000002)*AA506^3+0.00032*AA506^2+(-0.0021)*AA506)) -> 0 | AL506: =AB$1*((-0.000002)*AB506^3+0.00032*AB506^2+(-0.0021)*AB506)+AC$1*((-0.000002)*AC506^3+0.00032*AC506^2+(-0.0021)*AC506) -> 0 | AM506: =AD$1*((-0.000002)*AD506^3+0.00032*AD506^2+(-0.0021)*AD506)+AE$1*((-0.000002)*AE506^3+0.00032*AE506^2+(-0.0021)*AE506)+AF$1*((-0.000002)*AF506^3+0.00032*AF506^2+(-0.0021)*AF506)+AG$1*((-0.000002)*AG506^3+0.00032*AG506^2+(-0.0021)*AG506) -> 0

Sheet Pitchers
H1: 0.2 | I1: 1 | J1: 4 | K1: 2 | L1: 1 | M1: 1.5 | N1: 0.2 | O1: 0.2 | P1: 2 | Q1: 2 | R1: 1 | S1: 0.5 | T1: 0.3 | U1: 0.3
V2: 4 | W2: 2 | X2: 1 | Y2: 1
J4: 100 | K4: 100 | L4: 100 | M4: 100 | N4: 100 | O4: 100 | P4: 100 | Q4: 100 | R4: 100 | S4: 100 | T4: 100 | U4: 100 | V4: =K$1*(0.000001*K4^3)+L$1*((-0.000002)*L4^3+0.00032*L4^2+(-0.0021)*L4)+M$1*((-0.000002)*M4^3+0.00032*M4^2+(-0.0021)*M4)+N$1*((-0.000002)*N4^3+0.00032*N4^2+(-0.0021)*N4)+O$1*((-0.000002)*O4^3+0.00032*O4^2+(-0.0021)*O4) -> 4.871 | W4: =P$1*((-0.000002)*P4^3+0.00032*P4^2+(-0.0021)*P4)+Q$1*((-0.000002)*Q4^3+0.00032*Q4^2+(-0.0021)*Q4)+R$1*((-0.000002)*R4^3+0.00032*R4^2+(-0.0021)*R4)+S$1*((-0.000002)*S4^3+0.00032*S4^2+(-0.0021)*S4)+T$1*((-0.000002)*T4^3+0.00032*T4^2+(-0.0021)*T4) -> 5.742 | X4: =I$1*((-0.000002)*I4^3+0.00032*I4^2+(-0.0021)*I4)+J$1*((-0.000002)*J4^3+0.00032*J4^2+(-0.0021)*J4)+H$1*((-0.000002)*H4^3+0.00032*H4^2+(-0.0021)*H4) -> 3.96 | Z4: =U4*J$2+V4*O$2+W4*H$2 -> 0
A5: Overall Projection | B5: Rank | C5: Player | D5: Position | E5: B | F5: T | G5: Age | H5: Health | I5: Durability | J5: Stamina | K5: Control | L5: vsL | M5: vsR | N5: Velocity | O5: Groundball/Flyball Tendency | P5: Pitch 1 | Q5: Pitch 2 | R5: Pitch 3 | S5: Pitch 4 | T5: Pitch 5 | U5: Overall | V5: pitching | W5: pitches | X5: durability | Y5: durability | Z5: total
A6: =IFERROR((V6*V$2+W6*W$2+X6*X$2)*100/(V$4*V$2+W$4*W$2+X$4*X$2),0) -> 70.476504 | B6: 4 | C6: Stevenson, Madison | D6: P | E6: S | F6: R | G6: 18 | H6: 59 | I6: 20 | J6: 98 | K6: 69 | L6: 71 | M6: 100 | N6: 44 | O6: 34 | P6: 65 | Q6: 85 | R6: 46 | S6: 98 | T6: 68 | U6: 77 | V6: =K$1*(0.000001*K6^3)+L$1*((-0.000002)*L6^3+0.00032*L6^2+(-0.0021)*L6)+M$1*((-0.000002)*M6^3+0.00032*M6^2+(-0.0021)*M6)+N$1*((-0.000002)*N6^3+0.00032*N6^2+(-0.0021)*N6)+O$1*((-0.000002)*O6^3+0.00032*O6^2+(-0.0021)*O6) -> 3.0055488 | W6: =P$1*((-0.000002)*P6^3+0.00032*P6^2+(-0.0021)*P6)+Q$1*((-0.000002)*Q6^3+0.00032*Q6^2+(-0.0021)*Q6)+R$1*((-0.000002)*R6^3+0.00032*R6^2+(-0.0021)*R6)+S$1*((-0.000002)*S6^3+0.00032*S6^2+(-0.0021)*S6)+T$1*((-0.000002)*T6^3+0.00032*T6^2+(-0.0021)*T6) -> 4.2338008 | X6: =(I$1*((-0.000002)*I6^3+0.00032*I6^2+(-0.0021)*I6)+J$1*((-0.000002)*J6^3+0.00032*J6^2+(-0.0021)*J6)+H$1*((-0.000002)*H6^3+0.00032*H6^2+(-0.0021)*H6))*(MAX(0.05,MIN(1,(2*J6+I6)/120)*MIN(1,I6/10)*MIN(1,J6/10))) -> 4.1262364 | Y6: =(I$1*((-0.000002)*I6^3+0.00032*I6^2+(-0.0021)*I6)+J$1*((-0.000002)*J6^3+0.00032*J6^2+(-0.0021)*J6)+H$1*((-0.000002)*H6^3+0.00032*H6^2+(-0.0021)*H6))*(MAX(0.05,MIN(1,(2*J6+I6)/120)*MIN(1,I6/10)*MIN(1,J6/10))) -> 4.1262364 | Z6: =IF(AND(J6>50,I6+J6>75),"SP",IF(2*I6+J6>120,"RP","CRAP")) -> SP | AA6: =IF(AND(J6>50,I6+J6>75),"SP",IF(2*I6+J6>120,"RP","CRAP")) -> SP
A7: =IFERROR((V7*V$2+W7*W$2+X7*X$2)*100/(V$4*V$2+W$4*W$2+X$4*X$2),0) -> 69.566418 | B7: 6 | C7: Madson, Bo | D7: P | E7: R | F7: R | G7: 18 | H7: 56 | I7: 44 | J7: 67 | K7: 98 | L7: 30 | M7: 54 | N7: 98 | O7: 82 | P7: 82 | Q7: 73 | R7: 54 | S7: 65 | T7: 21 | U7: 71 | V7: =K$1*(0.000001*K7^3)+L$1*((-0.000002)*L7^3+0.00032*L7^2+(-0.0021)*L7)+M$1*((-0.000002)*M7^3+0.00032*M7^2+(-0.0021)*M7)+N$1*((-0.000002)*N7^3+0.00032*N7^2+(-0.0021)*N7)+O$1*((-0.000002)*O7^3+0.00032*O7^2+(-0.0021)*O7) -> 3.18294 | W7: =P$1*((-0.000002)*P7^3+0.00032*P7^2+(-0.0021)*P7)+Q$1*((-0.000002)*Q7^3+0.00032*Q7^2+(-0.0021)*Q7)+R$1*((-0.000002)*R7^3+0.00032*R7^2+(-0.0021)*R7)+S$1*((-0.000002)*S7^3+0.00032*S7^2+(-0.0021)*S7)+T$1*((-0.000002)*T7^3+0.00032*T7^2+(-0.0021)*T7) -> 4.1628464 | X7: =(I$1*((-0.000002)*I7^3+0.00032*I7^2+(-0.0021)*I7)+J$1*((-0.000002)*J7^3+0.00032*J7^2+(-0.0021)*J7)+H$1*((-0.000002)*H7^3+0.00032*H7^2+(-0.0021)*H7))*(MAX(0.05,MIN(1,(2*J7+I7)/120)*MIN(1,I7/10)*MIN(1,J7/10))) -> 3.2407056 | Y7: =(I$1*((-0.000002)*I7^3+0.00032*I7^2+(-0.0021)*I7)+J$1*((-0.000002)*J7^3+0.00032*J7^2+(-0.0021)*J7)+H$1*((-0.000002)*H7^3+0.00032*H7^2+(-0.0021)*H7))*(MAX(0.05,MIN(1,(2*J7+I7)/120)*MIN(1,I7/10)*MIN(1,J7/10))) -> 3.2407056 | Z7: =IF(AND(J7>50,I7+J7>75),"SP",IF(2*I7+J7>120,"RP","CRAP")) -> SP | AA7: =IF(AND(J7>50,I7+J7>75),"SP",IF(2*I7+J7>120,"RP","CRAP")) -> SP
A8: =IFERROR((V8*V$2+W8*W$2+X8*X$2)*100/(V$4*V$2+W$4*W$2+X$4*X$2),0) -> 68.441105 | B8: 8 | C8: Burch, Stu | D8: P | E8: L | F8: L | G8: 18 | H8: 65 | I8: 61 | J8: 23 | K8: 86 | L8: 76 | M8: 81 | N8: 23 | O8: 79 | P8: 96 | Q8: 100 | R8: 45 | S8: 0 | T8: 0 | U8: 69 | V8: =K$1*(0.000001*K8^3)+L$1*((-0.000002)*L8^3+0.00032*L8^2+(-0.0021)*L8)+M$1*((-0.000002)*M8^3+0.00032*M8^2+(-0.0021)*M8)+N$1*((-0.000002)*N8^3+0.00032*N8^2+(-0.0021)*N8)+O$1*((-0.000002)*O8^3+0.00032*O8^2+(-0.0021)*O8) -> 3.5710446 | W8: =P$1*((-0.000002)*P8^3+0.00032*P8^2+(-0.0021)*P8)+Q$1*((-0.000002)*Q8^3+0.00032*Q8^2+(-0.0021)*Q8)+R$1*((-0.000002)*R8^3+0.00032*R8^2+(-0.0021)*R8)+S$1*((-0.000002)*S8^3+0.00032*S8^2+(-0.0021)*S8)+T$1*((-0.000002)*T8^3+0.00032*T8^2+(-0.0021)*T8) -> 4.307346 | X8: =(I$1*((-0.000002)*I8^3+0.00032*I8^2+(-0.0021)*I8)+J$1*((-0.000002)*J8^3+0.00032*J8^2+(-0.0021)*J8)+H$1*((-0.000002)*H8^3+0.00032*H8^2+(-0.0021)*H8))*(MAX(0.05,MIN(1,(2*J8+I8)/120)*MIN(1,I8/10)*MIN(1,J8/10))) -> 1.0062387 | Y8: =(I$1*((-0.000002)*I8^3+0.00032*I8^2+(-0.0021)*I8)+J$1*((-0.000002)*J8^3+0.00032*J8^2+(-0.0021)*J8)+H$1*((-0.000002)*H8^3+0.00032*H8^2+(-0.0021)*H8))*(MAX(0.05,MIN(1,(2*J8+I8)/120)*MIN(1,I8/10)*MIN(1,J8/10))) -> 1.0062387 | Z8: =IF(AND(J8>50,I8+J8>75),"SP",IF(2*I8+J8>120,"RP","CRAP")) -> RP | AA8: =IF(AND(J8>50,I8+J8>75),"SP",IF(2*I8+J8>120,"RP","CRAP")) -> RP
A9: =IFERROR((V9*V$2+W9*W$2+X9*X$2)*100/(V$4*V$2+W$4*W$2+X$4*X$2),0) -> 74.874109 | B9: 9 | C9: Gleason, Curtis | D9: P | E9: L | F9: L | G9: 18 | H9: 89 | I9: 21 | J9: 51 | K9: 100 | L9: 65 | M9: 51 | N9: 78 | O9: 88 | P9: 93 | Q9: 72 | R9: 74 | S9: 57 | T9: 41 | U9: 70 | V9: =K$1*(0.000001*K9^3)+L$1*((-0.000002)*L9^3+0.00032*L9^2+(-0.0021)*L9)+M$1*((-0.000002)*M9^3+0.00032*M9^2+(-0.0021)*M9)+N$1*((-0.000002)*N9^3+0.00032*N9^2+(-0.0021)*N9)+O$1*((-0.000002)*O9^3+0.00032*O9^2+(-0.0021)*O9) -> 3.7089894 | W9: =P$1*((-0.000002)*P9^3+0.00032*P9^2+(-0.0021)*P9)+Q$1*((-0.000002)*Q9^3+0.00032*Q9^2+(-0.0021)*Q9)+R$1*((-0.000002)*R9^3+0.00032*R9^2+(-0.0021)*R9)+S$1*((-0.000002)*S9^3+0.00032*S9^2+(-0.0021)*S9)+T$1*((-0.000002)*T9^3+0.00032*T9^2+(-0.0021)*T9) -> 4.6051624 | X9: =(I$1*((-0.000002)*I9^3+0.00032*I9^2+(-0.0021)*I9)+J$1*((-0.000002)*J9^3+0.00032*J9^2+(-0.0021)*J9)+H$1*((-0.000002)*H9^3+0.00032*H9^2+(-0.0021)*H9))*(MAX(0.05,MIN(1,(2*J9+I9)/120)*MIN(1,I9/10)*MIN(1,J9/10))) -> 2.1057464 | Y9: =(I$1*((-0.000002)*I9^3+0.00032*I9^2+(-0.0021)*I9)+J$1*((-0.000002)*J9^3+0.00032*J9^2+(-0.0021)*J9)+H$1*((-0.000002)*H9^3+0.00032*H9^2+(-0.0021)*H9))*(MAX(0.05,MIN(1,(2*J9+I9)/120)*MIN(1,I9/10)*MIN(1,J9/10))) -> 2.1057464 | Z9: =IF(AND(J9>50,I9+J9>75),"SP",IF(2*I9+J9>120,"RP","CRAP")) -> CRAP | AA9: =IF(AND(J9>50,I9+J9>75),"SP",IF(2*I9+J9>120,"RP","CRAP")) -> CRAP
A10: =IFERROR((V10*V$2+W10*W$2+X10*X$2)*100/(V$4*V$2+W$4*W$2+X$4*X$2),0) -> 67.057084 | B10: 10 | C10: King, Sherman | D10: P | E10: R | F10: R | G10: 18 | H10: 69 | I10: 39 | J10: 26 | K10: 83 | L10: 83 | M10: 100 | N10: 100 | O10: 62 | P10: 71 | Q10: 82 | R10: 49 | S10: 0 | T10: 0 | U10: 71 | V10: =K$1*(0.000001*K10^3)+L$1*((-0.000002)*L10^3+0.00032*L10^2+(-0.0021)*L10)+M$1*((-0.000002)*M10^3+0.00032*M10^2+(-0.0021)*M10)+N$1*((-0.000002)*N10^3+0.00032*N10^2+(-0.0021)*N10)+O$1*((-0.000002)*O10^3+0.00032*O10^2+(-0.0021)*O10) -> 3.8378248 | W10: =P$1*((-0.000002)*P10^3+0.00032*P10^2+(-0.0021)*P10)+Q$1*((-0.000002)*Q10^3+0.00032*Q10^2+(-0.0021)*Q10)+R$1*((-0.000002)*R10^3+0.00032*R10^2+(-0.0021)*R10)+S$1*((-0.000002)*S10^3+0.00032*S10^2+(-0.0021)*S10)+T$1*((-0.000002)*T10^3+0.00032*T10^2+(-0.0021)*T10) -> 3.680006 | X10: =(I$1*((-0.000002)*I10^3+0.00032*I10^2+(-0.0021)*I10)+J$1*((-0.000002)*J10^3+0.00032*J10^2+(-0.0021)*J10)+H$1*((-0.000002)*H10^3+0.00032*H10^2+(-0.0021)*H10))*(MAX(0.05,MIN(1,(2*J10+I10)/120)*MIN(1,I10/10)*MIN(1,J10/10))) -> 0.71038725 | Y10: =(I$1*((-0.000002)*I10^3+0.00032*I10^2+(-0.0021)*I10)+J$1*((-0.000002)*J10^3+0.00032*J10^2+(-0.0021)*J10)+H$1*((-0.000002)*H10^3+0.00032*H10^2+(-0.0021)*H10))*(MAX(0.05,MIN(1,(2*J10+I10)/120)*MIN(1,I10/10)*MIN(1,J10/10))) -> 0.71038725 | Z10: =IF(AND(J10>50,I10+J10>75),"SP",IF(2*I10+J10>120,"RP","CRAP")) -> CRAP | AA10: =IF(AND(J10>50,I10+J10>75),"SP",IF(2*I10+J10>120,"RP","CRAP")) -> CRAP
A11: =IFERROR((V11*V$2+W11*W$2+X11*X$2)*100/(V$4*V$2+W$4*W$2+X$4*X$2),0) -> 64.462091 | B11: 13 | C11: Cook, Ken | D11: P | E11: L | F11: L | G11: 18 | H11: 67 | I11: 81 | J11: 21 | K11: 85 | L11: 77 | M11: 65 | N11: 93 | O11: 79 | P11: 97 | Q11: 85 | R11: 0 | S11: 0 | T11: 0 | U11: 69 | V11: =K$1*(0.000001*K11^3)+L$1*((-0.000002)*L11^3+0.00032*L11^2+(-0.0021)*L11)+M$1*((-0.000002)*M11^3+0.00032*M11^2+(-0.0021)*M11)+N$1*((-0.000002)*N11^3+0.00032*N11^2+(-0.0021)*N11)+O$1*((-0.000002)*O11^3+0.00032*O11^2+(-0.0021)*O11) -> 3.4119006 | W11: =P$1*((-0.000002)*P11^3+0.00032*P11^2+(-0.0021)*P11)+Q$1*((-0.000002)*Q11^3+0.00032*Q11^2+(-0.0021)*Q11)+R$1*((-0.000002)*R11^3+0.00032*R11^2+(-0.0021)*R11)+S$1*((-0.000002)*S11^3+0.00032*S11^2+(-0.0021)*S11)+T$1*((-0.000002)*T11^3+0.00032*T11^2+(-0.0021)*T11) -> 3.774168 | X11: =(I$1*((-0.000002)*I11^3+0.00032*I11^2+(-0.0021)*I11)+J$1*((-0.000002)*J11^3+0.00032*J11^2+(-0.0021)*J11)+H$1*((-0.000002)*H11^3+0.00032*H11^2+(-0.0021)*H11))*(MAX(0.05,MIN(1,(2*J11+I11)/120)*MIN(1,I11/10)*MIN(1,J11/10))) -> 1.3193808 | Y11: =(I$1*((-0.000002)*I11^3+0.00032*I11^2+(-0.0021)*I11)+J$1*((-0.000002)*J11^3+0.00032*J11^2+(-0.0021)*J11)+H$1*((-0.000002)*H11^3+0.00032*H11^2+(-0.0021)*H11))*(MAX(0.05,MIN(1,(2*J11+I11)/120)*MIN(1,I11/10)*MIN(1,J11/10))) -> 1.3193808 | Z11: =IF(AND(J11>50,I11+J11>75),"SP",IF(2*I11+J11>120,"RP","CRAP")) -> RP | AA11: =IF(AND(J11>50,I11+J11>75),"SP",IF(2*I11+J11>120,"RP","CRAP")) -> RP
A12: =IFERROR((V12*V$2+W12*W$2+X12*X$2)*100/(V$4*V$2+W$4*W$2+X$4*X$2),0) -> 63.340404 | B12: 15 | C12: Pena, Juan | D12: P | E12: L | F12: L | G12: 18 | H12: 44 | I12: 59 | J12: 31 | K12: 86 | L12: 68 | M12: 81 | N12: 17 | O12: 63 | P12: 91 | Q12: 58 | R12: 54 | S12: 0 | T12: 0 | U12: 66 | V12: =K$1*(0.000001*K12^3)+L$1*((-0.000002)*L12^3+0.00032*L12^2+(-0.0021)*L12)+M$1*((-0.000002)*M12^3+0.00032*M12^2+(-0.0021)*M12)+N$1*((-0.000002)*N12^3+0.00032*N12^2+(-0.0021)*N12)+O$1*((-0.000002)*O12^3+0.00032*O12^2+(-0.0021)*O12) -> 3.416863 | W12: =P$1*((-0.000002)*P12^3+0.00032*P12^2+(-0.0021)*P12)+Q$1*((-0.000002)*Q12^3+0.00032*Q12^2+(-0.0021)*Q12)+R$1*((-0.000002)*R12^3+0.00032*R12^2+(-0.0021)*R12)+S$1*((-0.000002)*S12^3+0.00032*S12^2+(-0.0021)*S12)+T$1*((-0.000002)*T12^3+0.00032*T12^2+(-0.0021)*T12) -> 3.53706 | X12: =(I$1*((-0.000002)*I12^3+0.00032*I12^2+(-0.0021)*I12)+J$1*((-0.000002)*J12^3+0.00032*J12^2+(-0.0021)*J12)+H$1*((-0.000002)*H12^3+0.00032*H12^2+(-0.0021)*H12))*(MAX(0.05,MIN(1,(2*J12+I12)/120)*MIN(1,I12/10)*MIN(1,J12/10))) -> 1.3819644 | Y12: =(I$1*((-0.000002)*I12^3+0.00032*I12^2+(-0.0021)*I12)+J$1*((-0.000002)*J12^3+0.00032*J12^2+(-0.0021)*J12)+H$1*((-0.000002)*H12^3+0.00032*H12^2+(-0.0021)*H12))*(MAX(0.05,MIN(1,(2*J12+I12)/120)*MIN(1,I12/10)*MIN(1,J12/10))) -> 1.3819644 | Z12: =IF(AND(J12>50,I12+J12>75),"SP",IF(2*I12+J12>120,"RP","CRAP")) -> RP | AA12: =IF(AND(J12>50,I12+J12>75),"SP",IF(2*I12+J12>120,"RP","CRAP")) -> RP
A13: =IFERROR((V13*V$2+W13*W$2+X13*X$2)*100/(V$4*V$2+W$4*W$2+X$4*X$2),0) -> 63.420024 | B13: 16 | C13: Reed, Walt | D13: P | E13: L | F13: L | G13: 18 | H13: 100 | I13: 37 | J13: 28 | K13: 82 | L13: 77 | M13: 88 | N13: 98 | O13: 72 | P13: 69 | Q13: 57 | R13: 74 | S13: 0 | T13: 0 | U13: 68 | V13: =K$1*(0.000001*K13^3)+L$1*((-0.000002)*L13^3+0.00032*L13^2+(-0.0021)*L13)+M$1*((-0.000002)*M13^3+0.00032*M13^2+(-0.0021)*M13)+N$1*((-0.000002)*N13^3+0.00032*N13^2+(-0.0021)*N13)+O$1*((-0.000002)*O13^3+0.00032*O13^2+(-0.0021)*O13) -> 3.67001 | W13: =P$1*((-0.000002)*P13^3+0.00032*P13^2+(-0.0021)*P13)+Q$1*((-0.000002)*Q13^3+0.00032*Q13^2+(-0.0021)*Q13)+R$1*((-0.000002)*R13^3+0.00032*R13^2+(-0.0021)*R13)+S$1*((-0.000002)*S13^3+0.00032*S13^2+(-0.0021)*S13)+T$1*((-0.000002)*T13^3+0.00032*T13^2+(-0.0021)*T13) -> 3.328864 | X13: =(I$1*((-0.000002)*I13^3+0.00032*I13^2+(-0.0021)*I13)+J$1*((-0.000002)*J13^3+0.00032*J13^2+(-0.0021)*J13)+H$1*((-0.000002)*H13^3+0.00032*H13^2+(-0.0021)*H13))*(MAX(0.05,MIN(1,(2*J13+I13)/120)*MIN(1,I13/10)*MIN(1,J13/10))) -> 0.81357795 | Y13: =(I$1*((-0.000002)*I13^3+0.00032*I13^2+(-0.0021)*I13)+J$1*((-0.000002)*J13^3+0.00032*J13^2+(-0.0021)*J13)+H$1*((-0.000002)*H13^3+0.00032*H13^2+(-0.0021)*H13))*(MAX(0.05,MIN(1,(2*J13+I13)/120)*MIN(1,I13/10)*MIN(1,J13/10))) -> 0.81357795 | Z13: =IF(AND(J13>50,I13+J13>75),"SP",IF(2*I13+J13>120,"RP","CRAP")) -> CRAP | AA13: =IF(AND(J13>50,I13+J13>75),"SP",IF(2*I13+J13>120,"RP","CRAP")) -> CRAP
A14: =IFERROR((V14*V$2+W14*W$2+X14*X$2)*100/(V$4*V$2+W$4*W$2+X$4*X$2),0) -> 58.245668 | B14: 20 | C14: Diaz, Charlie | D14: P | E14: R | F14: R | G14: 18 | H14: 57 | I14: 18 | J14: 67 | K14: 42 | L14: 78 | M14: 85 | N14: 83 | O14: 67 | P14: 78 | Q14: 62 | R14: 33 | S14: 56 | T14: 0 | U14: 68 | V14: =K$1*(0.000001*K14^3)+L$1*((-0.000002)*L14^3+0.00032*L14^2+(-0.0021)*L14)+M$1*((-0.000002)*M14^3+0.00032*M14^2+(-0.0021)*M14)+N$1*((-0.000002)*N14^3+0.00032*N14^2+(-0.0021)*N14)+O$1*((-0.000002)*O14^3+0.00032*O14^2+(-0.0021)*O14) -> 2.656199 | W14: =P$1*((-0.000002)*P14^3+0.00032*P14^2+(-0.0021)*P14)+Q$1*((-0.000002)*Q14^3+0.00032*Q14^2+(-0.0021)*Q14)+R$1*((-0.000002)*R14^3+0.00032*R14^2+(-0.0021)*R14)+S$1*((-0.000002)*S14^3+0.00032*S14^2+(-0.0021)*S14)+T$1*((-0.000002)*T14^3+0.00032*T14^2+(-0.0021)*T14) -> 3.38905 | X14: =(I$1*((-0.000002)*I14^3+0.00032*I14^2+(-0.0021)*I14)+J$1*((-0.000002)*J14^3+0.00032*J14^2+(-0.0021)*J14)+H$1*((-0.000002)*H14^3+0.00032*H14^2+(-0.0021)*H14))*(MAX(0.05,MIN(1,(2*J14+I14)/120)*MIN(1,I14/10)*MIN(1,J14/10))) -> 2.9411508 | Y14: =(I$1*((-0.000002)*I14^3+0.00032*I14^2+(-0.0021)*I14)+J$1*((-0.000002)*J14^3+0.00032*J14^2+(-0.0021)*J14)+H$1*((-0.000002)*H14^3+0.00032*H14^2+(-0.0021)*H14))*(MAX(0.05,MIN(1,(2*J14+I14)/120)*MIN(1,I14/10)*MIN(1,J14/10))) -> 2.9411508 | Z14: =IF(AND(J14>50,I14+J14>75),"SP",IF(2*I14+J14>120,"RP","CRAP")) -> SP | AA14: =IF(AND(J14>50,I14+J14>75),"SP",IF(2*I14+J14>120,"RP","CRAP")) -> SP
A15: =IFERROR((V15*V$2+W15*W$2+X15*X$2)*100/(V$4*V$2+W$4*W$2+X$4*X$2),0) -> 57.828153 | B15: 21 | C15: Sanders, Joe | D15: P | E15: R | F15: R | G15: 18 | H15: 61 | I15: 19 | J15: 85 | K15: 84 | L15: 40 | M15: 45 | N15: 50 | O15: 71 | P15: 75 | Q15: 74 | R15: 30 | S15: 48 | T15: 39 | U15: 60 | V15: =K$1*(0.000001*K15^3)+L$1*((-0.000002)*L15^3+0.00032*L15^2+(-0.0021)*L15)+M$1*((-0.000002)*M15^3+0.00032*M15^2+(-0.0021)*M15)+N$1*((-0.000002)*N15^3+0.00032*N15^2+(-0.0021)*N15)+O$1*((-0.000002)*O15^3+0.00032*O15^2+(-0.0021)*O15) -> 2.2809226 | W15: =P$1*((-0.000002)*P15^3+0.00032*P15^2+(-0.0021)*P15)+Q$1*((-0.000002)*Q15^3+0.00032*Q15^2+(-0.0021)*Q15)+R$1*((-0.000002)*R15^3+0.00032*R15^2+(-0.0021)*R15)+S$1*((-0.000002)*S15^3+0.00032*S15^2+(-0.0021)*S15)+T$1*((-0.000002)*T15^3+0.00032*T15^2+(-0.0021)*T15) -> 3.6349466 | X15: =(I$1*((-0.000002)*I15^3+0.00032*I15^2+(-0.0021)*I15)+J$1*((-0.000002)*J15^3+0.00032*J15^2+(-0.0021)*J15)+H$1*((-0.000002)*H15^3+0.00032*H15^2+(-0.0021)*H15))*(MAX(0.05,MIN(1,(2*J15+I15)/120)*MIN(1,I15/10)*MIN(1,J15/10))) -> 3.8046336 | Y15: =(I$1*((-0.000002)*I15^3+0.00032*I15^2+(-0.0021)*I15)+J$1*((-0.000002)*J15^3+0.00032*J15^2+(-0.0021)*J15)+H$1*((-0.000002)*H15^3+0.00032*H15^2+(-0.0021)*H15))*(MAX(0.05,MIN(1,(2*J15+I15)/120)*MIN(1,I15/10)*MIN(1,J15/10))) -> 3.8046336 | Z15: =IF(AND(J15>50,I15+J15>75),"SP",IF(2*I15+J15>120,"RP","CRAP")) -> SP | AA15: =IF(AND(J15>50,I15+J15>75),"SP",IF(2*I15+J15>120,"RP","CRAP")) -> SP
A16: =IFERROR((V16*V$2+W16*W$2+X16*X$2)*100/(V$4*V$2+W$4*W$2+X$4*X$2),0) -> 53.009116 | B16: 29 | C16: Peguero, Tony | D16: P | E16: S | F16: R | G16: 18 | H16: 74 | I16: 90 | J16: 20 | K16: 70 | L16: 57 | M16: 96 | N16: 71 | O16: 67 | P16: 96 | Q16: 41 | R16: 0 | S16: 0 | T16: 0 | U16: 65 | V16: =K$1*(0.000001*K16^3)+L$1*((-0.000002)*L16^3+0.00032*L16^2+(-0.0021)*L16)+M$1*((-0.000002)*M16^3+0.00032*M16^2+(-0.0021)*M16)+N$1*((-0.000002)*N16^3+0.00032*N16^2+(-0.0021)*N16)+O$1*((-0.000002)*O16^3+0.00032*O16^2+(-0.0021)*O16) -> 2.9911564 | W16: =P$1*((-0.000002)*P16^3+0.00032*P16^2+(-0.0021)*P16)+Q$1*((-0.000002)*Q16^3+0.00032*Q16^2+(-0.0021)*Q16)+R$1*((-0.000002)*R16^3+0.00032*R16^2+(-0.0021)*R16)+S$1*((-0.000002)*S16^3+0.00032*S16^2+(-0.0021)*S16)+T$1*((-0.000002)*T16^3+0.00032*T16^2+(-0.0021)*T16) -> 2.584052 | X16: =(I$1*((-0.000002)*I16^3+0.00032*I16^2+(-0.0021)*I16)+J$1*((-0.000002)*J16^3+0.00032*J16^2+(-0.0021)*J16)+H$1*((-0.000002)*H16^3+0.00032*H16^2+(-0.0021)*H16))*(MAX(0.05,MIN(1,(2*J16+I16)/120)*MIN(1,I16/10)*MIN(1,J16/10))) -> 1.3822944 | Y16: =(I$1*((-0.000002)*I16^3+0.00032*I16^2+(-0.0021)*I16)+J$1*((-0.000002)*J16^3+0.00032*J16^2+(-0.0021)*J16)+H$1*((-0.000002)*H16^3+0.00032*H16^2+(-0.0021)*H16))*(MAX(0.05,MIN(1,(2*J16+I16)/120)*MIN(1,I16/10)*MIN(1,J16/10))) -> 1.3822944 | Z16: =IF(AND(J16>50,I16+J16>75),"SP",IF(2*I16+J16>120,"RP","CRAP")) -> RP | AA16: =IF(AND(J16>50,I16+J16>75),"SP",IF(2*I16+J16>120,"RP","CRAP")) -> RP
A17: =IFERROR((V17*V$2+W17*W$2+X17*X$2)*100/(V$4*V$2+W$4*W$2+X$4*X$2),0) -> 68.317333 | B17: 30 | C17: Cedeno, Mateo | D17: P | E17: R | F17: R | G17: 22 | H17: 72 | I17: 21 | J17: 44 | K17: 100 | L17: 81 | M17: 74 | N17: 76 | O17: 53 | P17: 55 | Q17: 56 | R17: 29 | S17: 60 | T17: 0 | U17: 66 | V17: =K$1*(0.000001*K17^3)+L$1*((-0.000002)*L17^3+0.00032*L17^2+(-0.0021)*L17)+M$1*((-0.000002)*M17^3+0.00032*M17^2+(-0.0021)*M17)+N$1*((-0.000002)*N17^3+0.00032*N17^2+(-0.0021)*N17)+O$1*((-0.000002)*O17^3+0.00032*O17^2+(-0.0021)*O17) -> 4.3063648 | W17: =P$1*((-0.000002)*P17^3+0.00032*P17^2+(-0.0021)*P17)+Q$1*((-0.000002)*Q17^3+0.00032*Q17^2+(-0.0021)*Q17)+R$1*((-0.000002)*R17^3+0.00032*R17^2+(-0.0021)*R17)+S$1*((-0.000002)*S17^3+0.00032*S17^2+(-0.0021)*S17)+T$1*((-0.000002)*T17^3+0.00032*T17^2+(-0.0021)*T17) -> 2.565318 | X17: =(I$1*((-0.000002)*I17^3+0.00032*I17^2+(-0.0021)*I17)+J$1*((-0.000002)*J17^3+0.00032*J17^2+(-0.0021)*J17)+H$1*((-0.000002)*H17^3+0.00032*H17^2+(-0.0021)*H17))*(MAX(0.05,MIN(1,(2*J17+I17)/120)*MIN(1,I17/10)*MIN(1,J17/10))) -> 1.505783 | Y17: =(I$1*((-0.000002)*I17^3+0.00032*I17^2+(-0.0021)*I17)+J$1*((-0.000002)*J17^3+0.00032*J17^2+(-0.0021)*J17)+H$1*((-0.000002)*H17^3+0.00032*H17^2+(-0.0021)*H17))*(MAX(0.05,MIN(1,(2*J17+I17)/120)*MIN(1,I17/10)*MIN(1,J17/10))) -> 1.505783 | Z17: =IF(AND(J17>50,I17+J17>75),"SP",IF(2*I17+J17>120,"RP","CRAP")) -> CRAP | AA17: =IF(AND(J17>50,I17+J17>75),"SP",IF(2*I17+J17>120,"RP","CRAP")) -> CRAP
... A68: =IFERROR((V68*V$2+W68*W$2+X68*X$2)*100/(V$4*V$2+W$4*W$2+X$4*X$2),0) -> 21.198195 | B68: 142 | C68: Lankford, Morris | D68: P | E68: L | F68: L | G68: 18 | H68: 97 | I68: 97 | J68: 24 | K68: 40 | L68: 25 | M68: 7 | N68: 29 | O68: 87 | P68: 59 | Q68: 44 | R68: 24 | S68: 0 | T68: 0 | U68: 37 | V68: =K$1*(0.000001*K68^3)+L$1*((-0.000002)*L68^3+0.00032*L68^2+(-0.0021)*L68)+M$1*((-0.000002)*M68^3+0.00032*M68^2+(-0.0021)*M68)+N$1*((-0.000002)*N68^3+0.00032*N68^2+(-0.0021)*N68)+O$1*((-0.000002)*O68^3+0.00032*O68^2+(-0.0021)*O68) -> 0.4610542 | W68: =P$1*((-0.000002)*P68^3+0.00032*P68^2+(-0.0021)*P68)+Q$1*((-0.000002)*Q68^3+0.00032*Q68^2+(-0.0021)*Q68)+R$1*((-0.000002)*R68^3+0.00032*R68^2+(-0.0021)*R68)+S$1*((-0.000002)*S68^3+0.00032*S68^2+(-0.0021)*S68)+T$1*((-0.000002)*T68^3+0.00032*T68^2+(-0.0021)*T68) -> 1.9783 | X68: =(I$1*((-0.000002)*I68^3+0.00032*I68^2+(-0.0021)*I68)+J$1*((-0.000002)*J68^3+0.00032*J68^2+(-0.0021)*J68)+H$1*((-0.000002)*H68^3+0.00032*H68^2+(-0.0021)*H68))*(MAX(0.05,MIN(1,(2*J68+I68)/120)*MIN(1,I68/10)*MIN(1,J68/10))) -> 1.6032888 | Y68: =(I$1*((-0.000002)*I68^3+0.00032*I68^2+(-0.0021)*I68)+J$1*((-0.000002)*J68^3+0.00032*J68^2+(-0.0021)*J68)+H$1*((-0.000002)*H68^3+0.00032*H68^2+(-0.0021)*H68))*(MAX(0.05,MIN(1,(2*J68+I68)/120)*MIN(1,I68/10)*MIN(1,J68/10))) -> 1.6032888 | Z68: =IF(AND(J68>50,I68+J68>75),"SP",IF(2*I68+J68>120,"RP","CRAP")) -> RP | AA68: =IF(AND(J68>50,I68+J68>75),"SP",IF(2*I68+J68>120,"RP","CRAP")) -> RP
A69: =IFERROR((V69*V$2+W69*W$2+X69*X$2)*100/(V$4*V$2+W$4*W$2+X$4*X$2),0) -> 0 | B69: 143 | C69: Gomez, Alex | D69: P | E69: R | F69: R | G69: 18 | H69: ? | I69: 18 | J69: 67 | K69: 88 | L69: 25 | M69: 27 | N69: 50 | O69: 42 | P69: 66 | Q69: 75 | R69: 38 | S69: 45 | T69: 0 | U69: 52 | V69: =K$1*(0.000001*K69^3)+L$1*((-0.000002)*L69^3+0.00032*L69^2+(-0.0021)*L69)+M$1*((-0.000002)*M69^3+0.00032*M69^2+(-0.0021)*M69)+N$1*((-0.000002)*N69^3+0.00032*N69^2+(-0.0021)*N69)+O$1*((-0.000002)*O69^3+0.00032*O69^2+(-0.0021)*O69) -> 1.8396358 | W69: =P$1*((-0.000002)*P69^3+0.00032*P69^2+(-0.0021)*P69)+Q$1*((-0.000002)*Q69^3+0.00032*Q69^2+(-0.0021)*Q69)+R$1*((-0.000002)*R69^3+0.00032*R69^2+(-0.0021)*R69)+S$1*((-0.000002)*S69^3+0.00032*S69^2+(-0.0021)*S69)+T$1*((-0.000002)*T69^3+0.00032*T69^2+(-0.0021)*T69) -> 3.416317 | X69: =(I$1*((-0.000002)*I69^3+0.00032*I69^2+(-0.0021)*I69)+J$1*((-0.000002)*J69^3+0.00032*J69^2+(-0.0021)*J69)+H$1*((-0.000002)*H69^3+0.00032*H69^2+(-0.0021)*H69))*(MAX(0.05,MIN(1,(2*J69+I69)/120)*MIN(1,I69/10)*MIN(1,J69/10))) -> #VALUE! | Y69: =(I$1*((-0.000002)*I69^3+0.00032*I69^2+(-0.0021)*I69)+J$1*((-0.000002)*J69^3+0.00032*J69^2+(-0.0021)*J69)+H$1*((-0.000002)*H69^3+0.00032*H69^2+(-0.0021)*H69))*(MAX(0.05,MIN(1,(2*J69+I69)/120)*MIN(1,I69/10)*MIN(1,J69/10))) -> #VALUE! | Z69: =IF(AND(J69>50,I69+J69>75),"SP",IF(2*I69+J69>120,"RP","CRAP")) -> SP | AA69: =IF(AND(J69>50,I69+J69>75),"SP",IF(2*I69+J69>120,"RP","CRAP")) -> SP
A70: =IFERROR((V70*V$2+W70*W$2+X70*X$2)*100/(V$4*V$2+W$4*W$2+X$4*X$2),0) -> 0 | B70: 144 | C70: Cartwright, Shelley | D70: P | E70: R | F70: R | G70: 18 | H70: ? | I70: ? | J70: ? | K70: ? | L70: ? | M70: ? | N70: ? | O70: ? | P70: ? | Q70: ? | R70: ? | S70: ? | T70: ? | U70: ? | V70: =K$1*(0.000001*K70^3)+L$1*((-0.000002)*L70^3+0.00032*L70^2+(-0.0021)*L70)+M$1*((-0.000002)*M70^3+0.00032*M70^2+(-0.0021)*M70)+N$1*((-0.000002)*N70^3+0.00032*N70^2+(-0.0021)*N70)+O$1*((-0.000002)*O70^3+0.00032*O70^2+(-0.0021)*O70) -> #VALUE! | W70: =P$1*((-0.000002)*P70^3+0.00032*P70^2+(-0.0021)*P70)+Q$1*((-0.000002)*Q70^3+0.00032*Q70^2+(-0.0021)*Q70)+R$1*((-0.000002)*R70^3+0.00032*R70^2+(-0.0021)*R70)+S$1*((-0.000002)*S70^3+0.00032*S70^2+(-0.0021)*S70)+T$1*((-0.000002)*T70^3+0.00032*T70^2+(-0.0021)*T70) -> #VALUE! | X70: =(I$1*((-0.000002)*I70^3+0.00032*I70^2+(-0.0021)*I70)+J$1*((-0.000002)*J70^3+0.00032*J70^2+(-0.0021)*J70)+H$1*((-0.000002)*H70^3+0.00032*H70^2+(-0.0021)*H70))*(MAX(0.05,MIN(1,(2*J70+I70)/120)*MIN(1,I70/10)*MIN(1,J70/10))) -> #VALUE! | Y70: =(I$1*((-0.000002)*I70^3+0.00032*I70^2+(-0.0021)*I70)+J$1*((-0.000002)*J70^3+0.00032*J70^2+(-0.0021)*J70)+H$1*((-0.000002)*H70^3+0.00032*H70^2+(-0.0021)*H70))*(MAX(0.05,MIN(1,(2*J70+I70)/120)*MIN(1,I70/10)*MIN(1,J70/10))) -> #VALUE! | Z70: =IF(AND(J70>50,I70+J70>75),"SP",IF(2*I70+J70>120,"RP","CRAP")) -> #VALUE! | AA70: =IF(AND(J70>50,I70+J70>75),"SP",IF(2*I70+J70>120,"RP","CRAP")) -> #VALUE!
A71: =IFERROR((V71*V$2+W71*W$2+X71*X$2)*100/(V$4*V$2+W$4*W$2+X$4*X$2),0) -> 0 | B71: 145 | C71: Morgan, Rob | D71: P | E71: R | F71: R | G71: 18 | H71: ? | I71: ? | J71: ? | K71: ? | L71: ? | M71: ? | N71: ? | O71: ? | P71: ? | Q71: ? | R71: ? | S71: ? | T71: ? | U71: ? | V71: =K$1*(0.000001*K71^3)+L$1*((-0.000002)*L71^3+0.00032*L71^2+(-0.0021)*L71)+M$1*((-0.000002)*M71^3+0.00032*M71^2+(-0.0021)*M71)+N$1*((-0.000002)*N71^3+0.00032*N71^2+(-0.0021)*N71)+O$1*((-0.000002)*O71^3+0.00032*O71^2+(-0.0021)*O71) -> #VALUE! | W71: =P$1*((-0.000002)*P71^3+0.00032*P71^2+(-0.0021)*P71)+Q$1*((-0.000002)*Q71^3+0.00032*Q71^2+(-0.0021)*Q71)+R$1*((-0.000002)*R71^3+0.00032*R71^2+(-0.0021)*R71)+S$1*((-0.000002)*S71^3+0.00032*S71^2+(-0.0021)*S71)+T$1*((-0.000002)*T71^3+0.00032*T71^2+(-0.0021)*T71) -> #VALUE! | X71: =(I$1*((-0.000002)*I71^3+0.00032*I71^2+(-0.0021)*I71)+J$1*((-0.000002)*J71^3+0.00032*J71^2+(-0.0021)*J71)+H$1*((-0.000002)*H71^3+0.00032*H71^2+(-0.0021)*H71))*(MAX(0.05,MIN(1,(2*J71+I71)/120)*MIN(1,I71/10)*MIN(1,J71/10))) -> #VALUE! | Y71: =(I$1*((-0.000002)*I71^3+0.00032*I71^2+(-0.0021)*I71)+J$1*((-0.000002)*J71^3+0.00032*J71^2+(-0.0021)*J71)+H$1*((-0.000002)*H71^3+0.00032*H71^2+(-0.0021)*H71))*(MAX(0.05,MIN(1,(2*J71+I71)/120)*MIN(1,I71/10)*MIN(1,J71/10))) -> #VALUE! | Z71: =IF(AND(J71>50,I71+J71>75),"SP",IF(2*I71+J71>120,"RP","CRAP")) -> #VALUE! | AA71: =IF(AND(J71>50,I71+J71>75),"SP",IF(2*I71+J71>120,"RP","CRAP")) -> #VALUE!
A72: =IFERROR((V72*V$2+W72*W$2+X72*X$2)*100/(V$4*V$2+W$4*W$2+X$4*X$2),0) -> 0 | B72: 146 | C72: Lasker, Billy | D72: P | E72: R | F72: R | G72: 18 | H72: ? | I72: ? | J72: ? | K72: ? | L72: ? | M72: ? | N72: ? | O72: ? | P72: ? | Q72: ? | R72: ? | S72: ? | T72: ? | U72: ? | V72: =K$1*(0.000001*K72^3)+L$1*((-0.000002)*L72^3+0.00032*L72^2+(-0.0021)*L72)+M$1*((-0.000002)*M72^3+0.00032*M72^2+(-0.0021)*M72)+N$1*((-0.000002)*N72^3+0.00032*N72^2+(-0.0021)*N72)+O$1*((-0.000002)*O72^3+0.00032*O72^2+(-0.0021)*O72) -> #VALUE! | W72: =P$1*((-0.000002)*P72^3+0.00032*P72^2+(-0.0021)*P72)+Q$1*((-0.000002)*Q72^3+0.00032*Q72^2+(-0.0021)*Q72)+R$1*((-0.000002)*R72^3+0.00032*R72^2+(-0.0021)*R72)+S$1*((-0.000002)*S72^3+0.00032*S72^2+(-0.0021)*S72)+T$1*((-0.000002)*T72^3+0.00032*T72^2+(-0.0021)*T72) -> #VALUE! | X72: =(I$1*((-0.000002)*I72^3+0.00032*I72^2+(-0.0021)*I72)+J$1*((-0.000002)*J72^3+0.00032*J72^2+(-0.0021)*J72)+H$1*((-0.000002)*H72^3+0.00032*H72^2+(-0.0021)*H72))*(MAX(0.05,MIN(1,(2*J72+I72)/120)*MIN(1,I72/10)*MIN(1,J72/10))) -> #VALUE! | Y72: =(I$1*((-0.000002)*I72^3+0.00032*I72^2+(-0.0021)*I72)+J$1*((-0.000002)*J72^3+0.00032*J72^2+(-0.0021)*J72)+H$1*((-0.000002)*H72^3+0.00032*H72^2+(-0.0021)*H72))*(MAX(0.05,MIN(1,(2*J72+I72)/120)*MIN(1,I72/10)*MIN(1,J72/10))) -> #VALUE! | Z72: =IF(AND(J72>50,I72+J72>75),"SP",IF(2*I72+J72>120,"RP","CRAP")) -> #VALUE! | AA72: =IF(AND(J72>50,I72+J72>75),"SP",IF(2*I72+J72>120,"RP","CRAP")) -> #VALUE!
A73: =IFERROR((V73*V$2+W73*W$2+X73*X$2)*100/(V$4*V$2+W$4*W$2+X$4*X$2),0) -> 0 | B73: 147 | C73: Lockhart, Emerson | D73: P | E73: L | F73: L | G73: 19 | H73: ? | I73: ? | J73: ? | K73: ? | L73: ? | M73: ? | N73: ? | O73: ? | P73: ? | Q73: ? | R73: ? | S73: ? | T73: ? | U73: ? | V73: =K$1*(0.000001*K73^3)+L$1*((-0.000002)*L73^3+0.00032*L73^2+(-0.0021)*L73)+M$1*((-0.000002)*M73^3+0.00032*M73^2+(-0.0021)*M73)+N$1*((-0.000002)*N73^3+0.00032*N73^2+(-0.0021)*N73)+O$1*((-0.000002)*O73^3+0.00032*O73^2+(-0.0021)*O73) -> #VALUE! | W73: =P$1*((-0.000002)*P73^3+0.00032*P73^2+(-0.0021)*P73)+Q$1*((-0.000002)*Q73^3+0.00032*Q73^2+(-0.0021)*Q73)+R$1*((-0.000002)*R73^3+0.00032*R73^2+(-0.0021)*R73)+S$1*((-0.000002)*S73^3+0.00032*S73^2+(-0.0021)*S73)+T$1*((-0.000002)*T73^3+0.00032*T73^2+(-0.0021)*T73) -> #VALUE! | X73: =(I$1*((-0.000002)*I73^3+0.00032*I73^2+(-0.0021)*I73)+J$1*((-0.000002)*J73^3+0.00032*J73^2+(-0.0021)*J73)+H$1*((-0.000002)*H73^3+0.00032*H73^2+(-0.0021)*H73))*(MAX(0.05,MIN(1,(2*J73+I73)/120)*MIN(1,I73/10)*MIN(1,J73/10))) -> #VALUE! | Y73: =(I$1*((-0.000002)*I73^3+0.00032*I73^2+(-0.0021)*I73)+J$1*((-0.000002)*J73^3+0.00032*J73^2+(-0.0021)*J73)+H$1*((-0.000002)*H73^3+0.00032*H73^2+(-0.0021)*H73))*(MAX(0.05,MIN(1,(2*J73+I73)/120)*MIN(1,I73/10)*MIN(1,J73/10))) -> #VALUE! | Z73: =IF(AND(J73>50,I73+J73>75),"SP",IF(2*I73+J73>120,"RP","CRAP")) -> #VALUE! | AA73: =IF(AND(J73>50,I73+J73>75),"SP",IF(2*I73+J73>120,"RP","CRAP")) -> #VALUE!
A74: =IFERROR((V74*V$2+W74*W$2+X74*X$2)*100/(V$4*V$2+W$4*W$2+X$4*X$2),0) -> 0 | B74: 148 | C74: McDonald, Zip | D74: P | E74: L | F74: L | G74: 22 | H74: ? | I74: ? | J74: ? | K74: ? | L74: ? | M74: ? | N74: ? | O74: ? | P74: ? | Q74: ? | R74: ? | S74: ? | T74: ? | U74: ? | V74: =K$1*(0.000001*K74^3)+L$1*((-0.000002)*L74^3+0.00032*L74^2+(-0.0021)*L74)+M$1*((-0.000002)*M74^3+0.00032*M74^2+(-0.0021)*M74)+N$1*((-0.000002)*N74^3+0.00032*N74^2+(-0.0021)*N74)+O$1*((-0.000002)*O74^3+0.00032*O74^2+(-0.0021)*O74) -> #VALUE! | W74: =P$1*((-0.000002)*P74^3+0.00032*P74^2+(-0.0021)*P74)+Q$1*((-0.000002)*Q74^3+0.00032*Q74^2+(-0.0021)*Q74)+R$1*((-0.000002)*R74^3+0.00032*R74^2+(-0.0021)*R74)+S$1*((-0.000002)*S74^3+0.00032*S74^2+(-0.0021)*S74)+T$1*((-0.000002)*T74^3+0.00032*T74^2+(-0.0021)*T74) -> #VALUE! | X74: =(I$1*((-0.000002)*I74^3+0.00032*I74^2+(-0.0021)*I74)+J$1*((-0.000002)*J74^3+0.00032*J74^2+(-0.0021)*J74)+H$1*((-0.000002)*H74^3+0.00032*H74^2+(-0.0021)*H74))*(MAX(0.05,MIN(1,(2*J74+I74)/120)*MIN(1,I74/10)*MIN(1,J74/10))) -> #VALUE! | Y74: =(I$1*((-0.000002)*I74^3+0.00032*I74^2+(-0.0021)*I74)+J$1*((-0.000002)*J74^3+0.00032*J74^2+(-0.0021)*J74)+H$1*((-0.000002)*H74^3+0.00032*H74^2+(-0.0021)*H74))*(MAX(0.05,MIN(1,(2*J74+I74)/120)*MIN(1,I74/10)*MIN(1,J74/10))) -> #VALUE! | Z74: =IF(AND(J74>50,I74+J74>75),"SP",IF(2*I74+J74>120,"RP","CRAP")) -> #VALUE! | AA74: =IF(AND(J74>50,I74+J74>75),"SP",IF(2*I74+J74>120,"RP","CRAP")) -> #VALUE!
A75: =IFERROR((V75*V$2+W75*W$2+X75*X$2)*100/(V$4*V$2+W$4*W$2+X$4*X$2),0) -> 0 | B75: 149 | C75: Smart, Russell | D75: P | E75: R | F75: R | G75: 20 | H75: ? | I75: ? | J75: ? | K75: ? | L75: ? | M75: ? | N75: ? | O75: ? | P75: ? | Q75: ? | R75: ? | S75: ? | T75: ? | U75: ? | V75: =K$1*(0.000001*K75^3)+L$1*((-0.000002)*L75^3+0.00032*L75^2+(-0.0021)*L75)+M$1*((-0.000002)*M75^3+0.00032*M75^2+(-0.0021)*M75)+N$1*((-0.000002)*N75^3+0.00032*N75^2+(-0.0021)*N75)+O$1*((-0.000002)*O75^3+0.00032*O75^2+(-0.0021)*O75) -> #VALUE! | W75: =P$1*((-0.000002)*P75^3+0.00032*P75^2+(-0.0021)*P75)+Q$1*((-0.000002)*Q75^3+0.00032*Q75^2+(-0.0021)*Q75)+R$1*((-0.000002)*R75^3+0.00032*R75^2+(-0.0021)*R75)+S$1*((-0.000002)*S75^3+0.00032*S75^2+(-0.0021)*S75)+T$1*((-0.000002)*T75^3+0.00032*T75^2+(-0.0021)*T75) -> #VALUE! | X75: =(I$1*((-0.000002)*I75^3+0.00032*I75^2+(-0.0021)*I75)+J$1*((-0.000002)*J75^3+0.00032*J75^2+(-0.0021)*J75)+H$1*((-0.000002)*H75^3+0.00032*H75^2+(-0.0021)*H75))*(MAX(0.05,MIN(1,(2*J75+I75)/120)*MIN(1,I75/10)*MIN(1,J75/10))) -> #VALUE! | Y75: =(I$1*((-0.000002)*I75^3+0.00032*I75^2+(-0.0021)*I75)+J$1*((-0.000002)*J75^3+0.00032*J75^2+(-0.0021)*J75)+H$1*((-0.000002)*H75^3+0.00032*H75^2+(-0.0021)*H75))*(MAX(0.05,MIN(1,(2*J75+I75)/120)*MIN(1,I75/10)*MIN(1,J75/10))) -> #VALUE! | Z75: =IF(AND(J75>50,I75+J75>75),"SP",IF(2*I75+J75>120,"RP","CRAP")) -> #VALUE! | AA75: =IF(AND(J75>50,I75+J75>75),"SP",IF(2*I75+J75>120,"RP","CRAP")) -> #VALUE!
A76: =IFERROR((V76*V$2+W76*W$2+X76*X$2)*100/(V$4*V$2+W$4*W$2+X$4*X$2),0) -> 0 | B76: 150 | C76: Punto, Darrell | D76: P | E76: R | F76: R | G76: 20 | H76: ? | I76: ? | J76: ? | K76: ? | L76: ? | M76: ? | N76: ? | O76: ? | P76: ? | Q76: ? | R76: ? | S76: ? | T76: ? | U76: ? | V76: =K$1*(0.000001*K76^3)+L$1*((-0.000002)*L76^3+0.00032*L76^2+(-0.0021)*L76)+M$1*((-0.000002)*M76^3+0.00032*M76^2+(-0.0021)*M76)+N$1*((-0.000002)*N76^3+0.00032*N76^2+(-0.0021)*N76)+O$1*((-0.000002)*O76^3+0.00032*O76^2+(-0.0021)*O76) -> #VALUE! | W76: =P$1*((-0.000002)*P76^3+0.00032*P76^2+(-0.0021)*P76)+Q$1*((-0.000002)*Q76^3+0.00032*Q76^2+(-0.0021)*Q76)+R$1*((-0.000002)*R76^3+0.00032*R76^2+(-0.0021)*R76)+S$1*((-0.000002)*S76^3+0.00032*S76^2+(-0.0021)*S76)+T$1*((-0.000002)*T76^3+0.00032*T76^2+(-0.0021)*T76) -> #VALUE! | X76: =(I$1*((-0.000002)*I76^3+0.00032*I76^2+(-0.0021)*I76)+J$1*((-0.000002)*J76^3+0.00032*J76^2+(-0.0021)*J76)+H$1*((-0.000002)*H76^3+0.00032*H76^2+(-0.0021)*H76))*(MAX(0.05,MIN(1,(2*J76+I76)/120)*MIN(1,I76/10)*MIN(1,J76/10))) -> #VALUE! | Y76: =(I$1*((-0.000002)*I76^3+0.00032*I76^2+(-0.0021)*I76)+J$1*((-0.000002)*J76^3+0.00032*J76^2+(-0.0021)*J76)+H$1*((-0.000002)*H76^3+0.00032*H76^2+(-0.0021)*H76))*(MAX(0.05,MIN(1,(2*J76+I76)/120)*MIN(1,I76/10)*MIN(1,J76/10))) -> #VALUE! | Z76: =IF(AND(J76>50,I76+J76>75),"SP",IF(2*I76+J76>120,"RP","CRAP")) -> #VALUE! | AA76: =IF(AND(J76>50,I76+J76>75),"SP",IF(2*I76+J76>120,"RP","CRAP")) -> #VALUE!
A77: =IFERROR((V77*V$2+W77*W$2+X77*X$2)*100/(V$4*V$2+W$4*W$2+X$4*X$2),0) -> 0 | B77: 151 | C77: Simon, Kameron | D77: P | E77: L | F77: L | G77: 21 | H77: ? | I77: ? | J77: ? | K77: ? | L77: ? | M77: ? | N77: ? | O77: ? | P77: ? | Q77: ? | R77: ? | S77: ? | T77: ? | U77: ? | V77: =K$1*(0.000001*K77^3)+L$1*((-0.000002)*L77^3+0.00032*L77^2+(-0.0021)*L77)+M$1*((-0.000002)*M77^3+0.00032*M77^2+(-0.0021)*M77)+N$1*((-0.000002)*N77^3+0.00032*N77^2+(-0.0021)*N77)+O$1*((-0.000002)*O77^3+0.00032*O77^2+(-0.0021)*O77) -> #VALUE! | W77: =P$1*((-0.000002)*P77^3+0.00032*P77^2+(-0.0021)*P77)+Q$1*((-0.000002)*Q77^3+0.00032*Q77^2+(-0.0021)*Q77)+R$1*((-0.000002)*R77^3+0.00032*R77^2+(-0.0021)*R77)+S$1*((-0.000002)*S77^3+0.00032*S77^2+(-0.0021)*S77)+T$1*((-0.000002)*T77^3+0.00032*T77^2+(-0.0021)*T77) -> #VALUE! | X77: =(I$1*((-0.000002)*I77^3+0.00032*I77^2+(-0.0021)*I77)+J$1*((-0.000002)*J77^3+0.00032*J77^2+(-0.0021)*J77)+H$1*((-0.000002)*H77^3+0.00032*H77^2+(-0.0021)*H77))*(MAX(0.05,MIN(1,(2*J77+I77)/120)*MIN(1,I77/10)*MIN(1,J77/10))) -> #VALUE! | Y77: =(I$1*((-0.000002)*I77^3+0.00032*I77^2+(-0.0021)*I77)+J$1*((-0.000002)*J77^3+0.00032*J77^2+(-0.0021)*J77)+H$1*((-0.000002)*H77^3+0.00032*H77^2+(-0.0021)*H77))*(MAX(0.05,MIN(1,(2*J77+I77)/120)*MIN(1,I77/10)*MIN(1,J77/10))) -> #VALUE! | Z77: =IF(AND(J77>50,I77+J77>75),"SP",IF(2*I77+J77>120,"RP","CRAP")) -> #VALUE! | AA77: =IF(AND(J77>50,I77+J77>75),"SP",IF(2*I77+J77>120,"RP","CRAP")) -> #VALUE!
A78: =IFERROR((V78*V$2+W78*W$2+X78*X$2)*100/(V$4*V$2+W$4*W$2+X$4*X$2),0) -> 0 | B78: 152 | C78: Martin, Dennis | D78: P | E78: R | F78: R | G78: 18 | H78: ? | I78: ? | J78: ? | K78: ? | L78: ? | M78: ? | N78: ? | O78: ? | P78: ? | Q78: ? | R78: ? | S78: ? | T78: ? | U78: ? | V78: =K$1*(0.000001*K78^3)+L$1*((-0.000002)*L78^3+0.00032*L78^2+(-0.0021)*L78)+M$1*((-0.000002)*M78^3+0.00032*M78^2+(-0.0021)*M78)+N$1*((-0.000002)*N78^3+0.00032*N78^2+(-0.0021)*N78)+O$1*((-0.000002)*O78^3+0.00032*O78^2+(-0.0021)*O78) -> #VALUE! | W78: =P$1*((-0.000002)*P78^3+0.00032*P78^2+(-0.0021)*P78)+Q$1*((-0.000002)*Q78^3+0.00032*Q78^2+(-0.0021)*Q78)+R$1*((-0.000002)*R78^3+0.00032*R78^2+(-0.0021)*R78)+S$1*((-0.000002)*S78^3+0.00032*S78^2+(-0.0021)*S78)+T$1*((-0.000002)*T78^3+0.00032*T78^2+(-0.0021)*T78) -> #VALUE! | X78: =(I$1*((-0.000002)*I78^3+0.00032*I78^2+(-0.0021)*I78)+J$1*((-0.000002)*J78^3+0.00032*J78^2+(-0.0021)*J78)+H$1*((-0.000002)*H78^3+0.00032*H78^2+(-0.0021)*H78))*(MAX(0.05,MIN(1,(2*J78+I78)/120)*MIN(1,I78/10)*MIN(1,J78/10))) -> #VALUE! | Y78: =(I$1*((-0.000002)*I78^3+0.00032*I78^2+(-0.0021)*I78)+J$1*((-0.000002)*J78^3+0.00032*J78^2+(-0.0021)*J78)+H$1*((-0.000002)*H78^3+0.00032*H78^2+(-0.0021)*H78))*(MAX(0.05,MIN(1,(2*J78+I78)/120)*MIN(1,I78/10)*MIN(1,J78/10))) -> #VALUE! | Z78: =IF(AND(J78>50,I78+J78>75),"SP",IF(2*I78+J78>120,"RP","CRAP")) -> #VALUE! | AA78: =IF(AND(J78>50,I78+J78>75),"SP",IF(2*I78+J78>120,"RP","CRAP")) -> #VALUE!
A79: =IFERROR((V79*V$2+W79*W$2+X79*X$2)*100/(V$4*V$2+W$4*W$2+X$4*X$2),0) -> 0 | B79: 153 | C79: Weeks, Derek | D79: P | E79: R | F79: R | G79: 19 | H79: ? | I79: ? | J79: ? | K79: ? | L79: ? | M79: ? | N79: ? | O79: ? | P79: ? | Q79: ? | R79: ? | S79: ? | T79: ? | U79: ? | V79: =K$1*(0.000001*K79^3)+L$1*((-0.000002)*L79^3+0.00032*L79^2+(-0.0021)*L79)+M$1*((-0.000002)*M79^3+0.00032*M79^2+(-0.0021)*M79)+N$1*((-0.000002)*N79^3+0.00032*N79^2+(-0.0021)*N79)+O$1*((-0.000002)*O79^3+0.00032*O79^2+(-0.0021)*O79) -> #VALUE! | W79: =P$1*((-0.000002)*P79^3+0.00032*P79^2+(-0.0021)*P79)+Q$1*((-0.000002)*Q79^3+0.00032*Q79^2+(-0.0021)*Q79)+R$1*((-0.000002)*R79^3+0.00032*R79^2+(-0.0021)*R79)+S$1*((-0.000002)*S79^3+0.00032*S79^2+(-0.0021)*S79)+T$1*((-0.000002)*T79^3+0.00032*T79^2+(-0.0021)*T79) -> #VALUE! | X79: =(I$1*((-0.000002)*I79^3+0.00032*I79^2+(-0.0021)*I79)+J$1*((-0.000002)*J79^3+0.00032*J79^2+(-0.0021)*J79)+H$1*((-0.000002)*H79^3+0.00032*H79^2+(-0.0021)*H79))*(MAX(0.05,MIN(1,(2*J79+I79)/120)*MIN(1,I79/10)*MIN(1,J79/10))) -> #VALUE! | Y79: =(I$1*((-0.000002)*I79^3+0.00032*I79^2+(-0.0021)*I79)+J$1*((-0.000002)*J79^3+0.00032*J79^2+(-0.0021)*J79)+H$1*((-0.000002)*H79^3+0.00032*H79^2+(-0.0021)*H79))*(MAX(0.05,MIN(1,(2*J79+I79)/120)*MIN(1,I79/10)*MIN(1,J79/10))) -> #VALUE! | Z79: =IF(AND(J79>50,I79+J79>75),"SP",IF(2*I79+J79>120,"RP","CRAP")) -> #VALUE! | AA79: =IF(AND(J79>50,I79+J79>75),"SP",IF(2*I79+J79>120,"RP","CRAP")) -> #VALUE!
A80: =IFERROR((V80*V$2+W80*W$2+X80*X$2)*100/(V$4*V$2+W$4*W$2+X$4*X$2),0) -> 0 | B80: 154 | C80: Rose, Tyler | D80: P | E80: L | F80: L | G80: 19 | H80: ? | I80: ? | J80: ? | K80: ? | L80: ? | M80: ? | N80: ? | O80: ? | P80: ? | Q80: ? | R80: ? | S80: ? | T80: ? | U80: ? | V80: =K$1*(0.000001*K80^3)+L$1*((-0.000002)*L80^3+0.00032*L80^2+(-0.0021)*L80)+M$1*((-0.000002)*M80^3+0.00032*M80^2+(-0.0021)*M80)+N$1*((-0.000002)*N80^3+0.00032*N80^2+(-0.0021)*N80)+O$1*((-0.000002)*O80^3+0.00032*O80^2+(-0.0021)*O80) -> #VALUE! | W80: =P$1*((-0.000002)*P80^3+0.00032*P80^2+(-0.0021)*P80)+Q$1*((-0.000002)*Q80^3+0.00032*Q80^2+(-0.0021)*Q80)+R$1*((-0.000002)*R80^3+0.00032*R80^2+(-0.0021)*R80)+S$1*((-0.000002)*S80^3+0.00032*S80^2+(-0.0021)*S80)+T$1*((-0.000002)*T80^3+0.00032*T80^2+(-0.0021)*T80) -> #VALUE! | X80: =(I$1*((-0.000002)*I80^3+0.00032*I80^2+(-0.0021)*I80)+J$1*((-0.000002)*J80^3+0.00032*J80^2+(-0.0021)*J80)+H$1*((-0.000002)*H80^3+0.00032*H80^2+(-0.0021)*H80))*(MAX(0.05,MIN(1,(2*J80+I80)/120)*MIN(1,I80/10)*MIN(1,J80/10))) -> #VALUE! | Y80: =(I$1*((-0.000002)*I80^3+0.00032*I80^2+(-0.0021)*I80)+J$1*((-0.000002)*J80^3+0.00032*J80^2+(-0.0021)*J80)+H$1*((-0.000002)*H80^3+0.00032*H80^2+(-0.0021)*H80))*(MAX(0.05,MIN(1,(2*J80+I80)/120)*MIN(1,I80/10)*MIN(1,J80/10))) -> #VALUE! | Z80: =IF(AND(J80>50,I80+J80>75),"SP",IF(2*I80+J80>120,"RP","CRAP")) -> #VALUE! | AA80: =IF(AND(J80>50,I80+J80>75),"SP",IF(2*I80+J80>120,"RP","CRAP")) -> #VALUE!
A81: =IFERROR((V81*V$2+W81*W$2+X81*X$2)*100/(V$4*V$2+W$4*W$2+X$4*X$2),0) -> 0 | B81: 155 | C81: Concepcion, J.O. | D81: P | E81: L | F81: L | G81: 18 | H81: ? | I81: ? | J81: ? | K81: ? | L81: ? | M81: ? | N81: ? | O81: ? | P81: ? | Q81: ? | R81: ? | S81: ? | T81: ? | U81: ? | V81: =K$1*(0.000001*K81^3)+L$1*((-0.000002)*L81^3+0.00032*L81^2+(-0.0021)*L81)+M$1*((-0.000002)*M81^3+0.00032*M81^2+(-0.0021)*M81)+N$1*((-0.000002)*N81^3+0.00032*N81^2+(-0.0021)*N81)+O$1*((-0.000002)*O81^3+0.00032*O81^2+(-0.0021)*O81) -> #VALUE! | W81: =P$1*((-0.000002)*P81^3+0.00032*P81^2+(-0.0021)*P81)+Q$1*((-0.000002)*Q81^3+0.00032*Q81^2+(-0.0021)*Q81)+R$1*((-0.000002)*R81^3+0.00032*R81^2+(-0.0021)*R81)+S$1*((-0.000002)*S81^3+0.00032*S81^2+(-0.0021)*S81)+T$1*((-0.000002)*T81^3+0.00032*T81^2+(-0.0021)*T81) -> #VALUE! | X81: =(I$1*((-0.000002)*I81^3+0.00032*I81^2+(-0.0021)*I81)+J$1*((-0.000002)*J81^3+0.00032*J81^2+(-0.0021)*J81)+H$1*((-0.000002)*H81^3+0.00032*H81^2+(-0.0021)*H81))*(MAX(0.05,MIN(1,(2*J81+I81)/120)*MIN(1,I81/10)*MIN(1,J81/10))) -> #VALUE! | Y81: =(I$1*((-0.000002)*I81^3+0.00032*I81^2+(-0.0021)*I81)+J$1*((-0.000002)*J81^3+0.00032*J81^2+(-0.0021)*J81)+H$1*((-0.000002)*H81^3+0.00032*H81^2+(-0.0021)*H81))*(MAX(0.05,MIN(1,(2*J81+I81)/120)*MIN(1,I81/10)*MIN(1,J81/10))) -> #VALUE! | Z81: =IF(AND(J81>50,I81+J81>75),"SP",IF(2*I81+J81>120,"RP","CRAP")) -> #VALUE! | AA81: =IF(AND(J81>50,I81+J81>75),"SP",IF(2*I81+J81>120,"RP","CRAP")) -> #VALUE!
... A152: =IFERROR((V152*V$2+W152*W$2+X152*X$2)*100/(V$4*V$2+W$4*W$2+X$4*X$2),0) -> 0 | B152: 226 | C152: Sanders, Frank | D152: P | E152: R | F152: R | G152: 22 | H152: ? | I152: ? | J152: ? | K152: ? | L152: ? | M152: ? | N152: ? | O152: ? | P152: ? | Q152: ? | R152: ? | S152: ? | T152: ? | U152: ? | V152: =K$1*(0.000001*K152^3)+L$1*((-0.000002)*L152^3+0.00032*L152^2+(-0.0021)*L152)+M$1*((-0.000002)*M152^3+0.00032*M152^2+(-0.0021)*M152)+N$1*((-0.000002)*N152^3+0.00032*N152^2+(-0.0021)*N152)+O$1*((-0.000002)*O152^3+0.00032*O152^2+(-0.0021)*O152) -> #VALUE! | W152: =P$1*((-0.000002)*P152^3+0.00032*P152^2+(-0.0021)*P152)+Q$1*((-0.000002)*Q152^3+0.00032*Q152^2+(-0.0021)*Q152)+R$1*((-0.000002)*R152^3+0.00032*R152^2+(-0.0021)*R152)+S$1*((-0.000002)*S152^3+0.00032*S152^2+(-0.0021)*S152)+T$1*((-0.000002)*T152^3+0.00032*T152^2+(-0.0021)*T152) -> #VALUE! | X152: =(I$1*((-0.000002)*I152^3+0.00032*I152^2+(-0.0021)*I152)+J$1*((-0.000002)*J152^3+0.00032*J152^2+(-0.0021)*J152)+H$1*((-0.000002)*H152^3+0.00032*H152^2+(-0.0021)*H152))*(MAX(0.05,MIN(1,(2*J152+I152)/120)*MIN(1,I152/10)*MIN(1,J152/10))) -> #VALUE! | Y152: =(I$1*((-0.000002)*I152^3+0.00032*I152^2+(-0.0021)*I152)+J$1*((-0.000002)*J152^3+0.00032*J152^2+(-0.0021)*J152)+H$1*((-0.000002)*H152^3+0.00032*H152^2+(-0.0021)*H152))*(MAX(0.05,MIN(1,(2*J152+I152)/120)*MIN(1,I152/10)*MIN(1,J152/10))) -> #VALUE! | Z152: =IF(AND(J152>50,I152+J152>75),"SP",IF(2*I152+J152>120,"RP","CRAP")) -> #VALUE! | AA152: =IF(AND(J152>50,I152+J152>75),"SP",IF(2*I152+J152>120,"RP","CRAP")) -> #VALUE!
A153: =IFERROR((V153*V$2+W153*W$2+X153*X$2)*100/(V$4*V$2+W$4*W$2+X$4*X$2),0) -> 10.589414 | B153: 34 | C153: Carson, Eric | D153: SS | E153: R | F153: R | G153: 18 | J153: 84 | K153: 33 | L153: 11 | M153: 8 | N153: 10 | O153: 0 | P153: 27 | Q153: 64 | R153: 0 | S153: 0 | T153: 0 | U153: 0 | V153: =K$1*(0.000001*K153^3)+L$1*((-0.000002)*L153^3+0.00032*L153^2+(-0.0021)*L153)+M$1*((-0.000002)*M153^3+0.00032*M153^2+(-0.0021)*M153)+N$1*((-0.000002)*N153^3+0.00032*N153^2+(-0.0021)*N153)+O$1*((-0.000002)*O153^3+0.00032*O153^2+(-0.0021)*O153) -> 0.090616 | W153: =P$1*((-0.000002)*P153^3+0.00032*P153^2+(-0.0021)*P153)+Q$1*((-0.000002)*Q153^3+0.00032*Q153^2+(-0.0021)*Q153)+R$1*((-0.000002)*R153^3+0.00032*R153^2+(-0.0021)*R153)+S$1*((-0.000002)*S153^3+0.00032*S153^2+(-0.0021)*S153)+T$1*((-0.000002)*T153^3+0.00032*T153^2+(-0.0021)*T153) -> 1.578492 | X153: =(I$1*((-0.000002)*I153^3+0.00032*I153^2+(-0.0021)*I153)+J$1*((-0.000002)*J153^3+0.00032*J153^2+(-0.0021)*J153)+H$1*((-0.000002)*H153^3+0.00032*H153^2+(-0.0021)*H153))*(MAX(0.05,MIN(1,(2*J153+I153)/120)*MIN(1,I153/10)*MIN(1,J153/10))) -> 0.1792224 | Y153: =(I$1*((-0.000002)*I153^3+0.00032*I153^2+(-0.0021)*I153)+J$1*((-0.000002)*J153^3+0.00032*J153^2+(-0.0021)*J153)+H$1*((-0.000002)*H153^3+0.00032*H153^2+(-0.0021)*H153))*(MAX(0.05,MIN(1,(2*J153+I153)/120)*MIN(1,I153/10)*MIN(1,J153/10))) -> 0.1792224 | Z153: =IF(AND(J153>50,I153+J153>75),"SP",IF(2*I153+J153>120,"RP","CRAP")) -> SP | AA153: =IF(AND(J153>50,I153+J153>75),"SP",IF(2*I153+J153>120,"RP","CRAP")) -> SP
A154: =IFERROR((V154*V$2+W154*W$2+X154*X$2)*100/(V$4*V$2+W$4*W$2+X$4*X$2),0) -> 9.8720522 | B154: 150 | C154: Rhodes, Chadd | D154: LF | E154: R | F154: R | G154: 18 | J154: 92 | K154: 25 | L154: 26 | M154: 16 | N154: 8 | O154: 13 | P154: 25 | Q154: 52 | R154: 0 | S154: 0 | T154: 0 | U154: 0 | V154: =K$1*(0.000001*K154^3)+L$1*((-0.000002)*L154^3+0.00032*L154^2+(-0.0021)*L154)+M$1*((-0.000002)*M154^3+0.00032*M154^2+(-0.0021)*M154)+N$1*((-0.000002)*N154^3+0.00032*N154^2+(-0.0021)*N154)+O$1*((-0.000002)*O154^3+0.00032*O154^2+(-0.0021)*O154) -> 0.2230184 | W154: =P$1*((-0.000002)*P154^3+0.00032*P154^2+(-0.0021)*P154)+Q$1*((-0.000002)*Q154^3+0.00032*Q154^2+(-0.0021)*Q154)+R$1*((-0.000002)*R154^3+0.00032*R154^2+(-0.0021)*R154)+S$1*((-0.000002)*S154^3+0.00032*S154^2+(-0.0021)*S154)+T$1*((-0.000002)*T154^3+0.00032*T154^2+(-0.0021)*T154) -> 1.182228 | X154: =(I$1*((-0.000002)*I154^3+0.00032*I154^2+(-0.0021)*I154)+J$1*((-0.000002)*J154^3+0.00032*J154^2+(-0.0021)*J154)+H$1*((-0.000002)*H154^3+0.00032*H154^2+(-0.0021)*H154))*(MAX(0.05,MIN(1,(2*J154+I154)/120)*MIN(1,I154/10)*MIN(1,J154/10))) -> 0.1915808 | Y154: =(I$1*((-0.000002)*I154^3+0.00032*I154^2+(-0.0021)*I154)+J$1*((-0.000002)*J154^3+0.00032*J154^2+(-0.0021)*J154)+H$1*((-0.000002)*H154^3+0.00032*H154^2+(-0.0021)*H154))*(MAX(0.05,MIN(1,(2*J154+I154)/120)*MIN(1,I154/10)*MIN(1,J154/10))) -> 0.1915808 | Z154: =IF(AND(J154>50,I154+J154>75),"SP",IF(2*I154+J154>120,"RP","CRAP")) -> SP | AA154: =IF(AND(J154>50,I154+J154>75),"SP",IF(2*I154+J154>120,"RP","CRAP")) -> SP
A155: =IFERROR((V155*V$2+W155*W$2+X155*X$2)*100/(V$4*V$2+W$4*W$2+X$4*X$2),0) -> 11.280152 | B155: 71 | C155: Grahe, Jonathan | D155: LF | E155: R | F155: R | G155: 18 | J155: 93 | K155: 13 | L155: 19 | M155: 16 | N155: 8 | O155: 9 | P155: 37 | Q155: 57 | R155: 0 | S155: 0 | T155: 0 | U155: 0 | V155: =K$1*(0.000001*K155^3)+L$1*((-0.000002)*L155^3+0.00032*L155^2+(-0.0021)*L155)+M$1*((-0.000002)*M155^3+0.00032*M155^2+(-0.0021)*M155)+N$1*((-0.000002)*N155^3+0.00032*N155^2+(-0.0021)*N155)+O$1*((-0.000002)*O155^3+0.00032*O155^2+(-0.0021)*O155) -> 0.1281316 | W155: =P$1*((-0.000002)*P155^3+0.00032*P155^2+(-0.0021)*P155)+Q$1*((-0.000002)*Q155^3+0.00032*Q155^2+(-0.0021)*Q155)+R$1*((-0.000002)*R155^3+0.00032*R155^2+(-0.0021)*R155)+S$1*((-0.000002)*S155^3+0.00032*S155^2+(-0.0021)*S155)+T$1*((-0.000002)*T155^3+0.00032*T155^2+(-0.0021)*T155) -> 1.617336 | X155: =(I$1*((-0.000002)*I155^3+0.00032*I155^2+(-0.0021)*I155)+J$1*((-0.000002)*J155^3+0.00032*J155^2+(-0.0021)*J155)+H$1*((-0.000002)*H155^3+0.00032*H155^2+(-0.0021)*H155))*(MAX(0.05,MIN(1,(2*J155+I155)/120)*MIN(1,I155/10)*MIN(1,J155/10))) -> 0.1927332 | Y155: =(I$1*((-0.000002)*I155^3+0.00032*I155^2+(-0.0021)*I155)+J$1*((-0.000002)*J155^3+0.00032*J155^2+(-0.0021)*J155)+H$1*((-0.000002)*H155^3+0.00032*H155^2+(-0.0021)*H155))*(MAX(0.05,MIN(1,(2*J155+I155)/120)*MIN(1,I155/10)*MIN(1,J155/10))) -> 0.1927332 | Z155: =IF(AND(J155>50,I155+J155>75),"SP",IF(2*I155+J155>120,"RP","CRAP")) -> SP | AA155: =IF(AND(J155>50,I155+J155>75),"SP",IF(2*I155+J155>120,"RP","CRAP")) -> SP
A156: =IFERROR((V156*V$2+W156*W$2+X156*X$2)*100/(V$4*V$2+W$4*W$2+X$4*X$2),0) -> 11.271973 | B156: 141 | C156: Morris, Blake | D156: 1B | E156: L | F156: L | G156: 18 | J156: 91 | K156: 10 | L156: 16 | M156: 2 | N156: 13 | O156: 1 | P156: 39 | Q156: 61 | R156: 0 | S156: 0 | T156: 0 | U156: 0 | V156: =K$1*(0.000001*K156^3)+L$1*((-0.000002)*L156^3+0.00032*L156^2+(-0.0021)*L156)+M$1*((-0.000002)*M156^3+0.00032*M156^2+(-0.0021)*M156)+N$1*((-0.000002)*N156^3+0.00032*N156^2+(-0.0021)*N156)+O$1*((-0.000002)*O156^3+0.00032*O156^2+(-0.0021)*O156) -> 0.0418448 | W156: =P$1*((-0.000002)*P156^3+0.00032*P156^2+(-0.0021)*P156)+Q$1*((-0.000002)*Q156^3+0.00032*Q156^2+(-0.0021)*Q156)+R$1*((-0.000002)*R156^3+0.00032*R156^2+(-0.0021)*R156)+S$1*((-0.000002)*S156^3+0.00032*S156^2+(-0.0021)*S156)+T$1*((-0.000002)*T156^3+0.00032*T156^2+(-0.0021)*T156) -> 1.78968 | X156: =(I$1*((-0.000002)*I156^3+0.00032*I156^2+(-0.0021)*I156)+J$1*((-0.000002)*J156^3+0.00032*J156^2+(-0.0021)*J156)+H$1*((-0.000002)*H156^3+0.00032*H156^2+(-0.0021)*H156))*(MAX(0.05,MIN(1,(2*J156+I156)/120)*MIN(1,I156/10)*MIN(1,J156/10))) -> 0.1903356 | Y156: =(I$1*((-0.000002)*I156^3+0.00032*I156^2+(-0.0021)*I156)+J$1*((-0.000002)*J156^3+0.00032*J156^2+(-0.0021)*J156)+H$1*((-0.000002)*H156^3+0.00032*H156^2+(-0.0021)*H156))*(MAX(0.05,MIN(1,(2*J156+I156)/120)*MIN(1,I156/10)*MIN(1,J156/10))) -> 0.1903356 | Z156: =IF(AND(J156>50,I156+J156>75),"SP",IF(2*I156+J156>120,"RP","CRAP")) -> SP | AA156: =IF(AND(J156>50,I156+J156>75),"SP",IF(2*I156+J156>120,"RP","CRAP")) -> SP
A157: =IFERROR((V157*V$2+W157*W$2+X157*X$2)*100/(V$4*V$2+W$4*W$2+X$4*X$2),0) -> 9.5056986 | B157: 192 | C157: Castillo, Juan | D157: DH | E157: R | F157: R | G157: 18 | J157: 88 | K157: 27 | L157: 7 | M157: 20 | N157: 16 | O157: 13 | P157: 58 | Q157: 19 | R157: 0 | S157: 0 | T157: 0 | U157: 0 | V157: =K$1*(0.000001*K157^3)+L$1*((-0.000002)*L157^3+0.00032*L157^2+(-0.0021)*L157)+M$1*((-0.000002)*M157^3+0.00032*M157^2+(-0.0021)*M157)+N$1*((-0.000002)*N157^3+0.00032*N157^2+(-0.0021)*N157)+O$1*((-0.000002)*O157^3+0.00032*O157^2+(-0.0021)*O157) -> 0.1571628 | W157: =P$1*((-0.000002)*P157^3+0.00032*P157^2+(-0.0021)*P157)+Q$1*((-0.000002)*Q157^3+0.00032*Q157^2+(-0.0021)*Q157)+R$1*((-0.000002)*R157^3+0.00032*R157^2+(-0.0021)*R157)+S$1*((-0.000002)*S157^3+0.00032*S157^2+(-0.0021)*S157)+T$1*((-0.000002)*T157^3+0.00032*T157^2+(-0.0021)*T157) -> 1.252716 | X157: =(I$1*((-0.000002)*I157^3+0.00032*I157^2+(-0.0021)*I157)+J$1*((-0.000002)*J157^3+0.00032*J157^2+(-0.0021)*J157)+H$1*((-0.000002)*H157^3+0.00032*H157^2+(-0.0021)*H157))*(MAX(0.05,MIN(1,(2*J157+I157)/120)*MIN(1,I157/10)*MIN(1,J157/10))) -> 0.1860672 | Y157: =(I$1*((-0.000002)*I157^3+0.00032*I157^2+(-0.0021)*I157)+J$1*((-0.000002)*J157^3+0.00032*J157^2+(-0.0021)*J157)+H$1*((-0.000002)*H157^3+0.00032*H157^2+(-0.0021)*H157))*(MAX(0.05,MIN(1,(2*J157+I157)/120)*MIN(1,I157/10)*MIN(1,J157/10))) -> 0.1860672 | Z157: =IF(AND(J157>50,I157+J157>75),"SP",IF(2*I157+J157>120,"RP","CRAP")) -> SP | AA157: =IF(AND(J157>50,I157+J157>75),"SP",IF(2*I157+J157>120,"RP","CRAP")) -> SP
A158: =IFERROR((V158*V$2+W158*W$2+X158*X$2)*100/(V$4*V$2+W$4*W$2+X$4*X$2),0) -> 8.3188628 | B158: 184 | C158: Amaro, Alving | D158: DH | E158: R | F158: R | G158: 22 | J158: 91 | K158: 19 | L158: 22 | M158: 0 | N158: 28 | O158: 0 | P158: 6 | Q158: 57 | R158: 0 | S158: 0 | T158: 0 | U158: 0 | V158: =K$1*(0.000001*K158^3)+L$1*((-0.000002)*L158^3+0.00032*L158^2+(-0.0021)*L158)+M$1*((-0.000002)*M158^3+0.00032*M158^2+(-0.0021)*M158)+N$1*((-0.000002)*N158^3+0.00032*N158^2+(-0.0021)*N158)+O$1*((-0.000002)*O158^3+0.00032*O158^2+(-0.0021)*O158) -> 0.1307372 | W158: =P$1*((-0.000002)*P158^3+0.00032*P158^2+(-0.0021)*P158)+Q$1*((-0.000002)*Q158^3+0.00032*Q158^2+(-0.0021)*Q158)+R$1*((-0.000002)*R158^3+0.00032*R158^2+(-0.0021)*R158)+S$1*((-0.000002)*S158^3+0.00032*S158^2+(-0.0021)*S158)+T$1*((-0.000002)*T158^3+0.00032*T158^2+(-0.0021)*T158) -> 1.096164 | X158: =(I$1*((-0.000002)*I158^3+0.00032*I158^2+(-0.0021)*I158)+J$1*((-0.000002)*J158^3+0.00032*J158^2+(-0.0021)*J158)+H$1*((-0.000002)*H158^3+0.00032*H158^2+(-0.0021)*H158))*(MAX(0.05,MIN(1,(2*J158+I158)/120)*MIN(1,I158/10)*MIN(1,J158/10))) -> 0.1903356 | Y158: =(I$1*((-0.000002)*I158^3+0.00032*I158^2+(-0.0021)*I158)+J$1*((-0.000002)*J158^3+0.00032*J158^2+(-0.0021)*J158)+H$1*((-0.000002)*H158^3+0.00032*H158^2+(-0.0021)*H158))*(MAX(0.05,MIN(1,(2*J158+I158)/120)*MIN(1,I158/10)*MIN(1,J158/10))) -> 0.1903356 | Z158: =IF(AND(J158>50,I158+J158>75),"SP",IF(2*I158+J158>120,"RP","CRAP")) -> SP | AA158: =IF(AND(J158>50,I158+J158>75),"SP",IF(2*I158+J158>120,"RP","CRAP")) -> SP
A159: =IFERROR((V159*V$2+W159*W$2+X159*X$2)*100/(V$4*V$2+W$4*W$2+X$4*X$2),0) -> 9.1174496 | B159: 27 | C159: Bittle, Tommie | D159: 1B | E159: R | F159: R | G159: 18 | J159: 85 | K159: 36 | L159: 23 | M159: 24 | N159: 16 | O159: 21 | P159: 31 | Q159: 32 | R159: 0 | S159: 0 | T159: 0 | U159: 0 | V159: =K$1*(0.000001*K159^3)+L$1*((-0.000002)*L159^3+0.00032*L159^2+(-0.0021)*L159)+M$1*((-0.000002)*M159^3+0.00032*M159^2+(-0.0021)*M159)+N$1*((-0.000002)*N159^3+0.00032*N159^2+(-0.0021)*N159)+O$1*((-0.000002)*O159^3+0.00032*O159^2+(-0.0021)*O159) -> 0.3730912 | W159: =P$1*((-0.000002)*P159^3+0.00032*P159^2+(-0.0021)*P159)+Q$1*((-0.000002)*Q159^3+0.00032*Q159^2+(-0.0021)*Q159)+R$1*((-0.000002)*R159^3+0.00032*R159^2+(-0.0021)*R159)+S$1*((-0.000002)*S159^3+0.00032*S159^2+(-0.0021)*S159)+T$1*((-0.000002)*T159^3+0.00032*T159^2+(-0.0021)*T159) -> 0.755564 | X159: =(I$1*((-0.000002)*I159^3+0.00032*I159^2+(-0.0021)*I159)+J$1*((-0.000002)*J159^3+0.00032*J159^2+(-0.0021)*J159)+H$1*((-0.000002)*H159^3+0.00032*H159^2+(-0.0021)*H159))*(MAX(0.05,MIN(1,(2*J159+I159)/120)*MIN(1,I159/10)*MIN(1,J159/10))) -> 0.18105 | Y159: =(I$1*((-0.000002)*I159^3+0.00032*I159^2+(-0.0021)*I159)+J$1*((-0.000002)*J159^3+0.00032*J159^2+(-0.0021)*J159)+H$1*((-0.000002)*H159^3+0.00032*H159^2+(-0.0021)*H159))*(MAX(0.05,MIN(1,(2*J159+I159)/120)*MIN(1,I159/10)*MIN(1,J159/10))) -> 0.18105 | Z159: =IF(AND(J159>50,I159+J159>75),"SP",IF(2*I159+J159>120,"RP","CRAP")) -> SP | AA159: =IF(AND(J159>50,I159+J159>75),"SP",IF(2*I159+J159>120,"RP","CRAP")) -> SP
A160: =IFERROR((V160*V$2+W160*W$2+X160*X$2)*100/(V$4*V$2+W$4*W$2+X$4*X$2),0) -> 11.139907 | B160: 156 | C160: Cordero, Alfredo | D160: 1B | E160: S | F160: R | G160: 18 | J160: 81 | K160: 14 | L160: 13 | M160: 17 | N160: 12 | O160: 15 | P160: 39 | Q160: 56 | R160: 0 | S160: 0 | T160: 0 | U160: 0 | V160: =K$1*(0.000001*K160^3)+L$1*((-0.000002)*L160^3+0.00032*L160^2+(-0.0021)*L160)+M$1*((-0.000002)*M160^3+0.00032*M160^2+(-0.0021)*M160)+N$1*((-0.000002)*N160^3+0.00032*N160^2+(-0.0021)*N160)+O$1*((-0.000002)*O160^3+0.00032*O160^2+(-0.0021)*O160) -> 0.1085398 | W160: =P$1*((-0.000002)*P160^3+0.00032*P160^2+(-0.0021)*P160)+Q$1*((-0.000002)*Q160^3+0.00032*Q160^2+(-0.0021)*Q160)+R$1*((-0.000002)*R160^3+0.00032*R160^2+(-0.0021)*R160)+S$1*((-0.000002)*S160^3+0.00032*S160^2+(-0.0021)*S160)+T$1*((-0.000002)*T160^3+0.00032*T160^2+(-0.0021)*T160) -> 1.64174 | X160: =(I$1*((-0.000002)*I160^3+0.00032*I160^2+(-0.0021)*I160)+J$1*((-0.000002)*J160^3+0.00032*J160^2+(-0.0021)*J160)+H$1*((-0.000002)*H160^3+0.00032*H160^2+(-0.0021)*H160))*(MAX(0.05,MIN(1,(2*J160+I160)/120)*MIN(1,I160/10)*MIN(1,J160/10))) -> 0.1733076 | Y160: =(I$1*((-0.000002)*I160^3+0.00032*I160^2+(-0.0021)*I160)+J$1*((-0.000002)*J160^3+0.00032*J160^2+(-0.0021)*J160)+H$1*((-0.000002)*H160^3+0.00032*H160^2+(-0.0021)*H160))*(MAX(0.05,MIN(1,(2*J160+I160)/120)*MIN(1,I160/10)*MIN(1,J160/10))) -> 0.1733076 | Z160: =IF(AND(J160>50,I160+J160>75),"SP",IF(2*I160+J160>120,"RP","CRAP")) -> SP | AA160: =IF(AND(J160>50,I160+J160>75),"SP",IF(2*I160+J160>120,"RP","CRAP")) -> SP
A161: =IFERROR((V161*V$2+W161*W$2+X161*X$2)*100/(V$4*V$2+W$4*W$2+X$4*X$2),0) -> 12.507178 | B161: 114 | C161: Viciedo, Everth | D161: C | E161: R | F161: R | G161: 18 | J161: 72 | K161: 8 | L161: 5 | M161: 12 | N161: 10 | O161: 11 | P161: 22 | Q161: 89 | R161: 0 | S161: 0 | T161: 0 | U161: 0 | V161: =K$1*(0.000001*K161^3)+L$1*((-0.000002)*L161^3+0.00032*L161^2+(-0.0021)*L161)+M$1*((-0.000002)*M161^3+0.00032*M161^2+(-0.0021)*M161)+N$1*((-0.000002)*N161^3+0.00032*N161^2+(-0.0021)*N161)+O$1*((-0.000002)*O161^3+0.00032*O161^2+(-0.0021)*O161) -> 0.0288016 | W161: =P$1*((-0.000002)*P161^3+0.00032*P161^2+(-0.0021)*P161)+Q$1*((-0.000002)*Q161^3+0.00032*Q161^2+(-0.0021)*Q161)+R$1*((-0.000002)*R161^3+0.00032*R161^2+(-0.0021)*R161)+S$1*((-0.000002)*S161^3+0.00032*S161^2+(-0.0021)*S161)+T$1*((-0.000002)*T161^3+0.00032*T161^2+(-0.0021)*T161) -> 2.050532 | X161: =(I$1*((-0.000002)*I161^3+0.00032*I161^2+(-0.0021)*I161)+J$1*((-0.000002)*J161^3+0.00032*J161^2+(-0.0021)*J161)+H$1*((-0.000002)*H161^3+0.00032*H161^2+(-0.0021)*H161))*(MAX(0.05,MIN(1,(2*J161+I161)/120)*MIN(1,I161/10)*MIN(1,J161/10))) -> 0.1522368 | Y161: =(I$1*((-0.000002)*I161^3+0.00032*I161^2+(-0.0021)*I161)+J$1*((-0.000002)*J161^3+0.00032*J161^2+(-0.0021)*J161)+H$1*((-0.000002)*H161^3+0.00032*H161^2+(-0.0021)*H161))*(MAX(0.05,MIN(1,(2*J161+I161)/120)*MIN(1,I161/10)*MIN(1,J161/10))) -> 0.1522368 | Z161: =IF(AND(J161>50,I161+J161>75),"SP",IF(2*I161+J161>120,"RP","CRAP")) -> CRAP | AA161: =IF(AND(J161>50,I161+J161>75),"SP",IF(2*I161+J161>120,"RP","CRAP")) -> CRAP
A162: =IFERROR((V162*V$2+W162*W$2+X162*X$2)*100/(V$4*V$2+W$4*W$2+X$4*X$2),0) -> 10.659584 | B162: 49 | C162: Rodriguez, Arquimedes | D162: RF | E162: S | F162: L | G162: 18 | J162: 75 | K162: 17 | L162: 22 | M162: 17 | N162: 4 | O162: 0 | P162: 29 | Q162: 58 | R162: 0 | S162: 0 | T162: 0 | U162: 0 | V162: =K$1*(0.000001*K162^3)+L$1*((-0.000002)*L162^3+0.00032*L162^2+(-0.0021)*L162)+M$1*((-0.000002)*M162^3+0.00032*M162^2+(-0.0021)*M162)+N$1*((-0.000002)*N162^3+0.00032*N162^2+(-0.0021)*N162)+O$1*((-0.000002)*O162^3+0.00032*O162^2+(-0.0021)*O162) -> 0.1669594 | W162: =P$1*((-0.000002)*P162^3+0.00032*P162^2+(-0.0021)*P162)+Q$1*((-0.000002)*Q162^3+0.00032*Q162^2+(-0.0021)*Q162)+R$1*((-0.000002)*R162^3+0.00032*R162^2+(-0.0021)*R162)+S$1*((-0.000002)*S162^3+0.00032*S162^2+(-0.0021)*S162)+T$1*((-0.000002)*T162^3+0.00032*T162^2+(-0.0021)*T162) -> 1.447796 | X162: =(I$1*((-0.000002)*I162^3+0.00032*I162^2+(-0.0021)*I162)+J$1*((-0.000002)*J162^3+0.00032*J162^2+(-0.0021)*J162)+H$1*((-0.000002)*H162^3+0.00032*H162^2+(-0.0021)*H162))*(MAX(0.05,MIN(1,(2*J162+I162)/120)*MIN(1,I162/10)*MIN(1,J162/10))) -> 0.15975 | Y162: =(I$1*((-0.000002)*I162^3+0.00032*I162^2+(-0.0021)*I162)+J$1*((-0.000002)*J162^3+0.00032*J162^2+(-0.0021)*J162)+H$1*((-0.000002)*H162^3+0.00032*H162^2+(-0.0021)*H162))*(MAX(0.05,MIN(1,(2*J162+I162)/120)*MIN(1,I162/10)*MIN(1,J162/10))) -> 0.15975 | Z162: =IF(AND(J162>50,I162+J162>75),"SP",IF(2*I162+J162>120,"RP","CRAP")) -> CRAP | AA162: =IF(AND(J162>50,I162+J162>75),"SP",IF(2*I162+J162>120,"RP","CRAP")) -> CRAP
A163: =IFERROR((V163*V$2+W163*W$2+X163*X$2)*100/(V$4*V$2+W$4*W$2+X$4*X$2),0) -> 11.080791 | B163: 155 | C163: Wagner, Doug | D163: LF | E163: R | F163: R | G163: 18 | J163: 87 | K163: 12 | L163: 9 | M163: 26 | N163: 19 | O163: 11 | P163: 35 | Q163: 52 | R163: 0 | S163: 0 | T163: 0 | U163: 0 | V163: =K$1*(0.000001*K163^3)+L$1*((-0.000002)*L163^3+0.00032*L163^2+(-0.0021)*L163)+M$1*((-0.000002)*M163^3+0.00032*M163^2+(-0.0021)*M163)+N$1*((-0.000002)*N163^3+0.00032*N163^2+(-0.0021)*N163)+O$1*((-0.000002)*O163^3+0.00032*O163^2+(-0.0021)*O163) -> 0.213842 | W163: =P$1*((-0.000002)*P163^3+0.00032*P163^2+(-0.0021)*P163)+Q$1*((-0.000002)*Q163^3+0.00032*Q163^2+(-0.0021)*Q163)+R$1*((-0.000002)*R163^3+0.00032*R163^2+(-0.0021)*R163)+S$1*((-0.000002)*S163^3+0.00032*S163^2+(-0.0021)*S163)+T$1*((-0.000002)*T163^3+0.00032*T163^2+(-0.0021)*T163) -> 1.415228 | X163: =(I$1*((-0.000002)*I163^3+0.00032*I163^2+(-0.0021)*I163)+J$1*((-0.000002)*J163^3+0.00032*J163^2+(-0.0021)*J163)+H$1*((-0.000002)*H163^3+0.00032*H163^2+(-0.0021)*H163))*(MAX(0.05,MIN(1,(2*J163+I163)/120)*MIN(1,I163/10)*MIN(1,J163/10))) -> 0.1844748 | Y163: =(I$1*((-0.000002)*I163^3+0.00032*I163^2+(-0.0021)*I163)+J$1*((-0.000002)*J163^3+0.00032*J163^2+(-0.0021)*J163)+H$1*((-0.000002)*H163^3+0.00032*H163^2+(-0.0021)*H163))*(MAX(0.05,MIN(1,(2*J163+I163)/120)*MIN(1,I163/10)*MIN(1,J163/10))) -> 0.1844748 | Z163: =IF(AND(J163>50,I163+J163>75),"SP",IF(2*I163+J163>120,"RP","CRAP")) -> SP | AA163: =IF(AND(J163>50,I163+J163>75),"SP",IF(2*I163+J163>120,"RP","CRAP")) -> SP
A164: =IFERROR((V164*V$2+W164*W$2+X164*X$2)*100/(V$4*V$2+W$4*W$2+X$4*X$2),0) -> 9.8125332 | B164: 197 | C164: Graves, Dion | D164: DH | E164: R | F164: R | G164: 19 | J164: 70 | K164: 29 | L164: 3 | M164: 36 | N164: 29 | O164: 0 | P164: 12 | Q164: 44 | R164: 0 | S164: 0 | T164: 0 | U164: 0 | V164: =K$1*(0.000001*K164^3)+L$1*((-0.000002)*L164^3+0.00032*L164^2+(-0.0021)*L164)+M$1*((-0.000002)*M164^3+0.00032*M164^2+(-0.0021)*M164)+N$1*((-0.000002)*N164^3+0.00032*N164^2+(-0.0021)*N164)+O$1*((-0.000002)*O164^3+0.00032*O164^2+(-0.0021)*O164) -> 0.4459044 | W164: =P$1*((-0.000002)*P164^3+0.00032*P164^2+(-0.0021)*P164)+Q$1*((-0.000002)*Q164^3+0.00032*Q164^2+(-0.0021)*Q164)+R$1*((-0.000002)*R164^3+0.00032*R164^2+(-0.0021)*R164)+S$1*((-0.000002)*S164^3+0.00032*S164^2+(-0.0021)*S164)+T$1*((-0.000002)*T164^3+0.00032*T164^2+(-0.0021)*T164) -> 0.748352 | X164: =(I$1*((-0.000002)*I164^3+0.00032*I164^2+(-0.0021)*I164)+J$1*((-0.000002)*J164^3+0.00032*J164^2+(-0.0021)*J164)+H$1*((-0.000002)*H164^3+0.00032*H164^2+(-0.0021)*H164))*(MAX(0.05,MIN(1,(2*J164+I164)/120)*MIN(1,I164/10)*MIN(1,J164/10))) -> 0.147 | Y164: =(I$1*((-0.000002)*I164^3+0.00032*I164^2+(-0.0021)*I164)+J$1*((-0.000002)*J164^3+0.00032*J164^2+(-0.0021)*J164)+H$1*((-0.000002)*H164^3+0.00032*H164^2+(-0.0021)*H164))*(MAX(0.05,MIN(1,(2*J164+I164)/120)*MIN(1,I164/10)*MIN(1,J164/10))) -> 0.147 | Z164: =IF(AND(J164>50,I164+J164>75),"SP",IF(2*I164+J164>120,"RP","CRAP")) -> CRAP | AA164: =IF(AND(J164>50,I164+J164>75),"SP",IF(2*I164+J164>120,"RP","CRAP")) -> CRAP
... A206: =IFERROR((V206*V$2+W206*W$2+X206*X$2)*100/(V$4*V$2+W$4*W$2+X$4*X$2),0) -> 2.5859276 | B206: 91 | C206: Woodall, Timothy | D206: 1B | E206: L | F206: L | G206: 18 | J206: 86 | K206: 13 | L206: 6 | M206: 6 | N206: 7 | O206: 0 | P206: 4 | Q206: 31 | R206: 0 | S206: 0 | T206: 0 | U206: 0 | V206: =K$1*(0.000001*K206^3)+L$1*((-0.000002)*L206^3+0.00032*L206^2+(-0.0021)*L206)+M$1*((-0.000002)*M206^3+0.00032*M206^2+(-0.0021)*M206)+N$1*((-0.000002)*N206^3+0.00032*N206^2+(-0.0021)*N206)+O$1*((-0.000002)*O206^3+0.00032*O206^2+(-0.0021)*O206) -> 0.0006728 | W206: =P$1*((-0.000002)*P206^3+0.00032*P206^2+(-0.0021)*P206)+Q$1*((-0.000002)*Q206^3+0.00032*Q206^2+(-0.0021)*Q206)+R$1*((-0.000002)*R206^3+0.00032*R206^2+(-0.0021)*R206)+S$1*((-0.000002)*S206^3+0.00032*S206^2+(-0.0021)*S206)+T$1*((-0.000002)*T206^3+0.00032*T206^2+(-0.0021)*T206) -> 0.35886 | X206: =(I$1*((-0.000002)*I206^3+0.00032*I206^2+(-0.0021)*I206)+J$1*((-0.000002)*J206^3+0.00032*J206^2+(-0.0021)*J206)+H$1*((-0.000002)*H206^3+0.00032*H206^2+(-0.0021)*H206))*(MAX(0.05,MIN(1,(2*J206+I206)/120)*MIN(1,I206/10)*MIN(1,J206/10))) -> 0.1828016 | Y206: =(I$1*((-0.000002)*I206^3+0.00032*I206^2+(-0.0021)*I206)+J$1*((-0.000002)*J206^3+0.00032*J206^2+(-0.0021)*J206)+H$1*((-0.000002)*H206^3+0.00032*H206^2+(-0.0021)*H206))*(MAX(0.05,MIN(1,(2*J206+I206)/120)*MIN(1,I206/10)*MIN(1,J206/10))) -> 0.1828016 | Z206: =IF(AND(J206>50,I206+J206>75),"SP",IF(2*I206+J206>120,"RP","CRAP")) -> SP | AA206: =IF(AND(J206>50,I206+J206>75),"SP",IF(2*I206+J206>120,"RP","CRAP")) -> SP
A207: =(V207*V$2+W207*W$2+X207*X$2)*100/(V$4*V$2+W$4*W$2+X$4*X$2) -> 0 | V207: =K$1*(0.000001*K207^3)+L$1*((-0.000002)*L207^3+0.00032*L207^2+(-0.0021)*L207)+M$1*((-0.000002)*M207^3+0.00032*M207^2+(-0.0021)*M207)+N$1*((-0.000002)*N207^3+0.00032*N207^2+(-0.0021)*N207)+O$1*((-0.000002)*O207^3+0.00032*O207^2+(-0.0021)*O207) -> 0 | W207: =P$1*((-0.000002)*P207^3+0.00032*P207^2+(-0.0021)*P207)+Q$1*((-0.000002)*Q207^3+0.00032*Q207^2+(-0.0021)*Q207)+R$1*((-0.000002)*R207^3+0.00032*R207^2+(-0.0021)*R207)+S$1*((-0.000002)*S207^3+0.00032*S207^2+(-0.0021)*S207)+T$1*((-0.000002)*T207^3+0.00032*T207^2+(-0.0021)*T207) -> 0 | X207: =(I$1*((-0.000002)*I207^3+0.00032*I207^2+(-0.0021)*I207)+J$1*((-0.000002)*J207^3+0.00032*J207^2+(-0.0021)*J207)+H$1*((-0.000002)*H207^3+0.00032*H207^2+(-0.0021)*H207))*(MAX(0.05,MIN(1,(2*J207+I207)/120)*MIN(1,I207/10)*MIN(1,J207/10))) -> 0 | Y207: =(I$1*((-0.000002)*I207^3+0.00032*I207^2+(-0.0021)*I207)+J$1*((-0.000002)*J207^3+0.00032*J207^2+(-0.0021)*J207)+H$1*((-0.000002)*H207^3+0.00032*H207^2+(-0.0021)*H207))*(MAX(0.05,MIN(1,(2*J207+I207)/120)*MIN(1,I207/10)*MIN(1,J207/10))) -> 0 | Z207: =IF(AND(J207>50,I207+J207>75),"SP",IF(2*I207+J207>120,"RP","CRAP")) -> CRAP | AA207: =IF(AND(J207>50,I207+J207>75),"SP",IF(2*I207+J207>120,"RP","CRAP")) -> CRAP
A208: =(V208*V$2+W208*W$2+X208*X$2)*100/(V$4*V$2+W$4*W$2+X$4*X$2) -> 0 | V208: =K$1*(0.000001*K208^3)+L$1*((-0.000002)*L208^3+0.00032*L208^2+(-0.0021)*L208)+M$1*((-0.000002)*M208^3+0.00032*M208^2+(-0.0021)*M208)+N$1*((-0.000002)*N208^3+0.00032*N208^2+(-0.0021)*N208)+O$1*((-0.000002)*O208^3+0.00032*O208^2+(-0.0021)*O208) -> 0 | W208: =P$1*((-0.000002)*P208^3+0.00032*P208^2+(-0.0021)*P208)+Q$1*((-0.000002)*Q208^3+0.00032*Q208^2+(-0.0021)*Q208)+R$1*((-0.000002)*R208^3+0.00032*R208^2+(-0.0021)*R208)+S$1*((-0.000002)*S208^3+0.00032*S208^2+(-0.0021)*S208)+T$1*((-0.000002)*T208^3+0.00032*T208^2+(-0.0021)*T208) -> 0 | X208: =(I$1*((-0.000002)*I208^3+0.00032*I208^2+(-0.0021)*I208)+J$1*((-0.000002)*J208^3+0.00032*J208^2+(-0.0021)*J208)+H$1*((-0.000002)*H208^3+0.00032*H208^2+(-0.0021)*H208))*(MAX(0.05,MIN(1,(2*J208+I208)/120)*MIN(1,I208/10)*MIN(1,J208/10))) -> 0 | Y208: =(I$1*((-0.000002)*I208^3+0.00032*I208^2+(-0.0021)*I208)+J$1*((-0.000002)*J208^3+0.00032*J208^2+(-0.0021)*J208)+H$1*((-0.000002)*H208^3+0.00032*H208^2+(-0.0021)*H208))*(MAX(0.05,MIN(1,(2*J208+I208)/120)*MIN(1,I208/10)*MIN(1,J208/10))) -> 0 | Z208: =IF(AND(J208>50,I208+J208>75),"SP",IF(2*I208+J208>120,"RP","CRAP")) -> CRAP | AA208: =IF(AND(J208>50,I208+J208>75),"SP",IF(2*I208+J208>120,"RP","CRAP")) -> CRAP
A209: =(V209*V$2+W209*W$2+X209*X$2)*100/(V$4*V$2+W$4*W$2+X$4*X$2) -> 0 | V209: =K$1*(0.000001*K209^3)+L$1*((-0.000002)*L209^3+0.00032*L209^2+(-0.0021)*L209)+M$1*((-0.000002)*M209^3+0.00032*M209^2+(-0.0021)*M209)+N$1*((-0.000002)*N209^3+0.00032*N209^2+(-0.0021)*N209)+O$1*((-0.000002)*O209^3+0.00032*O209^2+(-0.0021)*O209) -> 0 | W209: =P$1*((-0.000002)*P209^3+0.00032*P209^2+(-0.0021)*P209)+Q$1*((-0.000002)*Q209^3+0.00032*Q209^2+(-0.0021)*Q209)+R$1*((-0.000002)*R209^3+0.00032*R209^2+(-0.0021)*R209)+S$1*((-0.000002)*S209^3+0.00032*S209^2+(-0.0021)*S209)+T$1*((-0.000002)*T209^3+0.00032*T209^2+(-0.0021)*T209) -> 0 | X209: =(I$1*((-0.000002)*I209^3+0.00032*I209^2+(-0.0021)*I209)+J$1*((-0.000002)*J209^3+0.00032*J209^2+(-0.0021)*J209)+H$1*((-0.000002)*H209^3+0.00032*H209^2+(-0.0021)*H209))*(MAX(0.05,MIN(1,(2*J209+I209)/120)*MIN(1,I209/10)*MIN(1,J209/10))) -> 0 | Y209: =(I$1*((-0.000002)*I209^3+0.00032*I209^2+(-0.0021)*I209)+J$1*((-0.000002)*J209^3+0.00032*J209^2+(-0.0021)*J209)+H$1*((-0.000002)*H209^3+0.00032*H209^2+(-0.0021)*H209))*(MAX(0.05,MIN(1,(2*J209+I209)/120)*MIN(1,I209/10)*MIN(1,J209/10))) -> 0 | Z209: =IF(AND(J209>50,I209+J209>75),"SP",IF(2*I209+J209>120,"RP","CRAP")) -> CRAP | AA209: =IF(AND(J209>50,I209+J209>75),"SP",IF(2*I209+J209>120,"RP","CRAP")) -> CRAP
A210: =(V210*V$2+W210*W$2+X210*X$2)*100/(V$4*V$2+W$4*W$2+X$4*X$2) -> 0 | V210: =K$1*(0.000001*K210^3)+L$1*((-0.000002)*L210^3+0.00032*L210^2+(-0.0021)*L210)+M$1*((-0.000002)*M210^3+0.00032*M210^2+(-0.0021)*M210)+N$1*((-0.000002)*N210^3+0.00032*N210^2+(-0.0021)*N210)+O$1*((-0.000002)*O210^3+0.00032*O210^2+(-0.0021)*O210) -> 0 | W210: =P$1*((-0.000002)*P210^3+0.00032*P210^2+(-0.0021)*P210)+Q$1*((-0.000002)*Q210^3+0.00032*Q210^2+(-0.0021)*Q210)+R$1*((-0.000002)*R210^3+0.00032*R210^2+(-0.0021)*R210)+S$1*((-0.000002)*S210^3+0.00032*S210^2+(-0.0021)*S210)+T$1*((-0.000002)*T210^3+0.00032*T210^2+(-0.0021)*T210) -> 0 | X210: =(I$1*((-0.000002)*I210^3+0.00032*I210^2+(-0.0021)*I210)+J$1*((-0.000002)*J210^3+0.00032*J210^2+(-0.0021)*J210)+H$1*((-0.000002)*H210^3+0.00032*H210^2+(-0.0021)*H210))*(MAX(0.05,MIN(1,(2*J210+I210)/120)*MIN(1,I210/10)*MIN(1,J210/10))) -> 0 | Y210: =(I$1*((-0.000002)*I210^3+0.00032*I210^2+(-0.0021)*I210)+J$1*((-0.000002)*J210^3+0.00032*J210^2+(-0.0021)*J210)+H$1*((-0.000002)*H210^3+0.00032*H210^2+(-0.0021)*H210))*(MAX(0.05,MIN(1,(2*J210+I210)/120)*MIN(1,I210/10)*MIN(1,J210/10))) -> 0 | Z210: =IF(AND(J210>50,I210+J210>75),"SP",IF(2*I210+J210>120,"RP","CRAP")) -> CRAP | AA210: =IF(AND(J210>50,I210+J210>75),"SP",IF(2*I210+J210>120,"RP","CRAP")) -> CRAP
A211: =(V211*V$2+W211*W$2+X211*X$2)*100/(V$4*V$2+W$4*W$2+X$4*X$2) -> 0 | V211: =K$1*(0.000001*K211^3)+L$1*((-0.000002)*L211^3+0.00032*L211^2+(-0.0021)*L211)+M$1*((-0.000002)*M211^3+0.00032*M211^2+(-0.0021)*M211)+N$1*((-0.000002)*N211^3+0.00032*N211^2+(-0.0021)*N211)+O$1*((-0.000002)*O211^3+0.00032*O211^2+(-0.0021)*O211) -> 0 | W211: =P$1*((-0.000002)*P211^3+0.00032*P211^2+(-0.0021)*P211)+Q$1*((-0.000002)*Q211^3+0.00032*Q211^2+(-0.0021)*Q211)+R$1*((-0.000002)*R211^3+0.00032*R211^2+(-0.0021)*R211)+S$1*((-0.000002)*S211^3+0.00032*S211^2+(-0.0021)*S211)+T$1*((-0.000002)*T211^3+0.00032*T211^2+(-0.0021)*T211) -> 0 | X211: =(I$1*((-0.000002)*I211^3+0.00032*I211^2+(-0.0021)*I211)+J$1*((-0.000002)*J211^3+0.00032*J211^2+(-0.0021)*J211)+H$1*((-0.000002)*H211^3+0.00032*H211^2+(-0.0021)*H211))*(MAX(0.05,MIN(1,(2*J211+I211)/120)*MIN(1,I211/10)*MIN(1,J211/10))) -> 0 | Y211: =(I$1*((-0.000002)*I211^3+0.00032*I211^2+(-0.0021)*I211)+J$1*((-0.000002)*J211^3+0.00032*J211^2+(-0.0021)*J211)+H$1*((-0.000002)*H211^3+0.00032*H211^2+(-0.0021)*H211))*(MAX(0.05,MIN(1,(2*J211+I211)/120)*MIN(1,I211/10)*MIN(1,J211/10))) -> 0 | Z211: =IF(AND(J211>50,I211+J211>75),"SP",IF(2*I211+J211>120,"RP","CRAP")) -> CRAP | AA211: =IF(AND(J211>50,I211+J211>75),"SP",IF(2*I211+J211>120,"RP","CRAP")) -> CRAP
A212: =(V212*V$2+W212*W$2+X212*X$2)*100/(V$4*V$2+W$4*W$2+X$4*X$2) -> 0 | V212: =K$1*(0.000001*K212^3)+L$1*((-0.000002)*L212^3+0.00032*L212^2+(-0.0021)*L212)+M$1*((-0.000002)*M212^3+0.00032*M212^2+(-0.0021)*M212)+N$1*((-0.000002)*N212^3+0.00032*N212^2+(-0.0021)*N212)+O$1*((-0.000002)*O212^3+0.00032*O212^2+(-0.0021)*O212) -> 0 | W212: =P$1*((-0.000002)*P212^3+0.00032*P212^2+(-0.0021)*P212)+Q$1*((-0.000002)*Q212^3+0.00032*Q212^2+(-0.0021)*Q212)+R$1*((-0.000002)*R212^3+0.00032*R212^2+(-0.0021)*R212)+S$1*((-0.000002)*S212^3+0.00032*S212^2+(-0.0021)*S212)+T$1*((-0.000002)*T212^3+0.00032*T212^2+(-0.0021)*T212) -> 0 | X212: =(I$1*((-0.000002)*I212^3+0.00032*I212^2+(-0.0021)*I212)+J$1*((-0.000002)*J212^3+0.00032*J212^2+(-0.0021)*J212)+H$1*((-0.000002)*H212^3+0.00032*H212^2+(-0.0021)*H212))*(MAX(0.05,MIN(1,(2*J212+I212)/120)*MIN(1,I212/10)*MIN(1,J212/10))) -> 0 | Y212: =(I$1*((-0.000002)*I212^3+0.00032*I212^2+(-0.0021)*I212)+J$1*((-0.000002)*J212^3+0.00032*J212^2+(-0.0021)*J212)+H$1*((-0.000002)*H212^3+0.00032*H212^2+(-0.0021)*H212))*(MAX(0.05,MIN(1,(2*J212+I212)/120)*MIN(1,I212/10)*MIN(1,J212/10))) -> 0 | Z212: =IF(AND(J212>50,I212+J212>75),"SP",IF(2*I212+J212>120,"RP","CRAP")) -> CRAP | AA212: =IF(AND(J212>50,I212+J212>75),"SP",IF(2*I212+J212>120,"RP","CRAP")) -> CRAP
A213: =(V213*V$2+W213*W$2+X213*X$2)*100/(V$4*V$2+W$4*W$2+X$4*X$2) -> 0 | V213: =K$1*(0.000001*K213^3)+L$1*((-0.000002)*L213^3+0.00032*L213^2+(-0.0021)*L213)+M$1*((-0.000002)*M213^3+0.00032*M213^2+(-0.0021)*M213)+N$1*((-0.000002)*N213^3+0.00032*N213^2+(-0.0021)*N213)+O$1*((-0.000002)*O213^3+0.00032*O213^2+(-0.0021)*O213) -> 0 | W213: =P$1*((-0.000002)*P213^3+0.00032*P213^2+(-0.0021)*P213)+Q$1*((-0.000002)*Q213^3+0.00032*Q213^2+(-0.0021)*Q213)+R$1*((-0.000002)*R213^3+0.00032*R213^2+(-0.0021)*R213)+S$1*((-0.000002)*S213^3+0.00032*S213^2+(-0.0021)*S213)+T$1*((-0.000002)*T213^3+0.00032*T213^2+(-0.0021)*T213) -> 0 | X213: =(I$1*((-0.000002)*I213^3+0.00032*I213^2+(-0.0021)*I213)+J$1*((-0.000002)*J213^3+0.00032*J213^2+(-0.0021)*J213)+H$1*((-0.000002)*H213^3+0.00032*H213^2+(-0.0021)*H213))*(MAX(0.05,MIN(1,(2*J213+I213)/120)*MIN(1,I213/10)*MIN(1,J213/10))) -> 0 | Y213: =(I$1*((-0.000002)*I213^3+0.00032*I213^2+(-0.0021)*I213)+J$1*((-0.000002)*J213^3+0.00032*J213^2+(-0.0021)*J213)+H$1*((-0.000002)*H213^3+0.00032*H213^2+(-0.0021)*H213))*(MAX(0.05,MIN(1,(2*J213+I213)/120)*MIN(1,I213/10)*MIN(1,J213/10))) -> 0 | Z213: =IF(AND(J213>50,I213+J213>75),"SP",IF(2*I213+J213>120,"RP","CRAP")) -> CRAP | AA213: =IF(AND(J213>50,I213+J213>75),"SP",IF(2*I213+J213>120,"RP","CRAP")) -> CRAP
A214: =(V214*V$2+W214*W$2+X214*X$2)*100/(V$4*V$2+W$4*W$2+X$4*X$2) -> 0 | V214: =K$1*(0.000001*K214^3)+L$1*((-0.000002)*L214^3+0.00032*L214^2+(-0.0021)*L214)+M$1*((-0.000002)*M214^3+0.00032*M214^2+(-0.0021)*M214)+N$1*((-0.000002)*N214^3+0.00032*N214^2+(-0.0021)*N214)+O$1*((-0.000002)*O214^3+0.00032*O214^2+(-0.0021)*O214) -> 0 | W214: =P$1*((-0.000002)*P214^3+0.00032*P214^2+(-0.0021)*P214)+Q$1*((-0.000002)*Q214^3+0.00032*Q214^2+(-0.0021)*Q214)+R$1*((-0.000002)*R214^3+0.00032*R214^2+(-0.0021)*R214)+S$1*((-0.000002)*S214^3+0.00032*S214^2+(-0.0021)*S214)+T$1*((-0.000002)*T214^3+0.00032*T214^2+(-0.0021)*T214) -> 0 | X214: =(I$1*((-0.000002)*I214^3+0.00032*I214^2+(-0.0021)*I214)+J$1*((-0.000002)*J214^3+0.00032*J214^2+(-0.0021)*J214)+H$1*((-0.000002)*H214^3+0.00032*H214^2+(-0.0021)*H214))*(MAX(0.05,MIN(1,(2*J214+I214)/120)*MIN(1,I214/10)*MIN(1,J214/10))) -> 0 | Y214: =(I$1*((-0.000002)*I214^3+0.00032*I214^2+(-0.0021)*I214)+J$1*((-0.000002)*J214^3+0.00032*J214^2+(-0.0021)*J214)+H$1*((-0.000002)*H214^3+0.00032*H214^2+(-0.0021)*H214))*(MAX(0.05,MIN(1,(2*J214+I214)/120)*MIN(1,I214/10)*MIN(1,J214/10))) -> 0 | Z214: =IF(AND(J214>50,I214+J214>75),"SP",IF(2*I214+J214>120,"RP","CRAP")) -> CRAP | AA214: =IF(AND(J214>50,I214+J214>75),"SP",IF(2*I214+J214>120,"RP","CRAP")) -> CRAP
A215: =(V215*V$2+W215*W$2+X215*X$2)*100/(V$4*V$2+W$4*W$2+X$4*X$2) -> 0 | V215: =K$1*(0.000001*K215^3)+L$1*((-0.000002)*L215^3+0.00032*L215^2+(-0.0021)*L215)+M$1*((-0.000002)*M215^3+0.00032*M215^2+(-0.0021)*M215)+N$1*((-0.000002)*N215^3+0.00032*N215^2+(-0.0021)*N215)+O$1*((-0.000002)*O215^3+0.00032*O215^2+(-0.0021)*O215) -> 0 | W215: =P$1*((-0.000002)*P215^3+0.00032*P215^2+(-0.0021)*P215)+Q$1*((-0.000002)*Q215^3+0.00032*Q215^2+(-0.0021)*Q215)+R$1*((-0.000002)*R215^3+0.00032*R215^2+(-0.0021)*R215)+S$1*((-0.000002)*S215^3+0.00032*S215^2+(-0.0021)*S215)+T$1*((-0.000002)*T215^3+0.00032*T215^2+(-0.0021)*T215) -> 0 | X215: =(I$1*((-0.000002)*I215^3+0.00032*I215^2+(-0.0021)*I215)+J$1*((-0.000002)*J215^3+0.00032*J215^2+(-0.0021)*J215)+H$1*((-0.000002)*H215^3+0.00032*H215^2+(-0.0021)*H215))*(MAX(0.05,MIN(1,(2*J215+I215)/120)*MIN(1,I215/10)*MIN(1,J215/10))) -> 0 | Y215: =(I$1*((-0.000002)*I215^3+0.00032*I215^2+(-0.0021)*I215)+J$1*((-0.000002)*J215^3+0.00032*J215^2+(-0.0021)*J215)+H$1*((-0.000002)*H215^3+0.00032*H215^2+(-0.0021)*H215))*(MAX(0.05,MIN(1,(2*J215+I215)/120)*MIN(1,I215/10)*MIN(1,J215/10))) -> 0 | Z215: =IF(AND(J215>50,I215+J215>75),"SP",IF(2*I215+J215>120,"RP","CRAP")) -> CRAP | AA215: =IF(AND(J215>50,I215+J215>75),"SP",IF(2*I215+J215>120,"RP","CRAP")) -> CRAP
A216: =(V216*V$2+W216*W$2+X216*X$2)*100/(V$4*V$2+W$4*W$2+X$4*X$2) -> 0 | V216: =K$1*(0.000001*K216^3)+L$1*((-0.000002)*L216^3+0.00032*L216^2+(-0.0021)*L216)+M$1*((-0.000002)*M216^3+0.00032*M216^2+(-0.0021)*M216)+N$1*((-0.000002)*N216^3+0.00032*N216^2+(-0.0021)*N216)+O$1*((-0.000002)*O216^3+0.00032*O216^2+(-0.0021)*O216) -> 0 | W216: =P$1*((-0.000002)*P216^3+0.00032*P216^2+(-0.0021)*P216)+Q$1*((-0.000002)*Q216^3+0.00032*Q216^2+(-0.0021)*Q216)+R$1*((-0.000002)*R216^3+0.00032*R216^2+(-0.0021)*R216)+S$1*((-0.000002)*S216^3+0.00032*S216^2+(-0.0021)*S216)+T$1*((-0.000002)*T216^3+0.00032*T216^2+(-0.0021)*T216) -> 0 | X216: =(I$1*((-0.000002)*I216^3+0.00032*I216^2+(-0.0021)*I216)+J$1*((-0.000002)*J216^3+0.00032*J216^2+(-0.0021)*J216)+H$1*((-0.000002)*H216^3+0.00032*H216^2+(-0.0021)*H216))*(MAX(0.05,MIN(1,(2*J216+I216)/120)*MIN(1,I216/10)*MIN(1,J216/10))) -> 0 | Y216: =(I$1*((-0.000002)*I216^3+0.00032*I216^2+(-0.0021)*I216)+J$1*((-0.000002)*J216^3+0.00032*J216^2+(-0.0021)*J216)+H$1*((-0.000002)*H216^3+0.00032*H216^2+(-0.0021)*H216))*(MAX(0.05,MIN(1,(2*J216+I216)/120)*MIN(1,I216/10)*MIN(1,J216/10))) -> 0 | Z216: =IF(AND(J216>50,I216+J216>75),"SP",IF(2*I216+J216>120,"RP","CRAP")) -> CRAP | AA216: =IF(AND(J216>50,I216+J216>75),"SP",IF(2*I216+J216>120,"RP","CRAP")) -> CRAP
A217: =(V217*V$2+W217*W$2+X217*X$2)*100/(V$4*V$2+W$4*W$2+X$4*X$2) -> 0 | V217: =K$1*(0.000001*K217^3)+L$1*((-0.000002)*L217^3+0.00032*L217^2+(-0.0021)*L217)+M$1*((-0.000002)*M217^3+0.00032*M217^2+(-0.0021)*M217)+N$1*((-0.000002)*N217^3+0.00032*N217^2+(-0.0021)*N217)+O$1*((-0.000002)*O217^3+0.00032*O217^2+(-0.0021)*O217) -> 0 | W217: =P$1*((-0.000002)*P217^3+0.00032*P217^2+(-0.0021)*P217)+Q$1*((-0.000002)*Q217^3+0.00032*Q217^2+(-0.0021)*Q217)+R$1*((-0.000002)*R217^3+0.00032*R217^2+(-0.0021)*R217)+S$1*((-0.000002)*S217^3+0.00032*S217^2+(-0.0021)*S217)+T$1*((-0.000002)*T217^3+0.00032*T217^2+(-0.0021)*T217) -> 0 | X217: =(I$1*((-0.000002)*I217^3+0.00032*I217^2+(-0.0021)*I217)+J$1*((-0.000002)*J217^3+0.00032*J217^2+(-0.0021)*J217)+H$1*((-0.000002)*H217^3+0.00032*H217^2+(-0.0021)*H217))*(MAX(0.05,MIN(1,(2*J217+I217)/120)*MIN(1,I217/10)*MIN(1,J217/10))) -> 0 | Y217: =(I$1*((-0.000002)*I217^3+0.00032*I217^2+(-0.0021)*I217)+J$1*((-0.000002)*J217^3+0.00032*J217^2+(-0.0021)*J217)+H$1*((-0.000002)*H217^3+0.00032*H217^2+(-0.0021)*H217))*(MAX(0.05,MIN(1,(2*J217+I217)/120)*MIN(1,I217/10)*MIN(1,J217/10))) -> 0 | Z217: =IF(AND(J217>50,I217+J217>75),"SP",IF(2*I217+J217>120,"RP","CRAP")) -> CRAP | AA217: =IF(AND(J217>50,I217+J217>75),"SP",IF(2*I217+J217>120,"RP","CRAP")) -> CRAP
A218: =(V218*V$2+W218*W$2+X218*X$2)*100/(V$4*V$2+W$4*W$2+X$4*X$2) -> 0 | V218: =K$1*(0.000001*K218^3)+L$1*((-0.000002)*L218^3+0.00032*L218^2+(-0.0021)*L218)+M$1*((-0.000002)*M218^3+0.00032*M218^2+(-0.0021)*M218)+N$1*((-0.000002)*N218^3+0.00032*N218^2+(-0.0021)*N218)+O$1*((-0.000002)*O218^3+0.00032*O218^2+(-0.0021)*O218) -> 0 | W218: =P$1*((-0.000002)*P218^3+0.00032*P218^2+(-0.0021)*P218)+Q$1*((-0.000002)*Q218^3+0.00032*Q218^2+(-0.0021)*Q218)+R$1*((-0.000002)*R218^3+0.00032*R218^2+(-0.0021)*R218)+S$1*((-0.000002)*S218^3+0.00032*S218^2+(-0.0021)*S218)+T$1*((-0.000002)*T218^3+0.00032*T218^2+(-0.0021)*T218) -> 0 | X218: =(I$1*((-0.000002)*I218^3+0.00032*I218^2+(-0.0021)*I218)+J$1*((-0.000002)*J218^3+0.00032*J218^2+(-0.0021)*J218)+H$1*((-0.000002)*H218^3+0.00032*H218^2+(-0.0021)*H218))*(MAX(0.05,MIN(1,(2*J218+I218)/120)*MIN(1,I218/10)*MIN(1,J218/10))) -> 0 | Y218: =(I$1*((-0.000002)*I218^3+0.00032*I218^2+(-0.0021)*I218)+J$1*((-0.000002)*J218^3+0.00032*J218^2+(-0.0021)*J218)+H$1*((-0.000002)*H218^3+0.00032*H218^2+(-0.0021)*H218))*(MAX(0.05,MIN(1,(2*J218+I218)/120)*MIN(1,I218/10)*MIN(1,J218/10))) -> 0 | Z218: =IF(AND(J218>50,I218+J218>75),"SP",IF(2*I218+J218>120,"RP","CRAP")) -> CRAP | AA218: =IF(AND(J218>50,I218+J218>75),"SP",IF(2*I218+J218>120,"RP","CRAP")) -> CRAP
... A505: =(V505*V$2+W505*W$2+X505*X$2)*100/(V$4*V$2+W$4*W$2+X$4*X$2) -> 0 | V505: =K$1*(0.000001*K505^3)+L$1*((-0.000002)*L505^3+0.00032*L505^2+(-0.0021)*L505)+M$1*((-0.000002)*M505^3+0.00032*M505^2+(-0.0021)*M505)+N$1*((-0.000002)*N505^3+0.00032*N505^2+(-0.0021)*N505)+O$1*((-0.000002)*O505^3+0.00032*O505^2+(-0.0021)*O505) -> 0 | W505: =P$1*((-0.000002)*P505^3+0.00032*P505^2+(-0.0021)*P505)+Q$1*((-0.000002)*Q505^3+0.00032*Q505^2+(-0.0021)*Q505)+R$1*((-0.000002)*R505^3+0.00032*R505^2+(-0.0021)*R505)+S$1*((-0.000002)*S505^3+0.00032*S505^2+(-0.0021)*S505)+T$1*((-0.000002)*T505^3+0.00032*T505^2+(-0.0021)*T505) -> 0 | X505: =(I$1*((-0.000002)*I505^3+0.00032*I505^2+(-0.0021)*I505)+J$1*((-0.000002)*J505^3+0.00032*J505^2+(-0.0021)*J505)+H$1*((-0.000002)*H505^3+0.00032*H505^2+(-0.0021)*H505))*(MAX(0.05,MIN(1,(2*J505+I505)/120)*MIN(1,I505/10)*MIN(1,J505/10))) -> 0 | Y505: =(I$1*((-0.000002)*I505^3+0.00032*I505^2+(-0.0021)*I505)+J$1*((-0.000002)*J505^3+0.00032*J505^2+(-0.0021)*J505)+H$1*((-0.000002)*H505^3+0.00032*H505^2+(-0.0021)*H505))*(MAX(0.05,MIN(1,(2*J505+I505)/120)*MIN(1,I505/10)*MIN(1,J505/10))) -> 0 | Z505: =IF(AND(J505>50,I505+J505>75),"SP",IF(2*I505+J505>120,"RP","CRAP")) -> CRAP | AA505: =IF(AND(J505>50,I505+J505>75),"SP",IF(2*I505+J505>120,"RP","CRAP")) -> CRAP

Sheet Algorithm Analysis
A1: 0 | B1: 0 | C1: =1/LOG10(111-A1) -> 0.48892034 | D1: =MAX(0, (((LOG(A1+0.000001, 100)*2.6-0.92)))) -> 0 | E1: =(-2*10^-6)*A1^3+0.00032*A1^2-0.0021*A1 -> 0 | G1: =-2*10^-6*A1^3 -> 0 | H1: =0.00032*A1^2 -> 0 | I1: =-0.0021*A1 -> 0 | J1: 0 | K1: =SUM(G1:J1) -> 0
A2: 10 | B2: 0.05 | C2: =1/LOG10(111-A2) -> 0.49892199 | D2: =MAX(0, (((LOG(A2+0.000001, 100)*2.6-0.92)))) -> 0.38000006 | E2: =(-2*10^-6)*A2^3+0.00032*A2^2-0.0021*A2 -> 0.009 | G2: =-2*10^-6*A2^3 -> -0.002 | H2: =0.00032*A2^2 -> 0.032 | I2: =-0.0021*A2 -> -0.021 | J2: 0 | K2: =SUM(G2:J2) -> 0.009
A3: 20 | B3: 0.1 | C3: =1/LOG10(111-A3) -> 0.51045374 | D3: =MAX(0, (((LOG(A3+0.000001, 100)*2.6-0.92)))) -> 0.77133902 | E3: =(-2*10^-6)*A3^3+0.00032*A3^2-0.0021*A3 -> 0.07 | G3: =-2*10^-6*A3^3 -> -0.016 | H3: =0.00032*A3^2 -> 0.128 | I3: =-0.0021*A3 -> -0.042 | J3: 0 | K3: =SUM(G3:J3) -> 0.07
A4: 22 | B4: 0.11 | C4: =1/LOG10(111-A4) -> 0.51298098 | D4: =MAX(0, (((LOG(A4+0.000001, 100)*2.6-0.92)))) -> 0.82514951 | E4: =(-2*10^-6)*A4^3+0.00032*A4^2-0.0021*A4 -> 0.087384 | G4: =-2*10^-6*A4^3 -> -0.021296 | H4: =0.00032*A4^2 -> 0.15488 | I4: =-0.0021*A4 -> -0.0462 | J4: 0 | K4: =SUM(G4:J4) -> 0.087384
A5: 24 | B5: 0.12 | C5: =1/LOG10(111-A5) -> 0.51559169 | D5: =MAX(0, (((LOG(A5+0.000001, 100)*2.6-0.92)))) -> 0.87427464 | E5: =(-2*10^-6)*A5^3+0.00032*A5^2-0.0021*A5 -> 0.106272 | G5: =-2*10^-6*A5^3 -> -0.027648 | H5: =0.00032*A5^2 -> 0.18432 | I5: =-0.0021*A5 -> -0.0504 | J5: 0 | K5: =SUM(G5:J5) -> 0.106272
A6: 26 | B6: 0.13 | C6: =1/LOG10(111-A6) -> 0.51829076 | D6: =MAX(0, (((LOG(A6+0.000001, 100)*2.6-0.92)))) -> 0.91946537 | E6: =(-2*10^-6)*A6^3+0.00032*A6^2-0.0021*A6 -> 0.126568 | G6: =-2*10^-6*A6^3 -> -0.035152 | H6: =0.00032*A6^2 -> 0.21632 | I6: =-0.0021*A6 -> -0.0546 | J6: 0 | K6: =SUM(G6:J6) -> 0.126568
A7: 30 | B7: 0.15 | C7: =1/LOG10(111-A7) -> 0.52397582 | D7: =MAX(0, (((LOG(A7+0.000001, 100)*2.6-0.92)))) -> 1.0002576 | E7: =(-2*10^-6)*A7^3+0.00032*A7^2-0.0021*A7 -> 0.171 | G7: =-2*10^-6*A7^3 -> -0.054 | H7: =0.00032*A7^2 -> 0.288 | I7: =-0.0021*A7 -> -0.063 | J7: 0 | K7: =SUM(G7:J7) -> 0.171
A8: 40 | B8: 0.3 | C8: =1/LOG10(111-A8) -> 0.54017312 | D8: =MAX(0, (((LOG(A8+0.000001, 100)*2.6-0.92)))) -> 1.162678 | E8: =(-2*10^-6)*A8^3+0.00032*A8^2-0.0021*A8 -> 0.3 | G8: =-2*10^-6*A8^3 -> -0.128 | H8: =0.00032*A8^2 -> 0.512 | I8: =-0.0021*A8 -> -0.084 | J8: 0 | K8: =SUM(G8:J8) -> 0.3
A9: 50 | B9: 0.45 | C9: =1/LOG10(111-A9) -> 0.56012059 | D9: =MAX(0, (((LOG(A9+0.000001, 100)*2.6-0.92)))) -> 1.288661 | E9: =(-2*10^-6)*A9^3+0.00032*A9^2-0.0021*A9 -> 0.445 | G9: =-2*10^-6*A9^3 -> -0.25 | H9: =0.00032*A9^2 -> 0.8 | I9: =-0.0021*A9 -> -0.105 | J9: 0 | K9: =SUM(G9:J9) -> 0.445
A10: 60 | B10: 0.6 | C10: =1/LOG10(111-A10) -> 0.58562747 | D10: =MAX(0, (((LOG(A10+0.000001, 100)*2.6-0.92)))) -> 1.3915966 | E10: =(-2*10^-6)*A10^3+0.00032*A10^2-0.0021*A10 -> 0.594 | G10: =-2*10^-6*A10^3 -> -0.432 | H10: =0.00032*A10^2 -> 1.152 | I10: =-0.0021*A10 -> -0.126 | J10: 0 | K10: =SUM(G10:J10) -> 0.594
A11: 70 | B11: 0.75 | C11: =1/LOG10(111-A11) -> 0.62004589 | D11: =MAX(0, (((LOG(A11+0.000001, 100)*2.6-0.92)))) -> 1.4786275 | E11: =(-2*10^-6)*A11^3+0.00032*A11^2-0.0021*A11 -> 0.735 | G11: =-2*10^-6*A11^3 -> -0.686 | H11: =0.00032*A11^2 -> 1.568 | I11: =-0.0021*A11 -> -0.147 | J11: 0 | K11: =SUM(G11:J11) -> 0.735
A12: 80 | B12: 0.85 | C12: =1/LOG10(111-A12) -> 0.67052815 | D12: =MAX(0, (((LOG(A12+0.000001, 100)*2.6-0.92)))) -> 1.554017 | E12: =(-2*10^-6)*A12^3+0.00032*A12^2-0.0021*A12 -> 0.856 | G12: =-2*10^-6*A12^3 -> -1.024 | H12: =0.00032*A12^2 -> 2.048 | I12: =-0.0021*A12 -> -0.168 | J12: 0 | K12: =SUM(G12:J12) -> 0.856
... A14: 100 | B14: 1 | C14: =1/LOG10(111-A14) -> 0.96025257 | D14: =MAX(0, (((LOG(A14+0.000001, 100)*2.6-0.92)))) -> 1.68 | E14: =(-2*10^-6)*A14^3+0.00032*A14^2-0.0021*A14 -> 0.99 | G14: =-2*10^-6*A14^3 -> -2 | H14: =0.00032*A14^2 -> 3.2 | I14: =-0.0021*A14 -> -0.21 | J14: 0 | K14: =SUM(G14:J14) -> 0.99

Sheet Algorithm
M1: a3 | N1: a2 | O1: a1 | P1: a0
M2: -2e-06 | N2: 0.00032 | O2: -0.0021 | P2: 0

Sheet Background Info
A1: Rnk | B1: Player | C1: Pos | D1: B | E1: T | F1: Age | G1: Hometown | H1: School | I1: Class | J1: Signability
A2: 1 | B2: Lozada, Marshall | C2: 3B | D2: R | E2: R | F2: 18 | G2: Caddo Mills,TX | H2: Anna HS | I2: -- | J2: Looking to sign. Will sign for slot money.
A3: 2 | B3: Romero, Jerome | C3: SS | D3: R | E3: R | F3: 18 | G3: Attleboro,MA | H3: Dedham HS | I3: -- | J3: May sign if the deal is right. Has been offered several scholarships to play college baseball at a DI school.
A4: 3 | B4: Cunnane, John | C4: RF | D4: R | E4: R | F4: 18 | G4: Pampa,TX | H4: Panhandle HS | I4: -- | J4: Looking to be drafted in the first five rounds. If not, he'll probably accept a scholarship to play DI college baseball.
A5: 4 | B5: Stevenson, Madison | C5: P | D5: S | E5: R | F5: 18 | G5: Fairview,OK | H5: Timberlake HS | I5: -- | J5: Looking to sign. Will sign for slot money.
A6: 5 | B6: Bailey, Alexander | C6: 1B | D6: R | E6: R | F6: 18 | G6: St. Anthony,MN | H6: Washburn HS | I6: -- | J6: Looking to sign. Will sign for slot money.
A7: 6 | B7: Madson, Bo | C7: P | D7: R | E7: R | F7: 18 | G7: Old Lyme,CT | H7: Norwich HS | I7: -- | J7: Looking to be drafted in the first round. If not, he'll probably accept a scholarship to play DI college baseball.
A8: 7 | B8: Patrick, Alex | C8: 3B | D8: R | E8: R | F8: 18 | G8: Ebensburg,PA | H8: Bishop Guilfoyle HS | I8: -- | J8: May sign if the deal is right. Has been offered several scholarships to play college baseball at a DI school.
A9: 8 | B9: Burch, Stu | C9: P | D9: L | E9: L | F9: 18 | G9: Watseka,IL | H9: Reed-Custer HS | I9: -- | J9: Looking to sign. Will sign for slot money.
A10: 9 | B10: Gleason, Curtis | C10: P | D10: L | E10: L | F10: 18 | G10: Simla,CO | H10: Peyton HS | I10: -- | J10: May sign if the deal is right. Has been offered several scholarships to play college baseball at a DI school.
A11: 10 | B11: King, Sherman | C11: P | D11: R | E11: R | F11: 18 | G11: State Center,IA | H11: Southeast Polk HS | I11: -- | J11: Looking to sign. Will sign for slot money.
A12: 11 | B12: Sanchez, Angel | C12: LF | D12: S | E12: L | F12: 18 | G12: Felton,CA | H12: Salinas HS | I12: -- | J12: Looking to sign. Will sign for slot money.
A13: 12 | B13: Arguelles, Arquimedes | C13: 2B | D13: R | E13: R | F13: 18 | G13: Atlanta,GA | H13: Woodstock HS | I13: -- | J13: Looking to sign. Will sign for slot money.
... A310: 309 | B310: Accardo, Einar | C310: RF | D310: R | E310: R | F310: 18 | G310: Rockaway Park,NY | H310: Commack HS | I310: -- | J310: Unknown. He wasn't scouted well enough.
A311: 310 | B311: Ryal, Dennys | C311: ? | D311: ? | E311: ? | F311: ? | G311: Unknown | H311: Unknown | I311: ? | J311: Unknown. He wasn't scouted well enough.
A312: 311 | B312: Lange, Ronald | C312: ? | D312: ? | E312: ? | F312: ? | G312: Unknown | H312: Unknown | I312: ? | J312: Unknown. He wasn't scouted well enough.
A313: 312 | B313: Sullivan, John | C313: ? | D313: ? | E313: ? | F313: ? | G313: Unknown | H313: Unknown | I313: ? | J313: Unknown. He wasn't scouted well enough.
A314: 313 | B314: Wengert, Japhet | C314: ? | D314: ? | E314: ? | F314: ? | G314: Unknown | H314: Unknown | I314: ? | J314: Unknown. He wasn't scouted well enough.
A315: 314 | B315: Cash, Shaggy | C315: ? | D315: ? | E315: ? | F315: ? | G315: Unknown | H315: Unknown | I315: ? | J315: Unknown. He wasn't scouted well enough.
A316: 315 | B316: Cannon, Philip | C316: ? | D316: ? | E316: ? | F316: ? | G316: Unknown | H316: Unknown | I316: ? | J316: Unknown. He wasn't scouted well enough.
A317: 316 | B317: Fisher, Brad | C317: ? | D317: ? | E317: ? | F317: ? | G317: Unknown | H317: Unknown | I317: ? | J317: Unknown. He wasn't scouted well enough.
A318: 317 | B318: Owen, Norberto | C318: ? | D318: ? | E318: ? | F318: ? | G318: Unknown | H318: Unknown | I318: ? | J318: Unknown. He wasn't scouted well enough.
A319: 318 | B319: Fonville, Scot | C319: ? | D319: ? | E319: ? | F319: ? | G319: Unknown | H319: Unknown | I319: ? | J319: Unknown. He wasn't scouted well enough.
A320: 319 | B320: Springer, Brad | C320: ? | D320: ? | E320: ? | F320: ? | G320: Unknown | H320: Unknown | I320: ? | J320: Unknown. He wasn't scouted well enough.
A321: 320 | B321: Lieber, Damian | C321: ? | D321: ? | E321: ? | F321: ? | G321: Unknown | H321: Unknown | I321: ? | J321: Unknown. He wasn't scouted well enough.
A322: 321 | B322: Brown, Todd | C322: ? | D322: ? | E322: ? | F322: ? | G322: Unknown | H322: Unknown | I322: ? | J322: Unknown. He wasn't scouted well enough.
... A501: 500 | B501: James, Yunel | C501: ? | D501: ? | E501: ? | F501: ? | G501: Unknown | H501: Unknown | I501: ? | J501: Unknown. He wasn't scouted well enough.

Sheet Master List
A1: Adjusted Score | B1: Overall Projection | C1: Raw Overall | D1: Scouting Trust | E1: Signability Factor | F1: Player | G1: Pos | H1: Type | I1: Category | J1: Signability
A2: =B2*D2*E2 -> 75.250027 | B2: =Hitters!A7 -> 75.250027 | C2: 88 | D2: 1 | E2: 1 | F2: Lozada, Marshall | G2: 3B | H2: Hitter | I2: high_school | J2: Looking to sign. Will sign for slot money.
A3: =B3*D3*E3 -> 75.18403 | B3: =Hitters!A8 -> 83.537811 | C3: 89 | D3: 1 | E3: 0.9 | F3: Romero, Jerome | G3: SS | H3: Hitter | I3: high_school | J3: May sign if the deal is right. Has been offered several scholarships to play college baseball at a DI school.
A4: =B4*D4*E4 -> 70.476504 | B4: =Pitchers!A6 -> 70.476504 | C4: 77 | D4: 1 | E4: 1 | F4: Stevenson, Madison | G4: P | H4: Pitcher | I4: high_school | J4: Looking to sign. Will sign for slot money.
A5: =B5*D5*E5 -> 69.832543 | B5: =Hitters!A9 -> 69.832543 | C5: 81 | D5: 1 | E5: 1 | F5: Cunnane, John | G5: RF | H5: Hitter | I5: high_school | J5: Looking to be drafted in the first five rounds. If not, he'll probably accept a scholarship to play DI college baseball.
A6: =B6*D6*E6 -> 69.566418 | B6: =Pitchers!A7 -> 69.566418 | C6: 71 | D6: 1 | E6: 1 | F6: Madson, Bo | G6: P | H6: Pitcher | I6: high_school | J6: Looking to be drafted in the first round. If not, he'll probably accept a scholarship to play DI college baseball.
A7: =B7*D7*E7 -> 68.441105 | B7: =Pitchers!A8 -> 68.441105 | C7: 69 | D7: 1 | E7: 1 | F7: Burch, Stu | G7: P | H7: Pitcher | I7: high_school | J7: Looking to sign. Will sign for slot money.
A8: =B8*D8*E8 -> 67.417684 | B8: =Hitters!A10 -> 67.417684 | C8: 74 | D8: 1 | E8: 1 | F8: Bailey, Alexander | G8: 1B | H8: Hitter | I8: high_school | J8: Looking to sign. Will sign for slot money.
A9: =B9*D9*E9 -> 67.386698 | B9: =Pitchers!A9 -> 74.874109 | C9: 70 | D9: 1 | E9: 0.9 | F9: Gleason, Curtis | G9: P | H9: Pitcher | I9: high_school | J9: May sign if the deal is right. Has been offered several scholarships to play college baseball at a DI school.
A10: =B10*D10*E10 -> 67.057084 | B10: =Pitchers!A10 -> 67.057084 | C10: 71 | D10: 1 | E10: 1 | F10: King, Sherman | G10: P | H10: Pitcher | I10: high_school | J10: Looking to sign. Will sign for slot money.
A11: =B11*D11*E11 -> 66.87692 | B11: =Hitters!A11 -> 74.307689 | C11: 80 | D11: 1 | E11: 0.9 | F11: Patrick, Alex | G11: 3B | H11: Hitter | I11: high_school | J11: May sign if the deal is right. Has been offered several scholarships to play college baseball at a DI school.
A12: =B12*D12*E12 -> 64.462091 | B12: =Pitchers!A11 -> 64.462091 | C12: 69 | D12: 1 | E12: 1 | F12: Cook, Ken | G12: P | H12: Pitcher | I12: high_school | J12: Looking to sign. Will sign for slot money.
A13: =B13*D13*E13 -> 63.931151 | B13: =Hitters!A12 -> 63.931151 | C13: 73 | D13: 1 | E13: 1 | F13: Sanchez, Angel | G13: LF | H13: Hitter | I13: high_school | J13: Looking to sign. Will sign for slot money.
A14: =B14*D14*E14 -> 63.420024 | B14: =Pitchers!A13 -> 63.420024 | C14: 68 | D14: 1 | E14: 1 | F14: Reed, Walt | G14: P | H14: Pitcher | I14: high_school | J14: Looking to be drafted in the first five rounds. If not, he'll probably accept a scholarship to play DI college baseball.
A15: =B15*D15*E15 -> 63.340404 | B15: =Pitchers!A12 -> 63.340404 | C15: 66 | D15: 1 | E15: 1 | F15: Pena, Juan | G15: P | H15: Pitcher | I15: high_school | J15: Looking to sign. Will sign for slot money.
A16: =B16*D16*E16 -> 62.680297 | B16: =Hitters!A13 -> 62.680297 | C16: 80 | D16: 1 | E16: 1 | F16: Arguelles, Arquimedes | G16: 2B | H16: Hitter | I16: high_school | J16: Looking to sign. Will sign for slot money.
A17: =B17*D17*E17 -> 61.737476 | B17: =Hitters!A14 -> 68.597196 | C17: 73 | D17: 1 | E17: 0.9 | F17: Finnegan, Johermyn | G17: SS | H17: Hitter | I17: high_school | J17: May sign if the deal is right. Has been offered several scholarships to play college baseball at a DI school.
A18: =B18*D18*E18 -> 60.439092 | B18: =Hitters!A15 -> 60.439092 | C18: 74 | D18: 1 | E18: 1 | F18: Nieves, Julio | G18: LF | H18: Hitter | I18: high_school | J18: Looking to sign. Will sign for slot money.
A19: =B19*D19*E19 -> 60.171612 | B19: =Hitters!A16 -> 66.857347 | C19: 61 | D19: 1 | E19: 0.9 | F19: Cruz, Yamid | G19: 2B | H19: Hitter | I19: high_school | J19: Looking to be drafted in the first round. If not, he'll probably accept a scholarship to play DI college baseball.
A20: =B20*D20*E20 -> 58.405511 | B20: =Hitters!A17 -> 73.006889 | C20: 85 | D20: 1 | E20: 0.8 | F20: Duchscherer, Bobby Joe | G20: 2B | H20: Hitter | I20: high_school | J20: Undecided. He is also being scouted to play pro hockey.
A21: =B21*D21*E21 -> 58.245668 | B21: =Pitchers!A14 -> 58.245668 | C21: 68 | D21: 1 | E21: 1 | F21: Diaz, Charlie | G21: P | H21: Pitcher | I21: high_school | J21: Looking to sign. Will sign for slot money.
A22: =B22*D22*E22 -> 57.828153 | B22: =Pitchers!A15 -> 57.828153 | C22: 60 | D22: 1 | E22: 1 | F22: Sanders, Joe | G22: P | H22: Pitcher | I22: high_school | J22: Looking to sign. Will sign for slot money.
A23: =B23*D23*E23 -> 55.804694 | B23: =Hitters!A18 -> 55.804694 | C23: 67 | D23: 1 | E23: 1 | F23: Morris, Dillon | G23: SS | H23: Hitter | I23: high_school | J23: Looking to sign. Will sign for slot money.
A24: =B24*D24*E24 -> 55.454913 | B24: =Hitters!A19 -> 69.318641 | C24: 76 | D24: 1 | E24: 0.8 | F24: Soriano, Garret | G24: SS | H24: Hitter | I24: high_school | J24: Undecided. He has scholarships on the table to play DI college football.
A25: =B25*D25*E25 -> 54.418216 | B25: =Hitters!A20 -> 60.464684 | C25: 72 | D25: 1 | E25: 0.9 | F25: Melendez, Renato | G25: DH | H25: Hitter | I25: high_school | J25: May sign if the deal is right. Has been offered several scholarships to play college baseball at a DI school.
A26: =B26*D26*E26 -> 54.240043 | B26: =Hitters!A21 -> 54.240043 | C26: 61 | D26: 1 | E26: 1 | F26: Perez, Phillip | G26: 3B | H26: Hitter | I26: high_school | J26: Looking to sign. Will sign for slot money.
A27: =B27*D27*E27 -> 53.846715 | B27: =Hitters!A22 -> 53.846715 | C27: 61 | D27: 1 | E27: 1 | F27: Estrada, Midre | G27: SS | H27: Hitter | I27: high_school | J27: Looking to sign. Will sign for slot money.
A28: =B28*D28*E28 -> 53.009116 | B28: =Pitchers!A16 -> 53.009116 | C28: 65 | D28: 1 | E28: 1 | F28: Peguero, Tony | G28: P | H28: Pitcher | I28: high_school | J28: Looking to sign. Will sign for slot money.
A29: =B29*D29*E29 -> 52.672664 | B29: =Pitchers!A17 -> 68.317333 | C29: 66 | D29: 0.771 | E29: 1 | F29: Cedeno, Mateo | G29: P | H29: Pitcher | I29: college | J29: Looking to sign. Will sign for slot money.
A30: =B30*D30*E30 -> 51.82551 | B30: =Pitchers!A18 -> 51.82551 | C30: 58 | D30: 1 | E30: 1 | F30: Guzman, Geronimo | G30: P | H30: Pitcher | I30: high_school | J30: Looking to sign. Will sign for slot money.
A31: =B31*D31*E31 -> 51.812048 | B31: =Hitters!A23 -> 51.812048 | C31: 66 | D31: 1 | E31: 1 | F31: Espinosa, Benito | G31: SS | H31: Hitter | I31: high_school | J31: Looking to sign. Will sign for slot money.
A32: =B32*D32*E32 -> 51.714383 | B32: =Hitters!A24 -> 51.714383 | C32: 58 | D32: 1 | E32: 1 | F32: Springer, Tony | G32: RF | H32: Hitter | I32: high_school | J32: Looking to sign. Will sign for slot money.
A33: =B33*D33*E33 -> 51.360099 | B33: =Pitchers!A19 -> 73.37157 | C33: 74 | D33: 1 | E33: 0.7 | F33: Cressend, Walt | G33: P | H33: Pitcher | I33: high_school | J33: Probably won't sign. He's got his heart set on going to college.
A34: =B34*D34*E34 -> 51.188507 | B34: =Pitchers!A20 -> 51.188507 | C34: 64 | D34: 1 | E34: 1 | F34: Mitchell, Aaron | G34: P | H34: Pitcher | I34: high_school | J34: Looking to sign. Will sign for slot money.
A35: =B35*D35*E35 -> 49.184995 | B35: =Pitchers!A21 -> 61.481244 | C35: 71 | D35: 1 | E35: 0.8 | F35: Pena, Gregor | G35: P | H35: Pitcher | I35: high_school | J35: Undecided. He has scholarships on the table to play DI college football.
A36: =B36*D36*E36 -> 49.043613 | B36: =Pitchers!A22 -> 49.043613 | C36: 58 | D36: 1 | E36: 1 | F36: Gose, Grady | G36: P | H36: Pitcher | I36: high_school | J36: Looking to sign. Will sign for slot money.
A37: =B37*D37*E37 -> 48.975708 | B37: =Pitchers!A23 -> 48.975708 | C37: 58 | D37: 1 | E37: 1 | F37: Duran, Vidal | G37: P | H37: Pitcher | I37: high_school | J37: Looking to sign. Will sign for slot money.
A38: =B38*D38*E38 -> 48.345808 | B38: =Hitters!A25 -> 48.345808 | C38: 56 | D38: 1 | E38: 1 | F38: Washington, Cy | G38: DH | H38: Hitter | I38: high_school | J38: Looking to sign. Will sign for slot money.
A39: =B39*D39*E39 -> 48.301433 | B39: =Hitters!A26 -> 48.301433 | C39: 64 | D39: 1 | E39: 1 | F39: Stratton, Keyvius | G39: C | H39: Hitter | I39: high_school | J39: Looking to sign. Will sign for slot money.
A40: =B40*D40*E40 -> 48.298891 | B40: =Pitchers!A24 -> 48.298891 | C40: 60 | D40: 1 | E40: 1 | F40: Maradona, Wilin | G40: P | H40: Pitcher | I40: high_school | J40: Looking to sign. Will sign for slot money.
A41: =B41*D41*E41 -> 48.033574 | B41: =Pitchers!A26 -> 48.033574 | C41: 58 | D41: 1 | E41: 1 | F41: Fleming, Hal | G41: P | H41: Pitcher | I41: high_school | J41: Looking to sign. Will sign for slot money.
A42: =B42*D42*E42 -> 47.84507 | B42: =Hitters!A27 -> 47.84507 | C42: 57 | D42: 1 | E42: 1 | F42: Newson, Albert | G42: 2B | H42: Hitter | I42: high_school | J42: Looking to sign. Will sign for slot money.
A43: =B43*D43*E43 -> 47.783302 | B43: =Hitters!A28 -> 47.783302 | C43: 53 | D43: 1 | E43: 1 | F43: Machi, Albert | G43: RF | H43: Hitter | I43: high_school | J43: Looking to sign. Will sign for slot money.
A44: =B44*D44*E44 -> 47.623922 | B44: =Pitchers!A25 -> 47.623922 | C44: 53 | D44: 1 | E44: 1 | F44: Escalona, Alfredo | G44: P | H44: Pitcher | I44: high_school | J44: Looking to sign. Will sign for slot money.
A45: =B45*D45*E45 -> 47.536679 | B45: =Hitters!A29 -> 61.655874 | C45: 76 | D45: 0.771 | E45: 1 | F45: Charles, Fred | G45: 1B | H45: Hitter | I45: college | J45: Looking to sign. Will sign for slot money.
A46: =B46*D46*E46 -> 46.326176 | B46: =Hitters!A30 -> 60.085831 | C46: 67 | D46: 0.771 | E46: 1 | F46: Burch, Clint | G46: LF | H46: Hitter | I46: college | J46: Looking to sign. Will sign for slot money.
A47: =B47*D47*E47 -> 46.245559 | B47: =Pitchers!A27 -> 57.806949 | C47: 60 | D47: 1 | E47: 0.8 | F47: Christenson, Darrin | G47: P | H47: Pitcher | I47: high_school | J47: Undecided. He is also being scouted to play pro hockey.
A48: =B48*D48*E48 -> 45.863593 | B48: =Hitters!A31 -> 45.863593 | C48: 60 | D48: 1 | E48: 1 | F48: Diaz, Pedro | G48: 2B | H48: Hitter | I48: high_school | J48: Looking to sign. Will sign for slot money.
A49: =B49*D49*E49 -> 45.863114 | B49: =Pitchers!A29 -> 50.959015 | C49: 64 | D49: 1 | E49: 0.9 | F49: Coggin, Dan | G49: P | H49: Pitcher | I49: high_school | J49: May sign if the deal is right. Has been offered several scholarships to play college baseball at a DI school.
A50: =B50*D50*E50 -> 45.781395 | B50: =Pitchers!A28 -> 59.379242 | C50: 67 | D50: 0.771 | E50: 1 | F50: Almanza, Magglio | G50: P | H50: Pitcher | I50: college | J50: Looking to sign. Will sign for slot money.
A51: =B51*D51*E51 -> 45.067564 | B51: =Pitchers!A30 -> 45.067564 | C51: 55 | D51: 1 | E51: 1 | F51: Torres, Wilfredo | G51: P | H51: Pitcher | I51: high_school | J51: Looking to sign. Will sign for slot money.
A52: =B52*D52*E52 -> 44.605689 | B52: =Pitchers!A31 -> 44.605689 | C52: 52 | D52: 1 | E52: 1 | F52: Stein, Quinton | G52: P | H52: Pitcher | I52: high_school | J52: Looking to sign. Will sign for slot money.
A53: =B53*D53*E53 -> 42.821038 | B53: =Hitters!A32 -> 42.821038 | C53: 54 | D53: 1 | E53: 1 | F53: Coyle, Dan | G53: 1B | H53: Hitter | I53: high_school | J53: Looking to sign. Will sign for slot money.
A54: =B54*D54*E54 -> 42.542102 | B54: =Pitchers!A32 -> 47.269003 | C54: 60 | D54: 1 | E54: 0.9 | F54: Brooks, Trevor | G54: P | H54: Pitcher | I54: high_school | J54: May sign if the deal is right. Has been offered several scholarships to play college baseball at a DI school.
A55: =B55*D55*E55 -> 42.168468 | B55: =Pitchers!A33 -> 46.853854 | C55: 55 | D55: 1 | E55: 0.9 | F55: Bagley, Taylor | G55: P | H55: Pitcher | I55: high_school | J55: May sign if the deal is right. Has been offered several scholarships to play college baseball at a DI school.
A56: =B56*D56*E56 -> 41.65158 | B56: =Pitchers!A34 -> 41.65158 | C56: 53 | D56: 1 | E56: 1 | F56: Roberts, Dewey | G56: P | H56: Pitcher | I56: high_school | J56: Looking to sign. Will sign for slot money.
A57: =B57*D57*E57 -> 41.301462 | B57: =Pitchers!A35 -> 45.890513 | C57: 59 | D57: 1 | E57: 0.9 | F57: Lugo, Riccio | G57: P | H57: Pitcher | I57: high_school | J57: Looking to be drafted in the first round. If not, he'll probably accept a scholarship to play DI college baseball.
A58: =B58*D58*E58 -> 40.991416 | B58: =Pitchers!A36 -> 53.166557 | C58: 56 | D58: 0.771 | E58: 1 | F58: Pina, Wally | G58: P | H58: Pitcher | I58: college | J58: Looking to sign. Will sign for slot money.
A59: =B59*D59*E59 -> 40.975238 | B59: =Hitters!A33 -> 53.145575 | C59: 67 | D59: 0.771 | E59: 1 | F59: Valentin, Renato | G59: RF | H59: Hitter | I59: college | J59: Looking to sign. Will sign for slot money.
A60: =B60*D60*E60 -> 40.558927 | B60: =Pitchers!A37 -> 45.065475 | C60: 51 | D60: 1 | E60: 0.9 | F60: Watson, Albert | G60: P | H60: Pitcher | I60: high_school | J60: May sign if the deal is right. Has been offered several scholarships to play college baseball at a DI school.
A61: =B61*D61*E61 -> 40.556357 | B61: =Pitchers!A38 -> 57.937653 | C61: 69 | D61: 1 | E61: 0.7 | F61: Lowry, Gerald | G61: P | H61: Pitcher | I61: high_school | J61: Probably won't sign. He's got his heart set on going to college.
A62: =B62*D62*E62 -> 40.439929 | B62: =Hitters!A34 -> 40.439929 | C62: 58 | D62: 1 | E62: 1 | F62: Martinson, Frank | G62: CF | H62: Hitter | I62: high_school | J62: Looking to sign. Will sign for slot money.
A63: =B63*D63*E63 -> 40.418847 | B63: =Hitters!A35 -> 40.418847 | C63: 56 | D63: 1 | E63: 1 | F63: Ellis, Richard | G63: SS | H63: Hitter | I63: high_school | J63: Looking to sign. Will sign for slot money.
A64: =B64*D64*E64 -> 39.949601 | B64: =Hitters!A36 -> 44.388446 | C64: 56 | D64: 1 | E64: 0.9 | F64: Mills, Dee | G64: LF | H64: Hitter | I64: high_school | J64: May sign if the deal is right. Has been offered several scholarships to play college baseball at a DI school.
A65: =B65*D65*E65 -> 39.912316 | B65: =Pitchers!A39 -> 51.766947 | C65: 53 | D65: 0.771 | E65: 1 | F65: LaHair, Jed | G65: P | H65: Pitcher | I65: college | J65: Looking to sign. Will sign for slot money.
A66: =B66*D66*E66 -> 39.812983 | B66: =Hitters!A37 -> 39.812983 | C66: 45 | D66: 1 | E66: 1 | F66: Kile, Elvis | G66: DH | H66: Hitter | I66: high_school | J66: Looking to sign. Will sign for slot money.
A67: =B67*D67*E67 -> 39.718166 | B67: =Hitters!A38 -> 39.718166 | C67: 53 | D67: 1 | E67: 1 | F67: Ellis, Donn | G67: SS | H67: Hitter | I67: high_school | J67: Looking to sign. Will sign for slot money.
A68: =B68*D68*E68 -> 38.980859 | B68: =Hitters!A39 -> 38.980859 | C68: 54 | D68: 1 | E68: 1 | F68: Arroyo, Alex | G68: 2B | H68: Hitter | I68: high_school | J68: Looking to sign. Will sign for slot money.
A69: =B69*D69*E69 -> 38.890563 | B69: =Hitters!A40 -> 43.211737 | C69: 54 | D69: 1 | E69: 0.9 | F69: Kinney, Claudio | G69: DH | H69: Hitter | I69: high_school | J69: May sign if the deal is right. Has been offered several scholarships to play college baseball at a DI school.
A70: =B70*D70*E70 -> 38.845449 | B70: =Hitters!A41 -> 43.16161 | C70: 57 | D70: 1 | E70: 0.9 | F70: Holmberg, Lonnie | G70: RF | H70: Hitter | I70: high_school | J70: May sign if the deal is right. Has been offered several scholarships to play college baseball at a DI school.
A71: =B71*D71*E71 -> 38.844868 | B71: =Hitters!A42 -> 38.844868 | C71: 46 | D71: 1 | E71: 1 | F71: Herndon, Mo | G71: DH | H71: Hitter | I71: high_school | J71: Looking to sign. Will sign for slot money.
A72: =B72*D72*E72 -> 38.756671 | B72: =Hitters!A43 -> 50.268056 | C72: 65 | D72: 0.771 | E72: 1 | F72: Bowden, Eric | G72: DH | H72: Hitter | I72: college | J72: Looking to sign. Will sign for slot money.
A73: =B73*D73*E73 -> 38.680191 | B73: =Pitchers!A40 -> 38.680191 | C73: 50 | D73: 1 | E73: 1 | F73: Flande, Albert | G73: P | H73: Pitcher | I73: high_school | J73: Looking to sign. Will sign for slot money.
A74: =B74*D74*E74 -> 38.670323 | B74: =Hitters!A44 -> 38.670323 | C74: 49 | D74: 1 | E74: 1 | F74: Singleton, Milt | G74: LF | H74: Hitter | I74: high_school | J74: Looking to sign. Will sign for slot money.
A75: =B75*D75*E75 -> 38.597771 | B75: =Pitchers!A41 -> 42.886412 | C75: 53 | D75: 1 | E75: 0.9 | F75: Garcia, Thurman | G75: P | H75: Pitcher | I75: high_school | J75: May sign if the deal is right. Has been offered several scholarships to play college baseball at a DI school.
A76: =B76*D76*E76 -> 38.101313 | B76: =Hitters!A45 -> 42.334793 | C76: 55 | D76: 1 | E76: 0.9 | F76: Murray, J.B. | G76: RF | H76: Hitter | I76: high_school | J76: May sign if the deal is right. Has been offered several scholarships to play college baseball at a DI school.
A77: =B77*D77*E77 -> 38.059601 | B77: =Hitters!A46 -> 38.059601 | C77: 52 | D77: 1 | E77: 1 | F77: Henley, Thomas | G77: 1B | H77: Hitter | I77: high_school | J77: Looking to sign. Will sign for slot money.
A78: =B78*D78*E78 -> 37.87664 | B78: =Hitters!A47 -> 37.87664 | C78: 53 | D78: 1 | E78: 1 | F78: German, Walter | G78: 1B | H78: Hitter | I78: high_school | J78: Looking to sign. Will sign for slot money.
A79: =B79*D79*E79 -> 37.533397 | B79: =Pitchers!A42 -> 46.916746 | C79: 57 | D79: 1 | E79: 0.8 | F79: Krill, Chris | G79: P | H79: Pitcher | I79: high_school | J79: Undecided. He has scholarships on the table to play DI college football.
A80: =B80*D80*E80 -> 37.485205 | B80: =Pitchers!A43 -> 37.485205 | C80: 49 | D80: 1 | E80: 1 | F80: Pearson, Fred | G80: P | H80: Pitcher | I80: high_school | J80: Looking to sign. Will sign for slot money.
A81: =B81*D81*E81 -> 37.471364 | B81: =Hitters!A48 -> 41.634849 | C81: 53 | D81: 1 | E81: 0.9 | F81: Nady, Orval | G81: 1B | H81: Hitter | I81: high_school | J81: May sign if the deal is right. Has been offered several scholarships to play college baseball at a DI school.
A82: =B82*D82*E82 -> 37.334177 | B82: =Hitters!A49 -> 37.334177 | C82: 51 | D82: 1 | E82: 1 | F82: Darwin, Gerald | G82: DH | H82: Hitter | I82: high_school | J82: Looking to sign. Will sign for slot money.
A83: =B83*D83*E83 -> 37.291019 | B83: =Pitchers!A45 -> 41.434465 | C83: 49 | D83: 1 | E83: 0.9 | F83: Harris, Clint | G83: P | H83: Pitcher | I83: high_school | J83: May sign if the deal is right. Has been offered several scholarships to play college baseball at a DI school.
A84: =B84*D84*E84 -> 37.11635 | B84: =Hitters!A50 -> 48.140532 | C84: 56 | D84: 0.771 | E84: 1 | F84: Reddick, Calvin | G84: DH | H84: Hitter | I84: college | J84: Looking to sign. Will sign for slot money.
A85: =B85*D85*E85 -> 37.11324 | B85: =Pitchers!A44 -> 37.11324 | C85: 41 | D85: 1 | E85: 1 | F85: Newman, Kevin | G85: P | H85: Pitcher | I85: high_school | J85: Looking to sign. Will sign for slot money.
A86: =B86*D86*E86 -> 36.82161 | B86: =Hitters!A51 -> 36.82161 | C86: 48 | D86: 1 | E86: 1 | F86: Sojo, Jose | G86: 1B | H86: Hitter | I86: high_school | J86: Looking to sign. Will sign for slot money.
A87: =B87*D87*E87 -> 36.237747 | B87: =Hitters!A52 -> 36.237747 | C87: 55 | D87: 1 | E87: 1 | F87: Smyly, Shelley | G87: 2B | H87: Hitter | I87: high_school | J87: Looking to sign. Will sign for slot money.
A88: =B88*D88*E88 -> 36.230768 | B88: =Hitters!A53 -> 36.230768 | C88: 57 | D88: 1 | E88: 1 | F88: Booker, Jason | G88: 2B | H88: Hitter | I88: high_school | J88: Looking to sign. Will sign for slot money.
A89: =B89*D89*E89 -> 36.139527 | B89: =Hitters!A54 -> 36.139527 | C89: 50 | D89: 1 | E89: 1 | F89: Lowe, Phillippe | G89: LF | H89: Hitter | I89: high_school | J89: Looking to sign. Will sign for slot money.
A90: =B90*D90*E90 -> 35.146494 | B90: =Pitchers!A46 -> 35.146494 | C90: 42 | D90: 1 | E90: 1 | F90: Locke, Hank | G90: P | H90: Pitcher | I90: high_school | J90: Looking to sign. Will sign for slot money.
A91: =B91*D91*E91 -> 34.814066 | B91: =Hitters!A55 -> 43.517583 | C91: 60 | D91: 1 | E91: 0.8 | F91: Turley, Ernie | G91: RF | H91: Hitter | I91: high_school | J91: Undecided. He has scholarships on the table to play DI college basketball.
A92: =B92*D92*E92 -> 34.277676 | B92: =Pitchers!A47 -> 44.458723 | C92: 56 | D92: 0.771 | E92: 1 | F92: Owen, Juan | G92: P | H92: Pitcher | I92: college | J92: Looking to sign. Will sign for slot money.
A93: =B93*D93*E93 -> 33.967137 | B93: =Hitters!A56 -> 55.069936 | C93: 66 | D93: 0.771 | E93: 0.8 | F93: Maggi, Archie | G93: 2B | H93: Hitter | I93: college | J93: Undecided. He is also being scouted to play professional basketball.
A94: =B94*D94*E94 -> 33.964317 | B94: =Pitchers!A48 -> 44.052292 | C94: 61 | D94: 0.771 | E94: 1 | F94: Li, Endy | G94: P | H94: Pitcher | I94: college | J94: Looking to sign. Will sign for slot money.
A95: =B95*D95*E95 -> 33.853282 | B95: =Pitchers!A49 -> 33.853282 | C95: 41 | D95: 1 | E95: 1 | F95: Brasier, Jacob | G95: P | H95: Pitcher | I95: high_school | J95: Looking to sign. Will sign for slot money.
A96: =B96*D96*E96 -> 33.839121 | B96: =Hitters!A57 -> 33.839121 | C96: 44 | D96: 1 | E96: 1 | F96: Dodd, Tucker | G96: 2B | H96: Hitter | I96: high_school | J96: Looking to sign. Will sign for slot money.
A97: =B97*D97*E97 -> 33.580757 | B97: =Hitters!A58 -> 37.311952 | C97: 46 | D97: 1 | E97: 0.9 | F97: Gunderson, Leo | G97: SS | H97: Hitter | I97: high_school | J97: May sign if the deal is right. Has been offered several scholarships to play college baseball at a DI school.
A98: =B98*D98*E98 -> 33.118087 | B98: =Hitters!A59 -> 33.118087 | C98: 45 | D98: 1 | E98: 1 | F98: Lyon, Sal | G98: RF | H98: Hitter | I98: high_school | J98: Looking to sign. Will sign for slot money.
A99: =B99*D99*E99 -> 32.994816 | B99: =Hitters!A60 -> 36.660907 | C99: 56 | D99: 1 | E99: 0.9 | F99: Lawrence, Davy | G99: DH | H99: Hitter | I99: high_school | J99: May sign if the deal is right. Has been offered several scholarships to play college baseball at a DI school.
A100: =B100*D100*E100 -> 32.87164 | B100: =Hitters!A61 -> 36.524044 | C100: 49 | D100: 1 | E100: 0.9 | F100: Daniels, Darryl | G100: 2B | H100: Hitter | I100: high_school | J100: May sign if the deal is right. Has been offered several scholarships to play college baseball at a DI school.
...
